Workbook

Sheet Jan
B1: Dia | C1: Lojas | D1: Faturamento dia | E1: Não pago dia | F1: Recebido dia | G1: Não pago Acumulado | H1: Peças | I1: Dia | J1: Lojas | K1: Faturamento | L1: Não pago dia | M1: Recebido dia | N1: Não pago Acumulado | O1: Peças | P1: Dia | Q1: Lojas | R1: Faturamento | S1: Não pago dia | T1: Recebido dia | U1: Não pago Acumulado | V1: Peças | W1: Dia | X1: Lojas | Y1: Faturamento | Z1: Não pago dia | AA1: Recebido dia | AB1: Não pago Acumulado | AC1: Peças | AD1: Dia | AE1: Lojas | AF1: Faturamento | AG1: Não pago dia | AH1: Recebido dia | AI1: Não pago Acumulado | AJ1: Peças | AM1: Lojas | AN1: Faturamento | AO1: Não pago dia | AP1: Recebido | AQ1: Peças
A2: Segunda-feira | C2: Lago Norte | I2: 45662 | J2: Lago Norte | K2: 1111.6 | L2: 267.7 | M2: 843.9 | N2: 2401.14 | O2: 42 | P2: 45669 | Q2: Lago Norte | R2: 907.3 | S2: 0 | T2: 1065.79 | U2: 1003.75 | V2: 29 | W2: 45676 | X2: Lago Norte | Y2: =848.6-36 -> 812.6 | Z2: 0 | AA2: 1415.35 | AB2: 597 | AC2: 35 | AD2: 45683 | AE2: Lago Norte | AF2: 1510.1 | AG2: 41.2 | AH2: 1594.9 | AI2: 1009.2 | AJ2: 49 | AL2: Faturamento Total das Segundas-feiras | AM2: Lago Norte | AN2: =D2+K2+R2+Y2+AF2 -> 4341.6 | AO2: =E2+L2+S2+Z2+AG2 -> 308.9 | AP2: =F2+M2+T2+AA2+AH2 -> 4919.94 | AQ2: =H2+O2+V2+AC2+AJ2 -> 155
C3: 202 Norte | J3: 202 Norte | K3: 1787 | L3: 267 | M3: 1770.9 | N3: 813.7 | O3: 47 | Q3: 202 Norte | R3: 316.9 | S3: 184 | T3: 132.9 | U3: 1423.6 | V3: 23 | X3: 202 Norte | Y3: 841 | Z3: 18 | AA3: 823 | AB3: 1401.5 | AC3: 46 | AE3: 202 Norte | AF3: 1543.8 | AG3: 1127.8 | AH3: 470.9 | AI3: 2626.4 | AJ3: 73 | AM3: 202 Norte | AN3: =D3+K3+R3+Y3+AF3 -> 4488.7 | AO3: =E3+L3+S3+Z3+AG3 -> 1596.8 | AP3: =F3+M3+T3+AA3+AH3 -> 3197.7 | AQ3: =H3+O3+V3+AC3+AJ3 -> 189
C4: 213 / Sof | J4: 213 / Sof | Q4: 213 Norte | X4: 213 Norte | AE4: 213 Norte | AM4: 213 Norte | AN4: =D4+K4+R4+Y4+AF4 -> 0 | AO4: =E4+L4+S4+Z4+AG4 -> 0 | AP4: =F4+M4+T4+AA4+AH4 -> 0 | AQ4: =H4+O4+V4+AC4+AJ4 -> 0
C5: 307 Norte | J5: 307 Norte | K5: 2497 | L5: 172 | M5: 2949.9 | N5: 6258.53 | O5: 83 | Q5: 307 Norte | R5: 3286.61 | S5: 1090.4 | T5: 2196.21 | U5: 6092.57 | V5: 93 | X5: 307 Norte | Y5: 2219.52 | Z5: 435.11 | AA5: 2059.41 | AB5: 5791.48 | AC5: 93 | AE5: 307 Norte | AF5: 3496.62 | AG5: 343.95 | AH5: 3420.67 | AI5: 6553.03 | AJ5: 119 | AM5: 307 Norte | AN5: =D5+K5+R5+Y5+AF5 -> 11499.75 | AO5: =E5+L5+S5+Z5+AG5 -> 2041.46 | AP5: =F5+M5+T5+AA5+AH5 -> 10626.19 | AQ5: =H5+O5+V5+AC5+AJ5 -> 388
C6: 313 Norte | J6: 313 Norte | K6: 2004.9 | L6: 0 | M6: 2004.9 | N6: 1295.9 | O6: 79 | Q6: 313 Norte | R6: 930 | S6: 0 | T6: 970 | U6: 1044.9 | V6: 27 | X6: 313 Norte | Y6: 1937.6 | Z6: 0 | AA6: 1937.6 | AB6: 1389.35 | AC6: 62 | AE6: 313 Norte | AF6: 1482.7 | AG6: 0 | AH6: 1482.7 | AI6: 1674.35 | AJ6: 53 | AM6: 313 Norte | AN6: =D6+K6+R6+Y6+AF6 -> 6355.2 | AO6: =E6+L6+S6+Z6+AG6 -> 0 | AP6: =F6+M6+T6+AA6+AH6 -> 6395.2 | AQ6: =H6+O6+V6+AC6+AJ6 -> 221
C7: 314 Sul | J7: 314 Sul | K7: 0 | L7: 0 | M7: 0 | N7: 584.7 | O7: 11 | Q7: 314 Sul | U7: 384.7 | X7: 314 Sul | AB7: 384.7 | AE7: 314 Sul | AM7: 314 Sul | AN7: =D7+K7+R7+Y7+AF7 -> 0 | AO7: =E7+L7+S7+Z7+AG7 -> 0 | AP7: =F7+M7+T7+AA7+AH7 -> 0 | AQ7: =H7+O7+V7+AC7+AJ7 -> 11
C8: Sudoeste | J8: Sudoeste | K8: 729.6 | L8: 255.8 | M8: 473.8 | N8: 2380.24 | O8: 30 | Q8: Sudoeste | R8: 2305 | S8: 490 | T8: 1865 | U8: 2737.34 | V8: 74 | X8: Sudoeste | Y8: 1278.9 | Z8: 233.9 | AA8: 1409 | AB8: 2516.74 | AC8: 49 | AE8: Sudoeste | AF8: 1279.8 | AG8: 462.8 | AH8: 1262.9 | AI8: 2665.59 | AJ8: 91 | AM8: Sudoeste | AN8: =D8+K8+R8+Y8+AF8 -> 5593.3 | AO8: =E8+L8+S8+Z8+AG8 -> 1442.5 | AP8: =F8+M8+T8+AA8+AH8 -> 5010.7 | AQ8: =H8+O8+V8+AC8+AJ8 -> 244
C9: Noroeste | J9: Noroeste | K9: 2932.95 | L9: 365.9 | M9: 3138.85 | N9: 5895.06 | O9: 121 | Q9: Noroeste | R9: 3576.8 | S9: 371.7 | T9: 3037.7 | U9: 6519.73 | V9: 125 | X9: Noroeste | Y9: 4230.57 | Z9: 529 | AA9: 4981.47 | AB9: 6080.83 | AC9: 116 | AE9: Noroeste | AF9: 3715.88 | AG9: 322.28 | AH9: 3634.4 | AI9: 6189.11 | AJ9: 141 | AM9: Noroeste | AN9: =D9+K9+R9+Y9+AF9 -> 14456.2 | AO9: =E9+L9+S9+Z9+AG9 -> 1588.88 | AP9: =F9+M9+T9+AA9+AH9 -> 14792.42 | AQ9: =H9+O9+V9+AC9+AJ9 -> 503
C10: Total: | D10: =D2+D3+D4+D5+D6+D7+D8+D9 -> 0 | E10: =E2+E3+E4+E5+E6+E7+E8+E9 -> 0 | F10: =F2+F3+F4+F5+F6+F7+F8+F9 -> 0 | G10: =G2+G3+G4+G5+G6+G7+G8+G9 -> 0 | H10: =H2+H3+H4+H5+H6+H7+H8+H9 -> 0 | J10: Total: | K10: =K2+K3+K4+K5+K6+K7+K8+K9 -> 11063.05 | L10: =L2+L3+L4+L5+L6+L7+L8+L9 -> 1328.4 | M10: =M2+M3+M4+M5+M6+M7+M8+M9 -> 11182.25 | N10: =N2+N3+N4+N5+N6+N7+N8+N9 -> 19629.27 | O10: =O2+O3+O4+O5+O6+O7+O8+O9 -> 413 | Q10: Total: | R10: =R2+R3+R4+R5+R6+R7+R8+R9 -> 11322.61 | S10: =S2+S3+S4+S5+S6+S7+S8+S9 -> 2136.1 | T10: =T2+T3+T4+T5+T6+T7+T8+T9 -> 9267.6 | U10: =U2+U3+U4+U5+U6+U7+U8+U9 -> 19206.59 | V10: =V2+V3+V4+V5+V6+V7+V8+V9 -> 371 | X10: Total: | Y10: =Y2+Y3+Y4+Y5+Y6+Y7+Y8+Y9 -> 11320.19 | Z10: =Z2+Z3+Z4+Z5+Z6+Z7+Z8+Z9 -> 1216.01 | AA10: =AA2+AA3+AA4+AA5+AA6+AA7+AA8+AA9 -> 12625.83 | AB10: =AB2+AB3+AB4+AB5+AB6+AB7+AB8+AB9 -> 18161.6 | AC10: =AC2+AC3+AC4+AC5+AC6+AC7+AC8+AC9 -> 401 | AE10: Total: | AF10: =AF2+AF3+AF4+AF5+AF6+AF7+AF8+AF9 -> 13028.9 | AG10: =AG2+AG3+AG4+AG5+AG6+AG7+AG8+AG9 -> 2298.03 | AH10: =AH2+AH3+AH4+AH5+AH6+AH7+AH8+AH9 -> 11866.47 | AI10: =AI2+AI3+AI4+AI5+AI6+AI7+AI8+AI9 -> 20717.68 | AJ10: =AJ2+AJ3+AJ4+AJ5+AJ6+AJ7+AJ8+AJ9 -> 526 | AM10: Total: | AN10: =AN2+AN3+AN4+AN5+AN6+AN7+AN8+AN9 -> 46734.75 | AO10: =AO2+AO3+AO4+AO5+AO6+AO7+AO8+AO9 -> 6978.54 | AP10: =AP2+AP3+AP4+AP5+AP6+AP7+AP8+AP9 -> 44942.15 | AQ10: =AQ2+AQ3+AQ4+AQ5+AQ6+AQ7+AQ8+AQ9 -> 1711
C11: Faturado dia real | D11: =D10-E10 -> 0 | J11: Faturado dia real | K11: =K10-L10 -> 9734.65 | Q11: Faturado dia real | R11: =R10-S10 -> 9186.51 | X11: Faturado dia real | Y11: =Y10-Z10 -> 10104.18 | AE11: Faturado dia real | AF11: =AF10-AG10 -> 10730.87 | AM11: Fat. Real | AN11: =AN10-AO10 -> 39756.21
C12: Recebido dia real | D12: =F10-E10 -> 0 | J12: Recebido dia real | K12: =M10-L10 -> 9853.85 | Q12: Recebido dia real | R12: =T10-S10 -> 7131.5 | X12: Recebido dia real | Y12: =AA10-Z10 -> 11409.82 | AE12: Recebido dia real | AF12: =AH10-AG10 -> 9568.44
B13: Dia | C13: Lojas | D13: Faturamento dia | E13: Não pago dia | F13: Recebido dia | G13: Não pago Acumulado | H13: Peças | I13: Dia | J13: Lojas | K13: Faturamento | L13: Não pago dia | M13: Recebido dia | N13: Não pago Acumulado | O13: Peças | P13: Dia | Q13: Lojas | R13: Faturamento | S13: Não pago dia | T13: Recebido dia | U13: Não pago Acumulado | V13: Peças | W13: Dia | X13: Lojas | Y13: Faturamento | Z13: Não pago dia | AA13: Recebido dia | AB13: Não pago Acumulado | AC13: Peças | AD13: Dia | AE13: Lojas | AF13: Faturamento | AG13: Não pago dia | AH13: Recebido dia | AI13: Não pago Acumulado | AJ13: Peças | AM13: Lojas | AN13: Faturamento | AO13: Não pago dia | AP13: Recebido | AQ13: Peças
A14: Terça-feira | C14: Lago Norte | I14: 45663 | J14: Lago Norte | K14: 284 | L14: 0 | M14: 287 | N14: 2401.14 | O14: 16 | P14: 45670 | Q14: Lago Norte | R14: 38.2 | S14: 0 | T14: 38.28 | U14: 1003.75 | V14: 6 | W14: 45677 | X14: Lago Norte | Y14: 807.8 | Z14: 140 | AA14: 667.8 | AB14: 737 | AC14: 29 | AD14: 45684 | AE14: Lago Norte | AF14: 693.5 | AG14: 163 | AH14: 637.7 | AI14: 1065 | AJ14: 37 | AL14: Faturamento Total das Terças-feiras | AM14: Lago Norte | AN14: =D14+K14+R14+Y14+AF14 -> 1823.5 | AO14: =E14+L14+S14+Z14+AG14 -> 303 | AP14: =F14+M14+T14+AA14+AH14 -> 1630.78 | AQ14: =H14+O14+V14+AC14+AJ14 -> 88
C15: 202 Norte | J15: 202 Norte | K15: 199 | L15: 0 | M15: 199 | N15: 813.7 | O15: 7 | Q15: 202 Norte | R15: 179.8 | S15: 139.8 | T15: 156.9 | U15: 1446.5 | V15: 4 | X15: 202 Norte | Y15: 420 | Z15: 96 | AA15: 324 | AB15: 1497.5 | AC15: 17 | AE15: 202 Norte | AF15: 568 | AG15: 68 | AH15: 1086.9 | AI15: 2107.5 | AJ15: 10 | AM15: 202 Norte | AN15: =D15+K15+R15+Y15+AF15 -> 1366.8 | AO15: =E15+L15+S15+Z15+AG15 -> 303.8 | AP15: =F15+M15+T15+AA15+AH15 -> 1766.8 | AQ15: =H15+O15+V15+AC15+AJ15 -> 38
C16: 213 / Sof | J16: 213 / Sof | Q16: 213 Norte | X16: 213 Norte | AE16: 213 Norte | AM16: 213 Norte | AN16: =D16+K16+R16+Y16+AF16 -> 0 | AO16: =E16+L16+S16+Z16+AG16 -> 0 | AP16: =F16+M16+T16+AA16+AH16 -> 0 | AQ16: =H16+O16+V16+AC16+AJ16 -> 0
C17: 307 Norte | J17: 307 Norte | K17: 1066.9 | L17: 132.9 | M17: 934 | N17: 6391.43 | O17: 31 | Q17: 307 Norte | R17: 1717 | S17: 165.6 | T17: 1817.4 | U17: 5992.17 | V17: 74 | X17: 307 Norte | Y17: 2471.7 | Z17: 512.9 | AA17: 2164.8 | AB17: 6098.38 | AC17: 59 | AE17: 307 Norte | AF17: 711.9 | AG17: 94 | AH17: 787.9 | AI17: 6477.03 | AJ17: 36 | AM17: 307 Norte | AN17: =D17+K17+R17+Y17+AF17 -> 5967.5 | AO17: =E17+L17+S17+Z17+AG17 -> 905.4 | AP17: =F17+M17+T17+AA17+AH17 -> 5704.1 | AQ17: =H17+O17+V17+AC17+AJ17 -> 200
C18: 313 Norte | J18: 313 Norte | K18: 1144 | L18: 40 | M18: 1204 | N18: 1235.9 | O18: 65 | Q18: 313 Norte | R18: 2122.25 | S18: 662.35 | T18: 1459.9 | U18: 1707.25 | V18: 99 | X18: 313 Norte | Y18: 1070 | Z18: 132 | AA18: 982 | AB18: 1477.35 | AC18: 52 | AE18: 313 Norte | AF18: 755.8 | AG18: 0 | AH18: 755.8 | AI18: 1674.35 | AJ18: 30 | AM18: 313 Norte | AN18: =D18+K18+R18+Y18+AF18 -> 5092.05 | AO18: =E18+L18+S18+Z18+AG18 -> 834.35 | AP18: =F18+M18+T18+AA18+AH18 -> 4401.7 | AQ18: =H18+O18+V18+AC18+AJ18 -> 246
C19: 314 Sul | J19: 314 Sul | K19: 0 | L19: 0 | M19: 0 | N19: 584.7 | O19: 0 | Q19: 314 Sul | U19: 384.7 | X19: 314 Sul | AE19: 314 Sul | AM19: 314 Sul | AN19: =D19+K19+R19+Y19+AF19 -> 0 | AO19: =E19+L19+S19+Z19+AG19 -> 0 | AP19: =F19+M19+T19+AA19+AH19 -> 0 | AQ19: =H19+O19+V19+AC19+AJ19 -> 0
C20: Sudoeste | J20: Sudoeste | K20: 742.9 | L20: 397 | M20: 387.9 | N20: 2735.24 | O20: 41 | Q20: Sudoeste | R20: 708 | S20: 32 | T20: 980 | U20: 2465.34 | V20: 29 | X20: Sudoeste | Y20: 459.05 | Z20: 113.35 | AA20: 345.7 | AB20: 2630.09 | AC20: 21 | AE20: Sudoeste | AF20: 604.9 | AG20: 177 | AH20: 774.9 | AI20: 2495.59 | AJ20: 18 | AM20: Sudoeste | AN20: =D20+K20+R20+Y20+AF20 -> 2514.85 | AO20: =E20+L20+S20+Z20+AG20 -> 719.35 | AP20: =F20+M20+T20+AA20+AH20 -> 2488.5 | AQ20: =H20+O20+V20+AC20+AJ20 -> 109
C21: Noroeste | J21: Noroeste | K21: 1412.1 | L21: 120.4 | M21: 1493.2 | N21: 5813.96 | O21: 63 | Q21: Noroeste | R21: 1968.5 | S21: 258.8 | T21: 1904.7 | U21: 6583.53 | V21: 96 | X21: Noroeste | Y21: 1581.5 | Z21: 109.7 | AA21: 1753.7 | AB21: 5908.63 | AC21: 97 | AE21: Noroeste | AF21: 2856.5 | AG21: 0 | AH21: 3002.7 | AI21: 5992.31 | AJ21: 116 | AM21: Noroeste | AN21: =D21+K21+R21+Y21+AF21 -> 7818.6 | AO21: =E21+L21+S21+Z21+AG21 -> 488.9 | AP21: =F21+M21+T21+AA21+AH21 -> 8154.3 | AQ21: =H21+O21+V21+AC21+AJ21 -> 372
C22: Total: | D22: =D14+D15+D16+D17+D18+D19+D20+D21 -> 0 | E22: =E14+E15+E16+E17+E18+E19+E20+E21 -> 0 | F22: =F14+F15+F16+F17+F18+F19+F20+F21 -> 0 | G22: =G14+G15+G16+G17+G18+G19+G20+G21 -> 0 | H22: =H14+H15+H16+H17+H18+H19+H20+H21 -> 0 | J22: Total: | K22: =K14+K15+K16+K17+K18+K19+K20+K21 -> 4848.9 | L22: =L14+L15+L16+L17+L18+L19+L20+L21 -> 690.3 | M22: =M14+M15+M16+M17+M18+M19+M20+M21 -> 4505.1 | N22: =N14+N15+N16+N17+N18+N19+N20+N21 -> 19976.07 | O22: =O14+O15+O16+O17+O18+O19+O20+O21 -> 223 | Q22: Total: | R22: =R14+R15+R16+R17+R18+R19+R20+R21 -> 6733.75 | S22: =S14+S15+S16+S17+S18+S19+S20+S21 -> 1258.55 | T22: =T14+T15+T16+T17+T18+T19+T20+T21 -> 6357.18 | U22: =U14+U15+U16+U17+U18+U19+U20+U21 -> 19583.24 | V22: =V14+V15+V16+V17+V18+V19+V20+V21 -> 308 | X22: Total: | Y22: =Y14+Y15+Y16+Y17+Y18+Y19+Y20+Y21 -> 6810.05 | Z22: =Z14+Z15+Z16+Z17+Z18+Z19+Z20+Z21 -> 1103.95 | AA22: =AA14+AA15+AA16+AA17+AA18+AA19+AA20+AA21 -> 6238 | AB22: =AB14+AB15+AB16+AB17+AB18+AB19+AB20+AB21 -> 18348.95 | AC22: =AC14+AC15+AC16+AC17+AC18+AC19+AC20+AC21 -> 275 | AE22: Total: | AF22: =AF14+AF15+AF16+AF17+AF18+AF19+AF20+AF21 -> 6190.6 | AG22: =AG14+AG15+AG16+AG17+AG18+AG19+AG20+AG21 -> 502 | AH22: =AH14+AH15+AH16+AH17+AH18+AH19+AH20+AH21 -> 7045.9 | AI22: =AI14+AI15+AI16+AI17+AI18+AI19+AI20+AI21 -> 19811.78 | AJ22: =AJ14+AJ15+AJ16+AJ17+AJ18+AJ19+AJ20+AJ21 -> 247 | AM22: Total: | AN22: =AN14+AN15+AN16+AN17+AN18+AN19+AN20+AN21 -> 24583.3 | AO22: =AO14+AO15+AO16+AO17+AO18+AO19+AO20+AO21 -> 3554.8 | AP22: =AP14+AP15+AP16+AP17+AP18+AP19+AP20+AP21 -> 24146.18 | AQ22: =AQ14+AQ15+AQ16+AQ17+AQ18+AQ19+AQ20+AQ21 -> 1053
C23: Faturado dia real | D23: =D22-E22 -> 0 | J23: Faturado dia real | K23: =K22-L22 -> 4158.6 | Q23: Faturado dia real | R23: =R22-S22 -> 5475.2 | X23: Faturado dia real | Y23: =Y22-Z22 -> 5706.1 | AE23: Faturado dia real | AF23: =AF22-AG22 -> 5688.6 | AM23: Fat. Real | AN23: =AN22-AO22 -> 21028.5
C24: Recebido dia real | D24: =F22-E22 -> 0 | J24: Recebido dia real | K24: =M22-L22 -> 3814.8 | Q24: Recebido dia real | R24: =T22-S22 -> 5098.63 | X24: Recebido dia real | Y24: =AA22-Z22 -> 5134.05 | AE24: Recebido dia real | AF24: =AH22-AG22 -> 6543.9
B25: Dia | C25: Lojas | D25: Faturamento dia | E25: Não pago dia | F25: Recebido dia | G25: Não pago Acumulado | H25: Peças | I25: Dia | J25: Lojas | K25: Faturamento | L25: Não pago dia | M25: Recebido dia | N25: Não pago Acumulado | O25: Peças | P25: Dia | Q25: Lojas | R25: Faturamento | S25: Não pago dia | T25: Recebido dia | U25: Não pago Acumulado | V25: Peças | W25: Dia | X25: Lojas | Y25: Faturamento | Z25: Não pago dia | AA25: Recebido dia | AB25: Não pago Acumulado | AC25: Peças | AD25: Dia | AE25: Lojas | AF25: Faturamento | AG25: Não pago dia | AH25: Recebido dia | AI25: Não pago Acumulado | AJ25: Peças | AM25: Lojas | AN25: Faturamento | AO25: Não pago dia | AP25: Recebido | AQ25: Peças
A26: Quarta-feira | C26: Lago Norte | I26: 45664 | J26: Lago Norte | K26: 1706.73 | L26: 392.7 | M26: 1314.03 | N26: 2793.84 | O26: 60 | P26: 45671 | Q26: Lago Norte | R26: 1263.8 | S26: 0 | T26: 1263.8 | U26: 1003.75 | V26: 28 | W26: 45678 | X26: Lago Norte | Y26: 935.9 | Z26: 104.9 | AA26: 831 | AB26: 841.9 | AC26: 31 | AD26: 45685 | AE26: Lago Norte | AF26: 889 | AG26: 0 | AH26: 1173 | AI26: 781 | AJ26: 28 | AL26: Faturamento Total das Quartas-feiras | AM26: Lago Norte | AN26: =D26+K26+R26+Y26+AF26 -> 4795.43 | AO26: =E26+L26+S26+Z26+AG26 -> 497.6 | AP26: =F26+M26+T26+AA26+AH26 -> 4581.83 | AQ26: =H26+O26+V26+AC26+AJ26 -> 147
C27: 202 Norte | J27: 202 Norte | K27: 511.9 | L27: 167.9 | M27: 365 | N27: 960.6 | O27: 43 | Q27: 202 Norte | R27: 731 | S27: 73 | T27: 676 | U27: 1501.5 | V27: 45 | X27: 202 Norte | Y27: 374.9 | Z27: 90 | AA27: 284.9 | AB27: 1587.5 | AC27: 20 | AE27: 202 Norte | AF27: 665.8 | AG27: 0 | AH27: 665.8 | AI27: 2107.5 | AJ27: 34 | AM27: 202 Norte | AN27: =D27+K27+R27+Y27+AF27 -> 2283.6 | AO27: =E27+L27+S27+Z27+AG27 -> 330.9 | AP27: =F27+M27+T27+AA27+AH27 -> 1991.7 | AQ27: =H27+O27+V27+AC27+AJ27 -> 142
C28: 213 / Sof | J28: 213 / Sof | Q28: 213 Norte | X28: 213 Norte | AE28: 213 Norte | AM28: 213 Norte | AN28: =D28+K28+R28+Y28+AF28 -> 0 | AO28: =E28+L28+S28+Z28+AG28 -> 0 | AP28: =F28+M28+T28+AA28+AH28 -> 0 | AQ28: =H28+O28+V28+AC28+AJ28 -> 0
C29: 307 Norte | J29: 307 Norte | K29: 1431.18 | L29: 185 | M29: 2073.34 | N29: 5749.27 | O29: 68 | Q29: 307 Norte | R29: 467.7 | S29: 0 | T29: 815.6 | U29: 5644.27 | V29: 27 | X29: 307 Norte | Y29: 2320.95 | Z29: 861.8 | AA29: 1943.55 | AB29: 6475.78 | AC29: 84 | AE29: 307 Norte | AF29: 3410.2 | AG29: 34.9 | AH29: 4782.7 | AI29: 5104.53 | AJ29: 82 | AM29: 307 Norte | AN29: =D29+K29+R29+Y29+AF29 -> 7630.03 | AO29: =E29+L29+S29+Z29+AG29 -> 1081.7 | AP29: =F29+M29+T29+AA29+AH29 -> 9615.19 | AQ29: =H29+O29+V29+AC29+AJ29 -> 261
C30: 313 Norte | J30: 313 Norte | K30: 1106.9 | L30: 0 | M30: 1106.9 | N30: 1235.9 | O30: 47 | Q30: 313 Norte | R30: 1192 | S30: 0 | T30: 1246.9 | U30: 1652.35 | V30: 51 | X30: 313 Norte | Y30: 560.6 | Z30: 119 | AA30: 441.6 | AB30: 1596.35 | AC30: 19 | AE30: 313 Norte | AF30: 1473 | AG30: 110 | AH30: 1363 | AI30: 1784.35 | AJ30: 60 | AM30: 313 Norte | AN30: =D30+K30+R30+Y30+AF30 -> 4332.5 | AO30: =E30+L30+S30+Z30+AG30 -> 229 | AP30: =F30+M30+T30+AA30+AH30 -> 4158.4 | AQ30: =H30+O30+V30+AC30+AJ30 -> 177
C31: 314 Sul | J31: 314 Sul | K31: 0 | L31: 0 | M31: 0 | N31: 584.7 | O31: 10 | Q31: 314 Sul | U31: 384.7 | X31: 314 Sul | AE31: 314 Sul | AM31: 314 Sul | AN31: =D31+K31+R31+Y31+AF31 -> 0 | AO31: =E31+L31+S31+Z31+AG31 -> 0 | AP31: =F31+M31+T31+AA31+AH31 -> 0 | AQ31: =H31+O31+V31+AC31+AJ31 -> 10
C32: Sudoeste | J32: Sudoeste | K32: 756.3 | L32: 50 | M32: 1009.2 | N32: 2482.34 | O32: 21 | Q32: Sudoeste | R32: 505 | S32: 265 | T32: 240 | U32: 2730.34 | V32: 22 | X32: Sudoeste | Y32: 568.8 | Z32: 49 | AA32: 519.8 | AB32: 2679.09 | AC32: 40 | AE32: Sudoeste | AF32: 785.9 | AG32: 30 | AH32: 909.2 | AI32: 2372.29 | AJ32: 28 | AM32: Sudoeste | AN32: =D32+K32+R32+Y32+AF32 -> 2616 | AO32: =E32+L32+S32+Z32+AG32 -> 394 | AP32: =F32+M32+T32+AA32+AH32 -> 2678.2 | AQ32: =H32+O32+V32+AC32+AJ32 -> 111
C33: Noroeste | J33: Noroeste | K33: 1596.7 | L33: 353 | M33: 1989.5 | N33: 5421.16 | O33: 82 | Q33: Noroeste | R33: 1740.7 | S33: 0 | T33: 2102.5 | U33: 6218.73 | V33: 83 | X33: Noroeste | Y33: 3191.05 | Z33: 391.7 | AA33: 3190.65 | AB33: 5909.03 | AC33: 98 | AE33: Noroeste | AF33: 2245.7 | AG33: 304 | AH33: 2221.4 | AI33: 6016.61 | AJ33: 113 | AM33: Noroeste | AN33: =D33+K33+R33+Y33+AF33 -> 8774.15 | AO33: =E33+L33+S33+Z33+AG33 -> 1048.7 | AP33: =F33+M33+T33+AA33+AH33 -> 9504.05 | AQ33: =H33+O33+V33+AC33+AJ33 -> 376
C34: Total: | D34: =D26+D27+D28+D29+D30+D31+D32+D33 -> 0 | E34: =E26+E27+E28+E29+E30+E31+E32+E33 -> 0 | F34: =F26+F27+F28+F29+F30+F31+F32+F33 -> 0 | G34: =G26+G27+G28+G29+G30+G31+G32+G33 -> 0 | H34: =H26+H27+H28+H29+H30+H31+H32+H33 -> 0 | J34: Total: | K34: =K26+K27+K28+K29+K30+K31+K32+K33 -> 7109.71 | L34: =L26+L27+L28+L29+L30+L31+L32+L33 -> 1148.6 | M34: =M26+M27+M28+M29+M30+M31+M32+M33 -> 7857.97 | N34: =N26+N27+N28+N29+N30+N31+N32+N33 -> 19227.81 | O34: =O26+O27+O28+O29+O30+O31+O32+O33 -> 331 | Q34: Total: | R34: =R26+R27+R28+R29+R30+R31+R32+R33 -> 5900.2 | S34: =S26+S27+S28+S29+S30+S31+S32+S33 -> 338 | T34: =T26+T27+T28+T29+T30+T31+T32+T33 -> 6344.8 | U34: =U26+U27+U28+U29+U30+U31+U32+U33 -> 19135.64 | V34: =V26+V27+V28+V29+V30+V31+V32+V33 -> 256 | X34: Total: | Y34: =Y26+Y27+Y28+Y29+Y30+Y31+Y32+Y33 -> 7952.2 | Z34: =Z26+Z27+Z28+Z29+Z30+Z31+Z32+Z33 -> 1616.4 | AA34: =AA26+AA27+AA28+AA29+AA30+AA31+AA32+AA33 -> 7211.5 | AB34: =AB26+AB27+AB28+AB29+AB30+AB31+AB32+AB33 -> 19089.65 | AC34: =AC26+AC27+AC28+AC29+AC30+AC31+AC32+AC33 -> 292 | AE34: Total: | AF34: =AF26+AF27+AF28+AF29+AF30+AF31+AF32+AF33 -> 9469.6 | AG34: =AG26+AG27+AG28+AG29+AG30+AG31+AG32+AG33 -> 478.9 | AH34: =AH26+AH27+AH28+AH29+AH30+AH31+AH32+AH33 -> 11115.1 | AI34: =AI26+AI27+AI28+AI29+AI30+AI31+AI32+AI33 -> 18166.28 | AJ34: =AJ26+AJ27+AJ28+AJ29+AJ30+AJ31+AJ32+AJ33 -> 345 | AM34: Total: | AN34: =AN26+AN27+AN28+AN29+AN30+AN31+AN32+AN33 -> 30431.71 | AO34: =AO26+AO27+AO28+AO29+AO30+AO31+AO32+AO33 -> 3581.9 | AP34: =AP26+AP27+AP28+AP29+AP30+AP31+AP32+AP33 -> 32529.37 | AQ34: =AQ26+AQ27+AQ28+AQ29+AQ30+AQ31+AQ32+AQ33 -> 1224
C35: Faturado dia real | D35: =D34-E34 -> 0 | J35: Faturado dia real | K35: =K34-L34 -> 5961.11 | Q35: Faturado dia real | R35: =R34-S34 -> 5562.2 | X35: Faturado dia real | Y35: =Y34-Z34 -> 6335.8 | AE35: Faturado dia real | AF35: =AF34-AG34 -> 8990.7 | AM35: Fat. Real | AN35: =AN34-AO34 -> 26849.81
C36: Recebido dia real | D36: =F34-E34 -> 0 | J36: Recebido dia real | K36: =M34-L34 -> 6709.37 | Q36: Recebido dia real | R36: =T34-S34 -> 6006.8 | X36: Recebido dia real | Y36: =AA34-Z34 -> 5595.1 | AE36: Recebido dia real | AF36: =AH34-AG34 -> 10636.2
B37: Dia | C37: Lojas | D37: Faturamento dia | E37: Não pago dia | F37: Recebido dia | G37: Não pago Acumulado | H37: Peças | I37: Dia | J37: Lojas | K37: Faturamento | L37: Não pago dia | M37: Recebido dia | N37: Não pago Acumulado | O37: Peças | P37: Dia | Q37: Lojas | R37: Faturamento | S37: Não pago dia | T37: Recebido dia | U37: Não pago Acumulado | V37: Peças | W37: Dia | X37: Lojas | Y37: Faturamento | Z37: Não pago dia | AA37: Recebido dia | AB37: Não pago Acumulado | AC37: Peças | AD37: Dia | AE37: Lojas | AF37: Faturamento | AG37: Não pago dia | AH37: Recebido dia | AI37: Não pago Acumulado | AJ37: Peças | AM37: Lojas | AN37: Faturamento | AO37: Não pago dia | AP37: Recebido | AQ37: Peças
A38: Quinta-feira | B38: 01/01/2025 - Feriado | C38: Lago Norte | I38: 45665 | J38: Lago Norte | K38: 1071.5 | L38: 0 | M38: 1381.3 | N38: 2484.04 | O38: 42 | P38: 45672 | Q38: Lago Norte | R38: 256.7 | S38: 0 | T38: 256.7 | U38: 1003.75 | V38: 6 | W38: 45679 | X38: Lago Norte | Y38: 773 | Z38: 186 | AA38: 587 | AB38: 1027.9 | AC38: 35 | AD38: 45686 | AE38: Lago Norte | AF38: 251 | AG38: 161 | AH38: 90 | AI38: 942 | AJ38: 8 | AL38: Faturamento Total das Quintas-feiras | AM38: Lago Norte | AN38: =D38+K38+R38+Y38+AF38 -> 2352.2 | AO38: =E38+L38+S38+Z38+AG38 -> 347 | AP38: =F38+M38+T38+AA38+AH38 -> 2315 | AQ38: =H38+O38+V38+AC38+AJ38 -> 91
C39: 202 Norte | J39: 202 Norte | K39: 210 | L39: 0 | M39: 231 | N39: 939.6 | O39: 9 | Q39: 202 Norte | R39: 838.56 | S39: 0 | T39: 896.56 | U39: 1443.5 | V39: 34 | X39: 202 Norte | Y39: 450.9 | Z39: 36 | AA39: 466.9 | AB39: 1571.5 | AC39: 12 | AE39: 202 Norte | AF39: 144 | AG39: 60 | AH39: 162 | AI39: 2059.5 | AJ39: 5 | AM39: 202 Norte | AN39: =D39+K39+R39+Y39+AF39 -> 1643.46 | AO39: =E39+L39+S39+Z39+AG39 -> 96 | AP39: =F39+M39+T39+AA39+AH39 -> 1756.46 | AQ39: =H39+O39+V39+AC39+AJ39 -> 60
C40: 213 / Sof | J40: 213 Norte | Q40: 213 Norte | X40: 213 Norte | AE40: 213 Norte | AM40: 213 Norte | AN40: =D40+K40+R40+Y40+AF40 -> 0 | AO40: =E40+L40+S40+Z40+AG40 -> 0 | AP40: =F40+M40+T40+AA40+AH40 -> 0 | AQ40: =H40+O40+V40+AC40+AJ40 -> 0
C41: 307 Norte | J41: 307 Norte | K41: 1699 | L41: 73 | M41: 1967.3 | N41: 5480.47 | O41: 46 | Q41: 307 Norte | R41: 1784.4 | S41: 39 | T41: 1745.4 | U41: 5683.27 | V41: 62 | X41: 307 Norte | Y41: 1783.4 | Z41: 442.8 | AA41: 2057.1 | AB41: 6202.08 | AC41: 68 | AE41: 307 Norte | AF41: 1169.9 | AG41: 1022.9 | AH41: 1019 | AI41: 5255.43 | AJ41: 58 | AM41: 307 Norte | AN41: =D41+K41+R41+Y41+AF41 -> 6436.7 | AO41: =E41+L41+S41+Z41+AG41 -> 1577.7 | AP41: =F41+M41+T41+AA41+AH41 -> 6788.8 | AQ41: =H41+O41+V41+AC41+AJ41 -> 234
C42: 313 Norte | J42: 313 Norte | K42: 809 | L42: 0 | M42: 960 | N42: 1084.9 | O42: 38 | Q42: 313 Norte | R42: 1079.5 | S42: 0 | T42: 1342.5 | U42: 1389.35 | V42: 48 | X42: 313 Norte | Y42: 1321.7 | Z42: 0 | AA42: 1321.7 | AB42: 1596.35 | AC42: 45 | AE42: 313 Norte | AF42: 285 | AG42: 144 | AH42: 141 | AI42: 1928.35 | AJ42: 20 | AM42: 313 Norte | AN42: =D42+K42+R42+Y42+AF42 -> 3495.2 | AO42: =E42+L42+S42+Z42+AG42 -> 144 | AP42: =F42+M42+T42+AA42+AH42 -> 3765.2 | AQ42: =H42+O42+V42+AC42+AJ42 -> 151
C43: 314 Sul | J43: 314 Sul | K43: 0 | L43: 0 | M43: 200 | N43: 384.7 | O43: 0 | Q43: 314 Sul | U43: 384.7 | X43: 314 Sul | AE43: 314 Sul | AM43: 314 Sul | AN43: =D43+K43+R43+Y43+AF43 -> 0 | AO43: =E43+L43+S43+Z43+AG43 -> 0 | AP43: =F43+M43+T43+AA43+AH43 -> 200 | AQ43: =H43+O43+V43+AC43+AJ43 -> 0
C44: Sudoeste | J44: Sudoeste | K44: 695.9 | L44: 0 | M44: 795.9 | N44: 2382.34 | O44: 26 | Q44: Sudoeste | R44: 573.9 | S44: 0 | T44: 733.7 | U44: 2570.54 | V44: 27 | X44: Sudoeste | Y44: 1284.6 | Z44: 219.6 | AA44: 1065 | AB44: 2898.69 | AC44: 34 | AE44: Sudoeste | AF44: 309.9 | AG44: 54 | AH44: 255.9 | AI44: 2426.29 | AJ44: 10 | AM44: Sudoeste | AN44: =D44+K44+R44+Y44+AF44 -> 2864.3 | AO44: =E44+L44+S44+Z44+AG44 -> 273.6 | AP44: =F44+M44+T44+AA44+AH44 -> 2850.5 | AQ44: =H44+O44+V44+AC44+AJ44 -> 97
C45: Noroeste | J45: Noroeste | K45: 1288.7 | L45: 36 | M45: 1379.6 | N45: 5330.26 | O45: 57 | Q45: Noroeste | R45: 2280.6 | S45: 687.8 | T45: 1776.6 | U45: 6722.73 | V45: 85 | X45: Noroeste | Y45: 2510.9 | Z45: 268 | AA45: 2512.9 | AB45: 5872.03 | AC45: 97 | AE45: Noroeste | AF45: 1898.5 | AG45: 366 | AH45: 1653.5 | AI45: 6261.61 | AJ45: 98 | AM45: Noroeste | AN45: =D45+K45+R45+Y45+AF45 -> 7978.7 | AO45: =E45+L45+S45+Z45+AG45 -> 1357.8 | AP45: =F45+M45+T45+AA45+AH45 -> 7322.6 | AQ45: =H45+O45+V45+AC45+AJ45 -> 337
C46: Total: | D46: =D38+D39+D40+D41+D42+D43+D44+D45 -> 0 | E46: =E38+E39+E40+E41+E42+E43+E44+E45 -> 0 | F46: =F38+F39+F40+F41+F42+F43+F44+F45 -> 0 | G46: =G38+G39+G40+G41+G42+G43+G44+G45 -> 0 | H46: =H38+H39+H40+H41+H42+H43+H44+H45 -> 0 | J46: Total: | K46: =K38+K39+K40+K41+K42+K43+K44+K45 -> 5774.1 | L46: =L38+L39+L40+L41+L42+L43+L44+L45 -> 109 | M46: =M38+M39+M40+M41+M42+M43+M44+M45 -> 6915.1 | N46: =N38+N39+N40+N41+N42+N43+N44+N45 -> 18086.31 | O46: =O38+O39+O40+O41+O42+O43+O44+O45 -> 218 | Q46: Total: | R46: =R38+R39+R40+R41+R42+R43+R44+R45 -> 6813.66 | S46: =S38+S39+S40+S41+S42+S43+S44+S45 -> 726.8 | T46: =T38+T39+T40+T41+T42+T43+T44+T45 -> 6751.46 | U46: =U38+U39+U40+U41+U42+U43+U44+U45 -> 19197.84 | V46: =V38+V39+V40+V41+V42+V43+V44+V45 -> 262 | X46: Total: | Y46: =Y38+Y39+Y40+Y41+Y42+Y43+Y44+Y45 -> 8124.5 | Z46: =Z38+Z39+Z40+Z41+Z42+Z43+Z44+Z45 -> 1152.4 | AA46: =AA38+AA39+AA40+AA41+AA42+AA43+AA44+AA45 -> 8010.6 | AB46: =AB38+AB39+AB40+AB41+AB42+AB43+AB44+AB45 -> 19168.55 | AC46: =AC38+AC39+AC40+AC41+AC42+AC43+AC44+AC45 -> 291 | AE46: Total: | AF46: =AF38+AF39+AF40+AF41+AF42+AF43+AF44+AF45 -> 4058.3 | AG46: =AG38+AG39+AG40+AG41+AG42+AG43+AG44+AG45 -> 1807.9 | AH46: =AH38+AH39+AH40+AH41+AH42+AH43+AH44+AH45 -> 3321.4 | AI46: =AI38+AI39+AI40+AI41+AI42+AI43+AI44+AI45 -> 18873.18 | AJ46: =AJ38+AJ39+AJ40+AJ41+AJ42+AJ43+AJ44+AJ45 -> 199 | AM46: Total: | AN46: =AN38+AN39+AN40+AN41+AN42+AN43+AN44+AN45 -> 24770.56 | AO46: =AO38+AO39+AO40+AO41+AO42+AO43+AO44+AO45 -> 3796.1 | AP46: =AP38+AP39+AP40+AP41+AP42+AP43+AP44+AP45 -> 24998.56 | AQ46: =AQ38+AQ39+AQ40+AQ41+AQ42+AQ43+AQ44+AQ45 -> 970
C47: Faturado dia real | D47: =D46-E46 -> 0 | J47: Faturado dia real | K47: =K46-L46 -> 5665.1 | Q47: Faturado dia real | R47: =R46-S46 -> 6086.86 | X47: Faturado dia real | Y47: =Y46-Z46 -> 6972.1 | AE47: Faturado dia real | AF47: =AF46-AG46 -> 2250.4 | AM47: Fat. Real | AN47: =AN46-AO46 -> 20974.46
C48: Recebido dia real | D48: =F46-E46 -> 0 | J48: Recebido dia real | K48: =M46-L46 -> 6806.1 | Q48: Recebido dia real | R48: =T46-S46 -> 6024.66 | X48: Recebido dia real | Y48: =AA46-Z46 -> 6858.2 | AE48: Recebido dia real | AF48: =AH46-AG46 -> 1513.5
B49: Dia | C49: Lojas | D49: Faturamento dia | E49: Não pago dia | F49: Recebido dia | G49: Não pago Acumulado | H49: Peças | I49: Dia | J49: Lojas | K49: Faturamento | L49: Não pago dia | M49: Recebido dia | N49: Não pago Acumulado | O49: Peças | P49: Dia | Q49: Lojas | R49: Faturamento | S49: Não pago dia | T49: Recebido dia | U49: Não pago Acumulado | V49: Peças | W49: Dia | X49: Lojas | Y49: Faturamento | Z49: Não pago dia | AA49: Recebido dia | AB49: Não pago Acumulado | AC49: Peças | AD49: Dia | AE49: Lojas | AF49: Faturamento | AG49: Não pago dia | AH49: Recebido dia | AI49: Não pago Acumulado | AJ49: Peças | AM49: Lojas | AN49: Faturamento | AO49: Não pago dia | AP49: Recebido | AQ49: Peças
A50: Sexta-feira | B50: 45659 | C50: Lago Norte | D50: 846.9 | E50: 329 | F50: 517.9 | G50: 2133.44 | H50: 38 | I50: 45666 | J50: Lago Norte | K50: 547.8 | L50: 36 | M50: 511.8 | N50: 2520.04 | O50: 25 | P50: 45673 | Q50: Lago Norte | R50: 373.1 | S50: 164 | T50: 189.1 | U50: 1167.75 | V50: 16 | W50: 45680 | X50: Lago Norte | Y50: 202.9 | Z50: 28 | AA50: 257.8 | AB50: 973 | AC50: 8 | AD50: 45687 | AE50: Lago Norte | AF50: 1192.9 | AG50: 164 | AH50: 1112.8 | AI50: 1001.1 | AJ50: 64 | AL50: Faturamento Total das Sextas-feiras | AM50: Lago Norte | AN50: =D50+K50+R50+Y50+AF50 -> 3163.6 | AO50: =E50+L50+S50+Z50+AG50 -> 721 | AP50: =F50+M50+T50+AA50+AH50 -> 2589.4 | AQ50: =H50+O50+V50+AC50+AJ50 -> 151
C51: 202 Norte | D51: 490.9 | E51: 21 | F51: 469.9 | G51: 797.6 | H51: 14 | J51: 202 Norte | K51: 855.7 | L51: 300 | M51: 555.7 | N51: 1239.6 | O51: 26 | Q51: 202 Norte | R51: 526 | S51: 66 | T51: 460 | U51: 1383.5 | V51: 39 | X51: 202 Norte | Y51: 1021.9 | Z51: 0 | AA51: 1039.9 | AB51: 1553.5 | AC51: 33 | AE51: 202 Norte | AF51: 818.8 | AG51: 353.9 | AH51: 764.9 | AI51: 2113.4 | AJ51: 32 | AM51: 202 Norte | AN51: =D51+K51+R51+Y51+AF51 -> 3713.3 | AO51: =E51+L51+S51+Z51+AG51 -> 740.9 | AP51: =F51+M51+T51+AA51+AH51 -> 3290.4 | AQ51: =H51+O51+V51+AC51+AJ51 -> 144
C52: 213 / Sof | J52: 213 Norte | Q52: 213 Norte | X52: 213 Norte | AE52: 213 Norte | AM52: 213 Norte | AN52: =D52+K52+R52+Y52+AF52 -> 0 | AO52: =E52+L52+S52+Z52+AG52 -> 0 | AP52: =F52+M52+T52+AA52+AH52 -> 0 | AQ52: =H52+O52+V52+AC52+AJ52 -> 0
C53: 307 Norte | D53: 1257.3 | E53: 430 | F53: 1162.3 | G53: 6537.43 | H53: 43 | J53: 307 Norte | K53: 2098.9 | L53: 1052.6 | M53: 2527.2 | N53: 5052.17 | O53: 99 | Q53: 307 Norte | R53: 1333.05 | S53: 84 | T53: 1380.05 | U53: 5636.27 | V53: 44 | X53: 307 Norte | Y53: 1561.8 | Z53: 727.9 | AA53: 1095.9 | AB53: 6604.98 | AC53: 73 | AE53: 307 Norte | AF53: 2171.9 | AG53: 22 | AH53: 2266.9 | AI53: 5160.43 | AJ53: 52 | AM53: 307 Norte | AN53: =D53+K53+R53+Y53+AF53 -> 8422.95 | AO53: =E53+L53+S53+Z53+AG53 -> 2316.5 | AP53: =F53+M53+T53+AA53+AH53 -> 8432.35 | AQ53: =H53+O53+V53+AC53+AJ53 -> 311
C54: 313 Norte | D54: 348 | E54: 0 | F54: 348 | G54: 1295.9 | H54: 19 | J54: 313 Norte | K54: 864.9 | L54: 0 | M54: 864.9 | N54: 1084.9 | O54: 35 | Q54: 313 Norte | R54: 1294.9 | S54: 0 | T54: 1294.9 | U54: 1389.35 | V54: 61 | X54: 313 Norte | Y54: 668 | Z54: 0 | AA54: 720 | AB54: 1544.35 | AC54: 33 | AE54: 313 Norte | AF54: 1363.9 | AG54: 303 | AH54: 1235.9 | AI54: 2056.35 | AJ54: 56 | AM54: 313 Norte | AN54: =D54+K54+R54+Y54+AF54 -> 4539.7 | AO54: =E54+L54+S54+Z54+AG54 -> 303 | AP54: =F54+M54+T54+AA54+AH54 -> 4463.7 | AQ54: =H54+O54+V54+AC54+AJ54 -> 204
C55: 314 Sul | D55: 0 | E55: 0 | F55: 0 | G55: 584.7 | H55: 0 | J55: 314 Sul | K55: 0 | L55: 0 | M55: 0 | N55: 384.7 | O55: 6 | Q55: 314 Sul | U55: 384.7 | X55: 314 Sul | AE55: 314 Sul | AM55: 314 Sul | AN55: =D55+K55+R55+Y55+AF55 -> 0 | AO55: =E55+L55+S55+Z55+AG55 -> 0 | AP55: =F55+M55+T55+AA55+AH55 -> 0 | AQ55: =H55+O55+V55+AC55+AJ55 -> 6
C56: Sudoeste | D56: 823.2 | E56: 204.3 | F56: 636.9 | G56: 2019.44 | H56: 28 | J56: Sudoeste | K56: 564.9 | L56: 50 | M56: 514.9 | N56: 2432.34 | O56: 19 | Q56: Sudoeste | R56: 730.7 | S56: 180.9 | T56: 549.8 | U56: 2751.44 | V56: 27 | X56: Sudoeste | Y56: 536.7 | Z56: 0 | AA56: 586.7 | AB56: 2848.69 | AC56: 25 | AE56: Sudoeste | AF56: 202.9 | AG56: 0 | AH56: 202.9 | AI56: 2426.29 | AJ56: 16 | AM56: Sudoeste | AN56: =D56+K56+R56+Y56+AF56 -> 2858.4 | AO56: =E56+L56+S56+Z56+AG56 -> 435.2 | AP56: =F56+M56+T56+AA56+AH56 -> 2491.2 | AQ56: =H56+O56+V56+AC56+AJ56 -> 115
C57: Noroeste | D57: 2902.7 | E57: 101 | F57: 3520.93 | G57: 6100.96 | H57: 131 | J57: Noroeste | K57: 2095.3 | L57: 333.8 | M57: 2122.5 | N57: 5303.06 | O57: 102 | Q57: Noroeste | R57: 1995.22 | S57: 213 | T57: 2107.22 | U57: 6610.73 | V57: 79 | X57: Noroeste | Y57: 3286.1 | Z57: 104.9 | AA57: 3338.1 | AB57: 5820.03 | AC57: 118 | AE57: Noroeste | AF57: 3265.6 | AG57: 670.8 | AH57: 2810.7 | AI57: 6690.51 | AJ57: 126 | AM57: Noroeste | AN57: =D57+K57+R57+Y57+AF57 -> 13544.92 | AO57: =E57+L57+S57+Z57+AG57 -> 1423.5 | AP57: =F57+M57+T57+AA57+AH57 -> 13899.45 | AQ57: =H57+O57+V57+AC57+AJ57 -> 556
C58: Total: | D58: =D50+D51+D52+D53+D54+D55+D56+D57 -> 6669 | E58: =E50+E51+E52+E53+E54+E55+E56+E57 -> 1085.3 | F58: =F50+F51+F52+F53+F54+F55+F56+F57 -> 6655.93 | G58: =G50+G51+G52+G53+G54+G55+G56+G57 -> 19469.47 | H58: =H50+H51+H52+H53+H54+H55+H56+H57 -> 273 | J58: Total: | K58: =K50+K51+K52+K53+K54+K55+K56+K57 -> 7027.5 | L58: =L50+L51+L52+L53+L54+L55+L56+L57 -> 1772.4 | M58: =M50+M51+M52+M53+M54+M55+M56+M57 -> 7097 | N58: =N50+N51+N52+N53+N54+N55+N56+N57 -> 18016.81 | O58: =O50+O51+O52+O53+O54+O55+O56+O57 -> 312 | Q58: Total: | R58: =R50+R51+R52+R53+R54+R55+R56+R57 -> 6252.97 | S58: =S50+S51+S52+S53+S54+S55+S56+S57 -> 707.9 | T58: =T50+T51+T52+T53+T54+T55+T56+T57 -> 5981.07 | U58: =U50+U51+U52+U53+U54+U55+U56+U57 -> 19323.74 | V58: =V50+V51+V52+V53+V54+V55+V56+V57 -> 266 | X58: Total: | Y58: =Y50+Y51+Y52+Y53+Y54+Y55+Y56+Y57 -> 7277.4 | Z58: =Z50+Z51+Z52+Z53+Z54+Z55+Z56+Z57 -> 860.8 | AA58: =AA50+AA51+AA52+AA53+AA54+AA55+AA56+AA57 -> 7038.4 | AB58: =AB50+AB51+AB52+AB53+AB54+AB55+AB56+AB57 -> 19344.55 | AC58: =AC50+AC51+AC52+AC53+AC54+AC55+AC56+AC57 -> 290 | AE58: Total: | AF58: =AF50+AF51+AF52+AF53+AF54+AF55+AF56+AF57 -> 9016 | AG58: =AG50+AG51+AG52+AG53+AG54+AG55+AG56+AG57 -> 1513.7 | AH58: =AH50+AH51+AH52+AH53+AH54+AH55+AH56+AH57 -> 8394.1 | AI58: =AI50+AI51+AI52+AI53+AI54+AI55+AI56+AI57 -> 19448.08 | AJ58: =AJ50+AJ51+AJ52+AJ53+AJ54+AJ55+AJ56+AJ57 -> 346 | AM58: Total: | AN58: =AN50+AN51+AN52+AN53+AN54+AN55+AN56+AN57 -> 36242.87 | AO58: =AO50+AO51+AO52+AO53+AO54+AO55+AO56+AO57 -> 5940.1 | AP58: =AP50+AP51+AP52+AP53+AP54+AP55+AP56+AP57 -> 35166.5 | AQ58: =AQ50+AQ51+AQ52+AQ53+AQ54+AQ55+AQ56+AQ57 -> 1487
C59: Faturado dia real | D59: =D58-E58 -> 5583.7 | J59: Faturado dia real | K59: =K58-L58 -> 5255.1 | Q59: Faturado dia real | R59: =R58-S58 -> 5545.07 | X59: Faturado dia real | Y59: =Y58-Z58 -> 6416.6 | AE59: Faturado dia real | AF59: =AF58-AG58 -> 7502.3 | AM59: Fat. Real | AN59: =AN58-AO58 -> 30302.77
C60: Recebido dia real | D60: =F58-E58 -> 5570.63 | J60: Recebido dia real | K60: =M58-L58 -> 5324.6 | Q60: Recebido dia real | R60: =T58-S58 -> 5273.17 | X60: Recebido dia real | Y60: =AA58-Z58 -> 6177.6 | AE60: Recebido dia real | AF60: =AH58-AG58 -> 6880.4
B61: Dia | C61: Lojas | D61: Faturamento dia | E61: Não pago dia | F61: Recebido dia | G61: Não pago Acumulado | H61: Peças | I61: Dia | J61: Lojas | K61: Faturamento | L61: Não pago dia | M61: Recebido dia | N61: Não pago Acumulado | O61: Peças | P61: Dia | Q61: Lojas | R61: Faturamento | S61: Não pago dia | T61: Recebido dia | U61: Não pago Acumulado | V61: Peças | W61: Dia | X61: Lojas | Y61: Faturamento | Z61: Não pago dia | AA61: Recebido dia | AB61: Não pago Acumulado | AC61: Peças | AD61: Dia | AE61: Lojas | AF61: Faturamento | AG61: Não pago dia | AH61: Recebido dia | AI61: Não pago Acumulado | AJ61: Peças | AM61: Lojas | AN61: Faturamento | AO61: Não pago dia | AP61: Recebido | AQ61: Peças
A62: Sábado | B62: 45660 | C62: Lago Norte | D62: 284 | E62: 0 | F62: 284 | G62: 2133.44 | H62: 22 | I62: 45667 | J62: Lago Norte | K62: 435 | L62: 0 | M62: 1777.8 | N62: 1177.24 | O62: 15 | P62: 45674 | Q62: Lago Norte | R62: 924.4 | S62: 0 | T62: 923.4 | U62: 1167.75 | V62: 41 | W62: 45681 | X62: Lago Norte | Y62: 1121 | Z62: 121 | AA62: 1000 | AB62: 1094 | AC62: 57 | AD62: 45688 | AE62: Lago Norte | AF62: 329 | AG62: 0 | AH62: 401 | AI62: 929.1 | AJ62: 15 | AL62: Faturamento Total dos Sábados | AM62: Lago Norte | AN62: =D62+K62+R62+Y62+AF62 -> 3093.4 | AO62: =E62+L62+S62+Z62+AG62 -> 121 | AP62: =F62+M62+T62+AA62+AH62 -> 4386.2 | AQ62: =H62+O62+V62+AC62+AJ62 -> 150
C63: 202 Norte | D63: 414 | E63: 0 | F63: 414 | G63: 797.6 | H63: 16 | J63: 202 Norte | K63: 85 | L63: 0 | M63: 85 | N63: 1239.6 | Q63: 202 Norte | R63: 49 | S63: 0 | T63: 49 | U63: 1383.5 | V63: 22 | X63: 202 Norte | Y63: 389 | Z63: 0 | AA63: 389 | AB63: 1553.5 | AC63: 23 | AE63: 202 Norte | AF63: 524 | AG63: 394 | AH63: 130 | AI63: 2507.4 | AJ63: 46 | AM63: 202 Norte | AN63: =D63+K63+R63+Y63+AF63 -> 1461 | AO63: =E63+L63+S63+Z63+AG63 -> 394 | AP63: =F63+M63+T63+AA63+AH63 -> 1067 | AQ63: =H63+O63+V63+AC63+AJ63 -> 107
C64: 213 / Sof | J64: 213 Norte | Q64: 213 Norte | X64: 213 Norte | AE64: 213 Norte | AM64: 213 Norte | AN64: =D64+K64+R64+Y64+AF64 -> 0 | AO64: =E64+L64+S64+Z64+AG64 -> 0 | AP64: =F64+M64+T64+AA64+AH64 -> 0 | AQ64: =H64+O64+V64+AC64+AJ64 -> 0
C65: 307 Norte | D65: 1518.6 | E65: 174 | F65: 1344.6 | G65: 6711.43 | H65: 76 | J65: 307 Norte | K65: 1502.54 | L65: 0 | M65: 1552.54 | N65: 5002.17 | O65: 58 | Q65: 307 Norte | R65: 1599.9 | S65: 50 | T65: 1604.8 | U65: 5631.37 | V65: 73 | X65: 307 Norte | Y65: 1189.4 | Z65: 0 | AA65: 1262.4 | AB65: 6531.98 | AC65: 62 | AE65: 307 Norte | AF65: 2253.55 | AG65: 203.9 | AH65: 2104.55 | AI65: 5309.43 | AJ65: 104 | AM65: 307 Norte | AN65: =D65+K65+R65+Y65+AF65 -> 8063.99 | AO65: =E65+L65+S65+Z65+AG65 -> 427.9 | AP65: =F65+M65+T65+AA65+AH65 -> 7868.89 | AQ65: =H65+O65+V65+AC65+AJ65 -> 373
C66: 313 Norte | D66: 170 | E66: 0 | F66: 170 | G66: 1295.9 | H66: 10 | J66: 313 Norte | K66: 1361.2 | L66: 0 | M66: 1361.2 | N66: 1084.9 | O66: 44 | Q66: 313 Norte | R66: 1272.7 | S66: 0 | T66: 1272.7 | U66: 1389.35 | V66: 50 | X66: 313 Norte | Y66: 1461.9 | Z66: 130 | AA66: 1331.9 | AB66: 1674.35 | AC66: 65 | AE66: 313 Norte | AF66: 2434.9 | AG66: 0 | AH66: 2434.9 | AI66: 2056.35 | AJ66: 86 | AM66: 313 Norte | AN66: =D66+K66+R66+Y66+AF66 -> 6700.7 | AO66: =E66+L66+S66+Z66+AG66 -> 130 | AP66: =F66+M66+T66+AA66+AH66 -> 6570.7 | AQ66: =H66+O66+V66+AC66+AJ66 -> 255
C67: 314 Sul | D67: 0 | E67: 0 | F67: 0 | G67: 584.7 | H67: 0 | J67: 314 Sul | N67: 384.7 | Q67: 314 Sul | U67: 384.7 | X67: 314 Sul | AE67: 314 Sul | AM67: 314 Sul | AN67: =D67+K67+R67+Y67+AF67 -> 0 | AO67: =E67+L67+S67+Z67+AG67 -> 0 | AP67: =F67+M67+T67+AA67+AH67 -> 0 | AQ67: =H67+O67+V67+AC67+AJ67 -> 0
C68: Sudoeste | D68: 375.9 | E68: 135 | F68: 270.9 | G68: 2124.44 | H68: 14 | J68: Sudoeste | K68: 669.9 | L68: 0 | M68: 804.9 | N68: 2297.34 | O68: 33 | Q68: Sudoeste | R68: 871 | S68: 21 | T68: 975.6 | U68: 2646.84 | V68: 39 | X68: Sudoeste | Y68: 435 | Z68: 0 | AA68: 635 | AB68: 2648.69 | AC68: 12 | AE68: Sudoeste | AF68: 684 | AG68: 50 | AH68: 637 | AI68: 2476.29 | AJ68: 38 | AM68: Sudoeste | AN68: =D68+K68+R68+Y68+AF68 -> 3035.8 | AO68: =E68+L68+S68+Z68+AG68 -> 206 | AP68: =F68+M68+T68+AA68+AH68 -> 3323.4 | AQ68: =H68+O68+V68+AC68+AJ68 -> 136
C69: Noroeste | D69: 890 | E69: 0 | F69: 890 | G69: 6100.96 | H69: 55 | J69: Noroeste | K69: 2654.47 | L69: 944.97 | M69: 1795.5 | N69: 6162.03 | O69: 104 | Q69: Noroeste | R69: 548 | S69: 257 | T69: 327 | U69: 6831.73 | V69: 63 | X69: Noroeste | Y69: 3430.11 | Z69: 341.6 | AA69: 3132.51 | AB69: 6117.63 | AC69: 87 | AE69: Noroeste | AF69: 3591.2 | AG69: 641.9 | AH69: 3261.27 | AI69: 7020.44 | AJ69: 115 | AM69: Noroeste | AN69: =D69+K69+R69+Y69+AF69 -> 11113.78 | AO69: =E69+L69+S69+Z69+AG69 -> 2185.47 | AP69: =F69+M69+T69+AA69+AH69 -> 9406.28 | AQ69: =H69+O69+V69+AC69+AJ69 -> 424
C70: Total: | D70: =D62+D63+D64+D65+D66+D67+D68+D69 -> 3652.5 | E70: =E62+E63+E64+E65+E66+E67+E68+E69 -> 309 | F70: =F62+F63+F64+F65+F66+F67+F68+F69 -> 3373.5 | G70: =G62+G63+G64+G65+G66+G67+G68+G69 -> 19748.47 | H70: =H62+H63+H64+H65+H66+H67+H68+H69 -> 193 | J70: Total: | K70: =K62+K63+K64+K65+K66+K67+K68+K69 -> 6708.11 | L70: =L62+L63+L64+L65+L66+L67+L68+L69 -> 944.97 | M70: =M62+M63+M64+M65+M66+M67+M68+M69 -> 7376.94 | N70: =N62+N63+N64+N65+N66+N67+N68+N69 -> 17347.98 | O70: =O62+O63+O64+O65+O66+O67+O68+O69 -> 254 | Q70: Total: | R70: =R62+R63+R64+R65+R66+R67+R68+R69 -> 5265 | S70: =S62+S63+S64+S65+S66+S67+S68+S69 -> 328 | T70: =T62+T63+T64+T65+T66+T67+T68+T69 -> 5152.5 | U70: =U62+U63+U64+U65+U66+U67+U68+U69 -> 19435.24 | V70: =V62+V63+V64+V65+V66+V67+V68+V69 -> 288 | X70: Total: | Y70: =Y62+Y63+Y64+Y65+Y66+Y67+Y68+Y69 -> 8026.41 | Z70: =Z62+Z63+Z64+Z65+Z66+Z67+Z68+Z69 -> 592.6 | AA70: =AA62+AA63+AA64+AA65+AA66+AA67+AA68+AA69 -> 7750.81 | AB70: =AB62+AB63+AB64+AB65+AB66+AB67+AB68+AB69 -> 19620.15 | AC70: =AC62+AC63+AC64+AC65+AC66+AC67+AC68+AC69 -> 306 | AE70: Total: | AF70: =AF62+AF63+AF64+AF65+AF66+AF67+AF68+AF69 -> 9816.65 | AG70: =AG62+AG63+AG64+AG65+AG66+AG67+AG68+AG69 -> 1289.8 | AH70: =AH62+AH63+AH64+AH65+AH66+AH67+AH68+AH69 -> 8968.72 | AI70: =AI62+AI63+AI64+AI65+AI66+AI67+AI68+AI69 -> 20299.01 | AJ70: =AJ62+AJ63+AJ64+AJ65+AJ66+AJ67+AJ68+AJ69 -> 404 | AM70: Total: | AN70: =AN62+AN63+AN64+AN65+AN66+AN67+AN68+AN69 -> 33468.67 | AO70: =AO62+AO63+AO64+AO65+AO66+AO67+AO68+AO69 -> 3464.37 | AP70: =AP62+AP63+AP64+AP65+AP66+AP67+AP68+AP69 -> 32622.47 | AQ70: =AQ62+AQ63+AQ64+AQ65+AQ66+AQ67+AQ68+AQ69 -> 1445
C71: Faturado dia real | D71: =D70-E70 -> 3343.5 | J71: Faturado dia real | K71: =K70-L70 -> 5763.14 | Q71: Faturado dia real | R71: =R70-S70 -> 4937 | X71: Faturado dia real | Y71: =Y70-Z70 -> 7433.81 | AE71: Faturado dia real | AF71: =AF70-AG70 -> 8526.85 | AM71: Fat. Real | AN71: =AN70-AO70 -> 30004.3
C72: Recebido dia real | D72: =F70-E70 -> 3064.5 | J72: Recebido dia real | K72: =M70-L70 -> 6431.97 | Q72: Recebido dia real | R72: =T70-S70 -> 4824.5 | X72: Recebido dia real | Y72: =AA70-Z70 -> 7158.21 | AE72: Recebido dia real | AF72: =AH70-AG70 -> 7678.92
B73: Dia | C73: Lojas | D73: Faturamento | E73: Não pago dia | F73: Recebido dia | G73: Não pago Acumulado | H73: Peças | I73: Dia | J73: Lojas | K73: Faturamento | L73: Não pago dia | M73: Recebido dia | N73: Não pago Acumulado | O73: Peças | P73: Dia | Q73: Lojas | R73: Faturamento | S73: Não pago dia | T73: Recebido dia | U73: Não pago Acumulado | V73: Peças | W73: Dia | X73: Lojas | Y73: Faturamento | Z73: Não pago dia | AA73: Recebido dia | AB73: Não pago Acumulado | AC73: Peças | AD73: Dia | AE73: Lojas | AF73: Faturamento | AG73: Não pago dia | AH73: Recebido dia | AI73: Não pago Acumulado | AJ73: Peças | AM73: Lojas | AN73: Faturamento | AO73: Não pago dia | AP73: Recebido | AQ73: Peças
A74: Domingo | B74: 45661 | C74: Lago Norte | I74: 45668 | P74: 45675 | W74: 45682 | AL74: Faturamento Total dos Domingos
C75: 202 Norte
C76: 213 Norte
C77: 307 Norte
C78: 313 Norte
C79: 314 Sul
C80: Sudoeste
C81: Noroeste | J81: Noroeste -Dani | Q81: Noroeste | X81: Noroeste | AE81: Noroeste | AM81: Noroeste | AN81: =D81+K81+R81+Y81+AF81 -> 0 | AO81: =E81+L81+S81+Z81+AG81 -> 0 | AP81: =F81+M81+T81+AA81+AH81 -> 0 | AQ81: =H81+O81+V81+AC81+AJ81 -> 0
C82: Total: | D82: =D74+D75+D76+D77+D78+D79+D80+D81 -> 0 | E82: =E74+E75+E76+E77+E78+E79+E80+E81 -> 0 | F82: =F74+F75+F76+F77+F78+F79+F80+F81 -> 0 | G82: =G74+G75+G76+G77+G78+G79+G80+G81 -> 0 | H82: =H74+H75+H76+H77+H78+H79+H80+H81 -> 0 | J82: Total: | K82: =K74+K75+K76+K77+K78+K79+K80+K81 -> 0 | L82: =L74+L75+L76+L77+L78+L79+L80+L81 -> 0 | M82: =M74+M75+M76+M77+M78+M79+M80+M81 -> 0 | N82: =N74+N75+N76+N77+N78+N79+N80+N81 -> 0 | O82: =O74+O75+O76+O77+O78+O79+O80+O81 -> 0 | Q82: Total: | R82: =R74+R75+R76+R77+R78+R79+R80+R81 -> 0 | S82: =S74+S75+S76+S77+S78+S79+S80+S81 -> 0 | T82: =T74+T75+T76+T77+T78+T79+T80+T81 -> 0 | U82: =U74+U75+U76+U77+U78+U79+U80+U81 -> 0 | V82: =V74+V75+V76+V77+V78+V79+V80+V81 -> 0 | X82: Total: | Y82: =Y74+Y75+Y76+Y77+Y78+Y79+Y80+Y81 -> 0 | Z82: =Z74+Z75+Z76+Z77+Z78+Z79+Z80+Z81 -> 0 | AA82: =AA74+AA75+AA76+AA77+AA78+AA79+AA80+AA81 -> 0 | AB82: =AB74+AB75+AB76+AB77+AB78+AB79+AB80+AB81 -> 0 | AC82: =AC74+AC75+AC76+AC77+AC78+AC79+AC80+AC81 -> 0 | AE82: Total: | AF82: =AF74+AF75+AF76+AF77+AF78+AF79+AF80+AF81 -> 0 | AG82: =AG74+AG75+AG76+AG77+AG78+AG79+AG80+AG81 -> 0 | AH82: =AH74+AH75+AH76+AH77+AH78+AH79+AH80+AH81 -> 0 | AI82: =AI74+AI75+AI76+AI77+AI78+AI79+AI80+AI81 -> 0 | AJ82: =AJ74+AJ75+AJ76+AJ77+AJ78+AJ79+AJ80+AJ81 -> 0 | AM82: Total: | AN82: =AN74+AN75+AN76+AN77+AN78+AN79+AN80+AN81 -> 0 | AO82: =AO74+AO75+AO76+AO77+AO78+AO79+AO80+AO81 -> 0 | AP82: =AP74+AP75+AP76+AP77+AP78+AP79+AP80+AP81 -> 0 | AQ82: =AQ74+AQ75+AQ76+AQ77+AQ78+AQ79+AQ80+AQ81 -> 0
C83: Faturado dia real | D83: =D82-E82 -> 0 | J83: Faturado dia real | K83: =K82-L82 -> 0 | Q83: Faturado dia real | R83: =R82-S82 -> 0 | X83: Faturado dia real | Y83: =Y82-Z82 -> 0 | AE83: Faturado dia real | AF83: =AF82-AG82 -> 0 | AM83: Fat. Real | AN83: =AN82-AO82 -> 0
C84: Recebido dia real | D84: =F82-E82 -> 0 | J84: Recebido dia real | K84: =M82-L82 -> 0 | Q84: Recebido dia real | R84: =T82-S82 -> 0 | X84: Recebido dia real | Y84: =AA82-Z82 -> 0 | AE84: Recebido dia real | AF84: =AH82-AG82 -> 0
C87: Faturamento 4° semana Janeiro | J87: Faturamento 4° semana Janeiro | Q87: Faturamento 4° semana Janeiro | X87: Faturamento 4° semana Janeiro | AE87: Faturamento 4 1/2° semana Janeiro
C88: Faturamento | D88: =D10+D22+D34+D46+D58+D70+D82 -> 10321.5 | J88: Faturamento | K88: =K10+K22+K34+K46+K58+K70+K82 -> 42531.37 | Q88: Faturamento | R88: =R10+R22+R34+R46+R58+R70+R82 -> 42288.19 | X88: Faturamento | Y88: =Y10+Y22+Y34+Y46+Y58+Y70+Y82 -> 49510.75 | AE88: Faturamento | AF88: =AF10+AF22+AF34+AF46+AF58+AF70+AF82 -> 51580.05 | AN88: {=AN10+AN22+AN34+AN46+AN58+AN70} -> 196231.86 | AP88: {=AP10+AP22+AP34+AP46+AP58+AP70} -> 194405.23
C89: Não pago dia | D89: =E10+E22+E34+E46+E58+E70+E82 -> 1394.3 | J89: Não pago dia | K89: =L10+L22+L34+L46+L58+L70+L82 -> 5993.67 | Q89: Não pago dia | R89: =S10+S22+S34+S46+S58+S70+S82 -> 5495.35 | X89: Não pago dia | Y89: =Z10+Z22+Z34+Z46+Z58+Z70+Z82 -> 6542.16 | AE89: Não pago dia | AF89: =AG10+AG22+AG34+AG46+AG58+AG70+AG82 -> 7890.33
C90: Recebido | D90: =F10+F22+F34+F46+F58+F70+F82 -> 10029.43 | J90: Recebido | K90: =M10+M22+M34+M46+M58+M70+M82 -> 44934.36 | Q90: Recebido | R90: =T10+T22+T34+T46+T58+T70+T82 -> 39854.61 | X90: Recebido | Y90: =AA10+AA22+AA34+AA46+AA58+AA70+AA82 -> 48875.14 | AE90: Recebido | AF90: =AH10+AH22+AH34+AH46+AH58+AH70+AH82 -> 50711.69
C91: Fat. Real | D91: {=D11:E11+D23:E23+D35:E35+D47:E47+D59:E59+D71:E71+D83:F83} -> 8927.2 | J91: Fat. Real | K91: {=K11:L11+K23:L23+K35:L35+K47:L47+K59:L59+K71:L71+K83:M83} -> 36537.7 | Q91: Fat. Real | R91: {=R11:S11+R23:S23+R35:S35+R47:S47+R59:S59+R71:S71+R83:T83} -> 36792.84 | X91: Fat. Real | Y91: {=Y11:Z11+Y23:Z23+Y35:Z35+Y47:Z47+Y59:Z59+Y71:Z71+Y83:AA83} -> 42968.59 | AE91: Fat. Real | AF91: {=AF11:AG11+AF23:AG23+AF35:AG35+AF47:AG47+AF59:AG59+AF71:AG71+AF83:AH83} -> 43689.72
C92: Recebido Real | D92: {=D12:F12+D24:F24+D36:F36+D48:F48+D60:F60+D72:F72+D84:F84} -> 8635.13 | J92: Recebido Real | K92: {=K12:M12+K24:M24+K36:M36+K48:M48+K60:M60+K72:M72+K84:M84} -> 38940.69 | Q92: Recebido Real | R92: {=R12:T12+R24:T24+R36:T36+R48:T48+R60:T60+R72:T72+R84:T84} -> 34359.26 | X92: Recebido Real | Y92: {=Y12:AA12+Y24:AA24+Y36:AA36+Y48:AA48+Y60:AA60+Y72:AA72+Y84:AA84} -> 42332.98 | AE92: Recebido Real | AF92: {=AF12:AH12+AF24:AH24+AF36:AH36+AF48:AH48+AF60:AH60+AF72:AH72+AF84:AH84} -> 42821.36
C93: N° Total de Peças | D93: {=H10+H22+H34+H46+H58+H70+H82} -> 466 | J93: N° Total de Peças | K93: {=O10+O22+O34+O46+O58+O70+O82} -> 1751 | Q93: N° Total de Peças | R93: {=V10+V22+V34+V46+V58+V70+V82} -> 1751 | X93: N° Total de Peças | Y93: {=AC10+AC22+AC34+AC46+AC58+AC70+AC82} -> 1855 | AE93: N° Total de Peças | AF93: {=AJ10+AJ22+AJ34+AJ46+AJ58+AJ70+AJ82} -> 2067
C96: Faturamento por Loja na 1° Semana | J96: Faturamento por Loja na 2° Semana | Q96: Faturamento por Loja na 3° Semana | X96: Faturamento por Loja na 4° Semana | AE96: Faturamento por Loja na 4° 1/2 Semana
C97: Lojas | D97: Faturamento | E97: Não pago dia | F97: Recebimento | G97: Real da semana | H97: Peças | J97: Lojas | K97: Faturamento | L97: Não pago dia | M97: Recebimento | N97: Real da semana | O97: Peças | Q97: Lojas | R97: Faturamento | S97: Não pago dia | T97: Recebimento | U97: Real da semana | V97: Peças | X97: Lojas | Y97: Faturamento | Z97: Não pago dia | AA97: Recebimento | AB97: Real da semana | AC97: Peças | AE97: Lojas | AF97: Faturamento | AG97: Não pago dia | AH97: Recebimento | AI97: Real da semana | AJ97: Peças
C98: Lago Norte | D98: =D2+D14+D26+D38+D50+D62 -> 1130.9 | E98: =E2+E14+E26+E38+E50+E62 -> 329 | F98: =F2+F14+F26+F38+F50+F62 -> 801.9 | G98: =F98-E98 -> 472.9 | H98: =H2+H14+H26+H38+H50+H62 -> 60 | J98: Lago Norte | K98: =K2+K14+K26+K38+K50+K62 -> 5156.63 | L98: =L2+L14+L26+L38+L50+L62 -> 696.4 | M98: =M2+M14+M26+M38+M50+M62 -> 6115.83 | N98: =M98-L98 -> 5419.43 | O98: =O2+O14+O26+O38+O50+O62 -> 200 | Q98: Lago Norte | R98: =R2+R14+R26+R38+R50+R62 -> 3763.5 | S98: =S2+S14+S26+S38+S50+S62 -> 164 | T98: =T2+T14+T26+T38+T50+T62 -> 3737.07 | U98: =T98-S98 -> 3573.07 | V98: =V2+V14+V26+V38+V50+V62 -> 126 | X98: Lago Norte | Y98: =Y2+Y14+Y26+Y38+Y50+Y62 -> 4653.2 | Z98: =Z2+Z14+Z26+Z38+Z50+Z62 -> 579.9 | AA98: =AA2+AA14+AA26+AA38+AA50+AA62 -> 4758.95 | AB98: =AA98-Z98 -> 4179.05 | AC98: =AC2+AC14+AC26+AC38+AC50+AC62 -> 195 | AE98: Lago Norte | AF98: =AF2+AF14+AF26+AF38+AF50+AF62 -> 4865.5 | AG98: =AG2+AG14+AG26+AG38+AG50+AG62 -> 529.2 | AH98: =AH2+AH14+AH26+AH38+AH50+AH62 -> 5009.4 | AI98: =AH98-AG98 -> 4480.2 | AJ98: =AJ2+AJ14+AJ26+AJ38+AJ50+AJ62 -> 201
C99: 202 Norte | D99: =D3+D15+D27+D39+D51+D63 -> 904.9 | E99: =E3+E15+E27+E39+E51+E63 -> 21 | F99: =F3+F15+F27+F39+F51+F63 -> 883.9 | G99: =F99-E99 -> 862.9 | H99: =H3+H15+H27+H39+H51+H63 -> 30 | J99: 202 Norte | K99: =K3+K15+K27+K39+K51+K63 -> 3648.6 | L99: =L3+L15+L27+L39+L51+L63 -> 734.9 | M99: =M3+M15+M27+M39+M51+M63 -> 3206.6 | N99: =M99-L99 -> 2471.7 | O99: =O3+O15+O27+O39+O51+O63 -> 132 | Q99: 202 Norte | R99: =R3+R15+R27+R39+R51+R63 -> 2641.26 | S99: =S3+S15+S27+S39+S51+S63 -> 462.8 | T99: =T3+T15+T27+T39+T51+T63 -> 2371.36 | U99: =T99-S99 -> 1908.56 | V99: =V3+V15+V27+V39+V51+V63 -> 167 | X99: 202 Norte | Y99: =Y3+Y15+Y27+Y39+Y51+Y63 -> 3497.7 | Z99: =Z3+Z15+Z27+Z39+Z51+Z63 -> 240 | AA99: =AA3+AA15+AA27+AA39+AA51+AA63 -> 3327.7 | AB99: =AA99-Z99 -> 3087.7 | AC99: =AC3+AC15+AC27+AC39+AC51+AC63 -> 151 | AE99: 202 Norte | AF99: =AF3+AF15+AF27+AF39+AF51+AF63 -> 4264.4 | AG99: =AG3+AG15+AG27+AG39+AG51+AG63 -> 2003.7 | AH99: =AH3+AH15+AH27+AH39+AH51+AH63 -> 3280.5 | AI99: =AH99-AG99 -> 1276.8 | AJ99: =AJ3+AJ15+AJ27+AJ39+AJ51+AJ63 -> 200
C100: 213 Norte | D100: =D4+D16+D28+D40+D52+D64 -> 0 | E100: =E4+E16+E28+E40+E52+E64 -> 0 | F100: =F4+F16+F28+F40+F52+F64 -> 0 | G100: =F100-E100 -> 0 | H100: =H4+H16+H28+H40+H52+H64 -> 0 | J100: 213 Norte | K100: =K4+K16+K28+K40+K52+K64 -> 0 | L100: =L4+L16+L28+L40+L52+L64 -> 0 | M100: =M4+M16+M28+M40+M52+M64 -> 0 | N100: =M100-L100 -> 0 | O100: =O4+O16+O28+O40+O52+O64 -> 0 | Q100: 213 Norte | R100: =R4+R16+R28+R40+R52+R64 -> 0 | S100: =S4+S16+S28+S40+S52+S64 -> 0 | T100: =T4+T16+T28+T40+T52+T64 -> 0 | U100: =T100-S100 -> 0 | V100: =V4+V16+V28+V40+V52+V64 -> 0 | X100: 213 Norte | Y100: =Y4+Y16+Y28+Y40+Y52+Y64 -> 0 | Z100: =Z4+Z16+Z28+Z40+Z52+Z64 -> 0 | AA100: =AA4+AA16+AA28+AA40+AA52+AA64 -> 0 | AB100: =AA100-Z100 -> 0 | AC100: =AC4+AC16+AC28+AC40+AC52+AC64 -> 0 | AE100: 213 Norte | AF100: =AF4+AF16+AF28+AF40+AF52+AF64 -> 0 | AG100: =AG4+AG16+AG28+AG40+AG52+AG64 -> 0 | AH100: =AH4+AH16+AH28+AH40+AH52+AH64 -> 0 | AI100: =AH100-AG100 -> 0 | AJ100: =AJ4+AJ16+AJ28+AJ40+AJ52+AJ64 -> 0
C101: 307 Norte | D101: =D5+D17+D29+D41+D53+D65 -> 2775.9 | E101: =E5+E17+E29+E41+E53+E65 -> 604 | F101: =F5+F17+F29+F41+F53+F65 -> 2506.9 | G101: =F101-E101 -> 1902.9 | H101: =H5+H17+H29+H41+H53+H65 -> 119 | J101: 307 Norte | K101: =K5+K17+K29+K41+K53+K65 -> 10295.52 | L101: =L5+L17+L29+L41+L53+L65 -> 1615.5 | M101: =M5+M17+M29+M41+M53+M65 -> 12004.28 | N101: =M101-L101 -> 10388.78 | O101: =O5+O17+O29+O41+O53+O65 -> 385 | Q101: 307 Norte | R101: =R5+R17+R29+R41+R53+R65 -> 10188.66 | S101: =S5+S17+S29+S41+S53+S65 -> 1429 | T101: =T5+T17+T29+T41+T53+T65 -> 9559.46 | U101: =T101-S101 -> 8130.46 | V101: =V5+V17+V29+V41+V53+V65 -> 373 | X101: 307 Norte | Y101: =Y5+Y17+Y29+Y41+Y53+Y65 -> 11546.77 | Z101: =Z5+Z17+Z29+Z41+Z53+Z65 -> 2980.51 | AA101: =AA5+AA17+AA29+AA41+AA53+AA65 -> 10583.16 | AB101: =AA101-Z101 -> 7602.65 | AC101: =AC5+AC17+AC29+AC41+AC53+AC65 -> 439 | AE101: 307 Norte | AF101: =AF5+AF17+AF29+AF41+AF53+AF65 -> 13214.07 | AG101: =AG5+AG17+AG29+AG41+AG53+AG65 -> 1721.65 | AH101: =AH5+AH17+AH29+AH41+AH53+AH65 -> 14381.72 | AI101: =AH101-AG101 -> 12660.07 | AJ101: =AJ5+AJ17+AJ29+AJ41+AJ53+AJ65 -> 451
C102: 313 Norte | D102: =D6+D18+D30+D42+D54+D66 -> 518 | E102: =E6+E18+E30+E42+E54+E66 -> 0 | F102: =F6+F18+F30+F42+F54+F66 -> 518 | G102: =F102-E102 -> 518 | H102: =H6+H18+H30+H42+H54+H66 -> 29 | J102: 313 Norte | K102: =K6+K18+K30+K42+K54+K66 -> 7290.9 | L102: =L6+L18+L30+L42+L54+L66 -> 40 | M102: =M6+M18+M30+M42+M54+M66 -> 7501.9 | N102: =M102-L102 -> 7461.9 | O102: =O6+O18+O30+O42+O54+O66 -> 308 | Q102: 313 Norte | R102: =R6+R18+R30+R42+R54+R66 -> 7891.35 | S102: =S6+S18+S30+S42+S54+S66 -> 662.35 | T102: =T6+T18+T30+T42+T54+T66 -> 7586.9 | U102: =T102-S102 -> 6924.55 | V102: =V6+V18+V30+V42+V54+V66 -> 336 | X102: 313 Norte | Y102: =Y6+Y18+Y30+Y42+Y54+Y66 -> 7019.8 | Z102: =Z6+Z18+Z30+Z42+Z54+Z66 -> 381 | AA102: =AA6+AA18+AA30+AA42+AA54+AA66 -> 6734.8 | AB102: =AA102-Z102 -> 6353.8 | AC102: =AC6+AC18+AC30+AC42+AC54+AC66 -> 276 | AE102: 313 Norte | AF102: =AF6+AF18+AF30+AF42+AF54+AF66 -> 7795.3 | AG102: =AG6+AG18+AG30+AG42+AG54+AG66 -> 557 | AH102: =AH6+AH18+AH30+AH42+AH54+AH66 -> 7413.3 | AI102: =AH102-AG102 -> 6856.3 | AJ102: =AJ6+AJ18+AJ30+AJ42+AJ54+AJ66 -> 305
C103: 314 Sul | D103: =D7+D19+D31+D43+D55+D67 -> 0 | E103: =E7+E19+E31+E43+E55+E67 -> 0 | F103: =F7+F19+F31+F43+F55+F67 -> 0 | G103: =F103-E103 -> 0 | H103: =H7+H19+H31+H43+H55+H67 -> 0 | J103: 314 Sul | K103: =K7+K19+K31+K43+K55+K67 -> 0 | L103: =L7+L19+L31+L43+L55+L67 -> 0 | M103: =M7+M19+M31+M43+M55+M67 -> 200 | N103: =M103-L103 -> 200 | O103: =O7+O19+O31+O43+O55+O67 -> 27 | Q103: 314 Sul | R103: =R7+R19+R31+R43+R55+R67 -> 0 | S103: =S7+S19+S31+S43+S55+S67 -> 0 | T103: =T7+T19+T31+T43+T55+T67 -> 0 | U103: =T103-S103 -> 0 | V103: =V7+V19+V31+V43+V55+V67 -> 0 | X103: 314 Sul | Y103: =Y7+Y19+Y31+Y43+Y55+Y67 -> 0 | Z103: =Z7+Z19+Z31+Z43+Z55+Z67 -> 0 | AA103: =AA7+AA19+AA31+AA43+AA55+AA67 -> 0 | AB103: =AA103-Z103 -> 0 | AC103: =AC7+AC19+AC31+AC43+AC55+AC67 -> 0 | AE103: 314 Sul | AF103: =AF7+AF19+AF31+AF43+AF55+AF67 -> 0 | AG103: =AG7+AG19+AG31+AG43+AG55+AG67 -> 0 | AH103: =AH7+AH19+AH31+AH43+AH55+AH67 -> 0 | AI103: =AH103-AG103 -> 0 | AJ103: =AJ7+AJ19+AJ31+AJ43+AJ55+AJ67 -> 0
C104: Sudoeste | D104: =D8+D20+D32+D44+D56+D68 -> 1199.1 | E104: =E8+E20+E32+E44+E56+E68 -> 339.3 | F104: =F8+F20+F32+F44+F56+F68 -> 907.8 | G104: =F104-E104 -> 568.5 | H104: =H8+H20+H32+H44+H56+H68 -> 42 | J104: Sudoeste | K104: =K8+K20+K32+K44+K56+K68 -> 4159.5 | L104: =L8+L20+L32+L44+L56+L68 -> 752.8 | M104: =M8+M20+M32+M44+M56+M68 -> 3986.6 | N104: =M104-L104 -> 3233.8 | O104: =O8+O20+O32+O44+O56+O68 -> 170 | Q104: Sudoeste | R104: =R8+R20+R32+R44+R56+R68 -> 5693.6 | S104: =S8+S20+S32+S44+S56+S68 -> 988.9 | T104: =T8+T20+T32+T44+T56+T68 -> 5344.1 | U104: =T104-S104 -> 4355.2 | V104: =V8+V20+V32+V44+V56+V68 -> 218 | X104: Sudoeste | Y104: =Y8+Y20+Y32+Y44+Y56+Y68 -> 4563.05 | Z104: =Z8+Z20+Z32+Z44+Z56+Z68 -> 615.85 | AA104: =AA8+AA20+AA32+AA44+AA56+AA68 -> 4561.2 | AB104: =AA104-Z104 -> 3945.35 | AC104: =AC8+AC20+AC32+AC44+AC56+AC68 -> 181 | AE104: Sudoeste | AF104: =AF8+AF20+AF32+AF44+AF56+AF68 -> 3867.4 | AG104: =AG8+AG20+AG32+AG44+AG56+AG68 -> 773.8 | AH104: =AH8+AH20+AH32+AH44+AH56+AH68 -> 4042.8 | AI104: =AH104-AG104 -> 3269 | AJ104: =AJ8+AJ20+AJ32+AJ44+AJ56+AJ68 -> 201
...

Sheet Faturamento 
J1: Vendas no Sistema 2023
I2: Lojas | J2: Setembro | K2: Outubro | L2: Novembro | M2: Dezembro
I3: 202 | J3: 14688.94 | K3: 16995.73 | L3: 13920.6 | M3: 9776.45
I4: 213 | J4: 17401.26 | K4: 17473.56 | L4: 14995.9 | M4: 17427.74
I5: 307 | J5: 39820.56 | K5: 41926.9 | L5: 37635.21 | M5: 38715.8
I6: 313 | J6: 0 | K6: 7543 | L6: 13055.9 | M6: 10273.45
I7: Lago | L7: 4075.53 | M7: 8989.87
I8: Sudoeste | J8: 24877.16 | K8: 17318.11 | L8: 19683.3 | M8: 17992.5
I9: Total: | J9: =J3+J4+J5+J6+J7+J8 -> 96787.92 | K9: =K3+K4+K5+K6+K7+K8 -> 101257.3 | L9: =L3+L4+L5+L6+L7+L8 -> 103366.44 | M9: =M3+M4+M5+M6+M7+M8 -> 103175.81
I10: Total Ano: | J10: =J9+K9+L9+M9 -> 404587.47
B12: Vendas no Sistema 2024
A13: Lojas | B13: Janeiro | C13: Fevereiro | D13: Março | E13: Abril | F13: Maio | G13: Junho | H13: Julho | I13: Agosto | J13: Setembro | K13: Outubro | L13: Novembro | M13: Dezembro | O13: Média do ano
A14: 202 Norte | B14: 11957.8 | C14: 9855.58 | D14: 11843.23 | E14: 13074.46 | F14: 11484.73 | G14: 13540.53 | H14: 17314.1 | I14: 17483.18 | J14: 15424.26 | K14: 13337.64 | L14: 16819.49 | M14: 14128.32 | O14: =(C14+D14+E14+F14+G14+H14+I14+J14+K14+L14+M14)/12 -> 12858.793
A15: 213 Norte | B15: 18085.15 | C15: 16018.83 | D15: 14639.95 | E15: 16569.81 | F15: 18127.68 | G15: 16896.93 | H15: 17790.89 | I15: 19754.73 | J15: 17001.54 | K15: 17803.02 | L15: 13036.38 | M15: 17726.84 | O15: =(C15+D15+E15+F15+G15+H15+I15+J15+K15+L15+M15)/12 -> 15447.217
A16: 307 Norte | B16: 40832.92 | C16: 34766.15 | D16: 37138.31 | E16: 36583.9 | F16: 35900.67 | G16: 32882.06 | H16: 40662.58 | I16: 39584.16 | J16: 37348.14 | K16: 43194.11 | L16: 39268.88 | M16: 40693.26 | O16: =(C16+D16+E16+F16+G16+H16+I16+J16+K16+L16+M16)/12 -> 34835.185
A17: 313 Norte | B17: 9680.39 | C17: 11122.08 | D17: 12643.38 | E17: 13284.78 | F17: 12605.04 | G17: 13112.08 | H17: 14477.14 | I17: 12789.4 | J17: 14418.09 | K17: 11108.22 | L17: 14684.53 | M17: 13726.15 | O17: =(C17+D17+E17+F17+G17+H17+I17+J17+K17+L17+M17)/12 -> 11997.574
A18: 314 Sul | I18: 4456.43 | J18: 8695.66 | K18: 12076.09 | L18: 11549.62 | M18: 9387.9 | O18: =(C18+D18+E18+F18+G18+H18+I18+J18+K18+L18+M18)/5 -> 9233.14
A19: Lago Norte | B19: 12000.82 | C19: 9407.74 | D19: 12603.58 | E19: 12708.46 | F19: 18034.45 | G19: 16798.24 | H19: 16481.65 | I19: 18241.19 | J19: 16195.89 | K19: 18783.68 | L19: 20264.86 | M19: 15775.31 | O19: =(C19+D19+E19+F19+G19+H19+I19+J19+K19+L19+M19)/12 -> 14607.921
A20: Sudoeste | B20: 21809.85 | C20: 19266.65 | D20: 16581.98 | E20: 14334.25 | F20: 17403.8 | G20: 19475.73 | H20: 22992.38 | I20: 19444.64 | J20: 15245.15 | K20: 18224.85 | L20: 16608.49 | M20: 18105.8 | O20: =(C20+D20+E20+F20+G20+H20+I20+J20+K20+L20+M20)/12 -> 16473.643
A21: Noroeste | D21: 21353.58 | E21: 30809.12 | F21: 35437.47 | G21: 48159.72 | H21: 55238.9 | I21: 53474.74 | J21: 53145.15 | K21: 57749.37 | L21: 49235.12 | M21: 47041.73 | O21: =(C21+D21+E21+F21+G21+H21+I21+J21+K21+L21+M21)/10 -> 45164.49
A22: Total Mês | B22: =B14+B15+B16+B17+B18+B19+B20+B21 -> 114366.93 | C22: =C14+C15+C16+C17+C18+C19+C20+C21 -> 100437.03 | D22: =D14+D15+D16+D17+D18+D19+D20+D21 -> 126804.01 | E22: =E14+E15+E16+E17+E18+E19+E20+E21 -> 137364.78 | F22: =F14+F15+F16+F17+F18+F19+F20+F21 -> 148993.84 | G22: =G14+G15+G16+G17+G18+G19+G20+G21 -> 160865.29 | H22: =H14+H15+H16+H17+H18+H19+H20+H21 -> 184957.64 | I22: =I14+I15+I16+I17+I18+I19+I20+I21 -> 185228.47 | ... M22: =M14+M15+M16+M17+M18+M19+M20+M21 -> 176585.31 | O22: =(C22+D22+E22+F22+G22+H22+I22+J22+K22+L22+M22)/12 -> 147704.55
A23: Total Ano: | B23: =B22+C22+D22+E22+F22+G22+H22+I22+J22+K22+L22+M22 -> 1886821.5
B25: Vendas no Sistema 2025
A26: Lojas | B26: Janeiro | C26: Fevereiro | D26: Março | E26: Abril | F26: Maio | G26: Junho | H26: Julho | I26: Agosto | J26: Setembro | K26: Outubro | L26: Novembro | M26: Dezembro
A27: 202 Norte | B27: 18140.59 | C27: 15528.37 | D27: 15073.15 | E27: 15135.61 | F27: 19623.04 | G27: 18366.98 | H27: 21472.85 | I27: 17722.95 | J27: 19589.33 | K27: 18448.43 | L27: 17093.15 | M27: 12555.4 | O27: 20000
A28: 213 Norte | B28: 16491.46 | C28: 12876.86 | D28: 16473.35 | E28: 5346.9 | F28: 23.4 | G28: 0 | H28: 266.9 | I28: 233 | J28: 110 | K28: 682.8 | L28: 360 | M28: 54.9
A29: 307 Norte | B29: 43525.27 | C29: 33837.39 | D29: 34965.59 | E29: 38467.01 | F29: 47263.05 | G29: 38706.32 | H29: 44217.01 | I29: 42862.3 | J29: 44423.08 | K29: 44606.51 | L29: 38493.02 | M29: 44165.31 | O29: 44000
A30: 313 Norte | B30: 21962.36 | C30: 12537.45 | D30: 19666.08 | E30: 21202.74 | F30: 29454.83 | G30: 26999.2 | H30: 26380.18 | I30: 27309.15 | J30: 26091.28 | K30: 25097.95 | L30: 21978.9 | M30: 21777.68 | O30: 28000
A31: 314 Sul | B31: 15848.95 | C31: 8847.69 | D31: 13651.71 | E31: 15100.58 | F31: 15504.5 | G31: 17680.89 | H31: 13408.4 | I31: 16213 | J31: 15156.9 | K31: 13950.8 | L31: 10917.25 | M31: 5809.86
A32: Lago Norte | B32: 17360.97 | C32: 16812.79 | D32: 16366.79 | E32: 17614.19 | F32: 22195.55 | G32: 22858.11 | H32: 23633.26 | I32: 18961.82 | J32: 23331.76 | K32: 21151.72 | L32: 16791.69 | M32: 18192.62 | O32: 23000
A33: Sudoeste | B33: 21302.49 | C33: 15823.85 | D33: 19665.84 | E33: 20658.61 | F33: 18943.27 | G33: 19884.67 | H33: 18736.87 | I33: 19783.77 | J33: 21980.55 | K33: 18246.38 | L33: 14083.21 | M33: 17840.81 | O33: 21000
A34: Noroeste | B34: 62860.36 | C34: 48283.62 | D34: 56924.27 | E34: 59868.86 | F34: 64708.01 | G34: 55012.69 | H34: 71350.15 | I34: 57628.49 | J34: 64575.91 | K34: 54630.2 | L34: 59398.06 | M34: 55236.21 | O34: 64000
A35: Total Mês | B35: =B27+B28+B29+B30+B31+B32+B33+B34 -> 217492.45 | C35: =C27+C28+C29+C30+C31+C32+C33+C34 -> 164548.02 | D35: =D27+D28+D29+D30+D31+D32+D33+D34 -> 192786.78 | E35: =E27+E28+E29+E30+E31+E32+E33+E34 -> 193394.5 | F35: =F27+F28+F29+F30+F31+F32+F33+F34 -> 217715.65 | G35: =G27+G28+G29+G30+G31+G32+G33+G34 -> 199508.86 | H35: =H27+H28+H29+H30+H31+H32+H33+H34 -> 219465.62 | I35: =I27+I28+I29+I30+I31+I32+I33+I34 -> 200714.48 | ... M35: =M27+M28+M29+M30+M31+M32+M33+M34 -> 175632.79 | O35: =O27+O28+O29+O30+O31+O32+O33+O34 -> 200000
A36: Total Ano: | B36: =B35+C35+D35+E35+F35+G35+H35+I35+J35+K35+L35+M35 -> 2372448
B38: Vendas no Sistema 2026
A39: Lojas | B39: Janeiro | C39: Fevereiro | D39: Março | E39: Abril | F39: Maio | G39: Junho | H39: Julho | I39: Agosto | J39: Setembro | K39: Outubro | L39: Novembro | M39: Dezembro
A40: 202 Norte | B40: =Jan!D128 -> 14956.86 | C40: =Fev!D128 -> 15394.71 | D40: =Mar!D128 -> 0 | E40: =Abr!D128 -> 0 | F40: =Mai!D128 -> 0 | G40: =Jun!D128 -> 0 | H40: =Jul!D128 -> 0 | I40: =Ago!D128 -> 0 | J40: =Set!D128 -> 0 | K40: =Out!D128 -> 0 | L40: =Nov!D128 -> 0 | M40: =Dez!D128 -> 0 | O40: 20000
A41: 213 Norte / SOF | B41: =Jan!D129 -> 0 | C41: =Fev!D129 -> 0 | D41: =Mar!D129 -> 0 | E41: =Abr!D129 -> 0 | F41: =Mai!D129 -> 0 | G41: =Jun!D129 -> 0 | H41: =Jul!D129 -> 0 | I41: =Ago!D129 -> 0 | J41: =Set!D129 -> 0 | K41: =Out!D129 -> 0 | L41: =Nov!D129 -> 0 | M41: =Dez!D129 -> 0
A42: 307 Norte | B42: =Jan!D130 -> 48020.92 | C42: =Fev!D130 -> 32756.95 | D42: =Mar!D130 -> 0 | E42: =Abr!D130 -> 0 | F42: =Mai!D130 -> 0 | G42: =Jun!D130 -> 0 | H42: =Jul!D130 -> 0 | I42: =Ago!D130 -> 0 | J42: =Set!D130 -> 0 | K42: =Out!D130 -> 0 | L42: =Nov!D130 -> 0 | M42: =Dez!D130 -> 0 | O42: 44000
A43: 313 Norte | B43: =Jan!D131 -> 30515.35 | C43: =Fev!D131 -> 18490.14 | D43: =Mar!D131 -> 0 | E43: =Abr!D131 -> 0 | F43: =Mai!D131 -> 0 | G43: =Jun!D131 -> 0 | H43: =Jul!D131 -> 0 | I43: =Ago!D131 -> 0 | J43: =Set!D131 -> 0 | K43: =Out!D131 -> 0 | L43: =Nov!D131 -> 0 | M43: =Dez!D131 -> 0 | O43: 28000
A44: 314 Sul | B44: =Jan!D132 -> 0 | C44: =Fev!D132 -> 0 | D44: =Mar!D132 -> 0 | E44: =Abr!D132 -> 0 | F44: =Mai!D132 -> 0 | G44: =Jun!D132 -> 0 | H44: =Jul!D132 -> 0 | I44: =Ago!D132 -> 0 | J44: =Set!D132 -> 0 | K44: =Out!D132 -> 0 | L44: =Nov!D132 -> 0 | M44: =Dez!D132 -> 0
A45: Lago Norte | B45: =Jan!D127 -> 19569.73 | C45: =Fev!D127 -> 17496.33 | D45: =Mar!D127 -> 0 | E45: =Abr!D127 -> 0 | F45: =Mai!D127 -> 0 | G45: =Jun!D127 -> 0 | H45: =Jul!D127 -> 0 | I45: =Ago!D127 -> 0 | J45: =Set!D127 -> 0 | K45: =Out!D127 -> 0 | L45: =Nov!D127 -> 0 | M45: =Dez!D127 -> 0 | O45: 23000
A46: Sudoeste | B46: =Jan!D133 -> 19482.65 | C46: =Fev!D133 -> 10796.04 | D46: =Mar!D133 -> 0 | E46: =Abr!D133 -> 0 | F46: =Mai!D133 -> 0 | G46: =Jun!D133 -> 0 | H46: =Jul!D133 -> 0 | I46: =Ago!D133 -> 0 | J46: =Set!D133 -> 0 | K46: =Out!D133 -> 0 | L46: =Nov!D133 -> 0 | M46: =Dez!D133 -> 0 | O46: 21000
A47: Noroeste | B47: =Jan!D134 -> 63686.35 | C47: =Fev!D134 -> 42089.98 | D47: =Mar!D134 -> 0 | E47: =Abr!D134 -> 0 | F47: =Mai!D134 -> 0 | G47: =Jun!D134 -> 0 | H47: =Jul!D134 -> 0 | I47: =Ago!D134 -> 0 | J47: =Set!D134 -> 0 | K47: =Out!D134 -> 0 | L47: =Nov!D134 -> 0 | M47: =Dez!D134 -> 0 | O47: 64000
A48: Total Mês | B48: =B40+B41+B42+B43+B44+B45+B46+B47 -> 196231.86 | C48: =C40+C41+C42+C43+C44+C45+C46+C47 -> 137024.15 | D48: =D40+D41+D42+D43+D44+D45+D46+D47 -> 0 | E48: =E40+E41+E42+E43+E44+E45+E46+E47 -> 0 | F48: =F40+F41+F42+F43+F44+F45+F46+F47 -> 0 | G48: =G40+G41+G42+G43+G44+G45+G46+G47 -> 0 | H48: =H40+H41+H42+H43+H44+H45+H46+H47 -> 0 | I48: =I40+I41+I42+I43+I44+I45+I46+I47 -> 0 | ... M48: =M40+M41+M42+M43+M44+M45+M46+M47 -> 0 | O48: =O40+O41+O42+O43+O44+O45+O46+O47 -> 200000 | P48: =O48/2 -> 100000
A49: Total Ano: | B49: =B48+C48+D48+E48+F48+G48+H48+I48+J48+K48+L48+M48 -> 333256.01 | P49: 297
B74: Quantidade de peças por mês em 2026
A75: Lojas | B75: Janeiro | C75: Fevereiro | D75: Março | E75: Abril | F75: Maio | G75: Junho | H75: julho | I75: Agosto | J75: Setembro | K75: Outubro | L75: Novembro | M75: Dezembro
A76: 202 Norte | B76: =Jan!H128 -> 680 | C76: =Fev!H128 -> 656 | D76: =Mar!H128 -> 0 | E76: =Abr!H128 -> 0 | F76: =Mai!H128 -> 0 | G76: =Jun!H128 -> 0 | H76: =Jul!H128 -> 0 | I76: =Ago!H128 -> 0 | J76: =Set!H128 -> 0 | K76: =Out!H128 -> 0 | L76: =Nov!H128 -> 0 | M76: =Dez!H128 -> 0
A77: 213 Norte | B77: =Jan!H129 -> 0 | C77: =Fev!H129 -> 0 | D77: =Mar!H129 -> 0 | E77: =Abr!H129 -> 0 | F77: =Mai!H129 -> 0 | G77: =Jun!H129 -> 0 | H77: =Jul!H129 -> 0 | I77: =Ago!H129 -> 0 | J77: =Set!H129 -> 0 | K77: =Out!H129 -> 0 | L77: =Nov!H129 -> 0 | M77: =Dez!H129 -> 0
A78: 307 Norte | B78: =Jan!H130 -> 1767 | C78: =Fev!H130 -> 1516 | D78: =Mar!H130 -> 0 | E78: =Abr!H130 -> 0 | F78: =Mai!H130 -> 0 | G78: =Jun!H130 -> 0 | H78: =Jul!H130 -> 0 | I78: =Ago!H130 -> 0 | J78: =Set!H130 -> 0 | K78: =Out!H130 -> 0 | L78: =Nov!H130 -> 0 | M78: =Dez!H130 -> 0
A79: 313 Norte | B79: =Jan!H131 -> 1254 | C79: =Fev!H131 -> 909 | D79: =Mar!H131 -> 0 | E79: =Abr!H131 -> 0 | F79: =Mai!H131 -> 0 | G79: =Jun!H131 -> 0 | H79: =Jul!H131 -> 0 | I79: =Ago!H131 -> 0 | J79: =Set!H131 -> 0 | K79: =Out!H131 -> 0 | L79: =Nov!H131 -> 0 | M79: =Dez!H131 -> 0
A80: 314 Sul | B80: =Jan!H132 -> 27 | C80: =Fev!H132 -> 0 | D80: =Mar!H132 -> 0 | E80: =Abr!H132 -> 0 | F80: =Mai!H132 -> 0 | G80: =Jun!H132 -> 0 | H80: =Jul!H132 -> 0 | I80: =Ago!H132 -> 0 | J80: =Set!H132 -> 0 | K80: =Out!H132 -> 0 | L80: =Nov!H132 -> 0 | M80: =Dez!H132 -> 0
A81: Lago Norte | B81: =Jan!H127 -> 782 | C81: =Fev!H127 -> 724 | D81: =Mar!H127 -> 0 | E81: =Abr!H127 -> 0 | F81: =Mai!H127 -> 0 | G81: =Jun!H127 -> 0 | H81: =Jul!H127 -> 0 | I81: =Ago!H127 -> 0 | J81: =Set!H127 -> 0 | K81: =Out!H127 -> 0 | L81: =Nov!H127 -> 0 | M81: =Dez!H127 -> 0
A82: Sudoeste | B82: =Jan!H133 -> 812 | C82: =Fev!H133 -> 525 | D82: =Mar!H133 -> 0 | E82: =Abr!H133 -> 0 | F82: =Mai!H133 -> 0 | G82: =Jun!H133 -> 0 | H82: =Jul!H133 -> 0 | I82: =Ago!H133 -> 0 | J82: =Set!H133 -> 0 | K82: =Out!H133 -> 0 | L82: =Nov!H133 -> 0 | M82: =Dez!H133 -> 0
A83: Noroeste | B83: =Jan!H134 -> 2568 | C83: =Fev!H134 -> 2206 | D83: =Mar!H134 -> 0 | E83: =Abr!H134 -> 0 | F83: =Mai!H134 -> 0 | G83: =Jun!H134 -> 0 | H83: =Jul!H134 -> 0 | I83: =Ago!H134 -> 0 | J83: =Set!H134 -> 0 | K83: =Out!H134 -> 0 | L83: =Nov!H134 -> 0 | M83: =Dez!H134 -> 0
A84: Total Mês | B84: =B76+B77+B78+B79+B80+B81+B82+B83 -> 7890 | C84: =C76+C77+C78+C79+C81+C82+C83 -> 6536 | D84: =D76+D77+D78+D79+D80+D81+D82+D83 -> 0 | E84: =E76+E77+E78+E79+E80+E81+E82+E83 -> 0 | F84: =F76+F77+F78+F79+F80+F81+F82+F83 -> 0 | G84: =G76+G77+G78+G79+G80+G81+G82+G83 -> 0 | H84: =H76+H77+H78+H79+H80+H81+H82+H83 -> 0 | I84: =I76+I77+I78+I79+I80+I81+I82+I83 -> 0 | J84: =J76+J77+J78+J79+J80+J81+J82+J83 -> 0 | K84: =K76+K77+K78+K79+K80+K81+K82+K83 -> 0 | ... M84: =M76+M77+M78+M79+M80+M81+M82+M83 -> 0
A85: Total Ano: | B85: =B84+C84+D84+E84+F84+G84+H84+I84+J84+K84+L84+M84 -> 14426
B88: Quantidade de peças por mês em 2025
A89: Lojas | B89: Janeiro | C89: Fevereiro | D89: Março | E89: Abril | F89: Maio | G89: Junho | H89: julho | I89: Agosto | J89: Setembro | K89: Outubro | L89: Novembro | M89: Dezembro
A90: 202 Norte | B90: 923 | C90: 807
A91: 213 Norte | B91: 873 | C91: 632
A92: 307 Norte | B92: 1707 | C92: 1623
A93: 313 Norte | B93: 983 | C93: 696
A94: 314 Sul | B94: 662 | C94: 508
A95: Lago Norte | B95: 723 | C95: 707
A96: Sudoeste | B96: 929 | C96: 833
A97: Noroeste | B97: 3142 | C97: 2771
A98: Total Mês | B98: =B90+B91+B92+B93+B94+B95+B96+B97 -> 9942 | C98: =C90+C91+C92+C93+C95+C96+C97 -> 8069 | D98: =D90+D91+D92+D93+D94+D95+D96+D97 -> 0 | E98: =E90+E91+E92+E93+E94+E95+E96+E97 -> 0 | F98: =F90+F91+F92+F93+F94+F95+F96+F97 -> 0 | G98: =G90+G91+G92+G93+G94+G95+G96+G97 -> 0 | H98: =H90+H91+H92+H93+H94+H95+H96+H97 -> 0 | I98: =I90+I91+I92+I93+I94+I95+I96+I97 -> 0 | J98: =J90+J91+J92+J93+J94+J95+J96+J97 -> 0 | K98: =K90+K91+K92+K93+K94+K95+K96+K97 -> 0 | ... M98: =M90+M91+M92+M93+M94+M95+M96+M97 -> 0
A99: Total Ano: | B99: =B98+C98+D98+E98+F98+G98+H98+I98+J98+K98+L98+M98 -> 18011
B129: 1 | C129: ok, para esse mês meta de 10% e como referência pegamos maio. Próximo mês meta de 15% até chegar em 30%
B130: 2 | C130: loja 02 no Noroeste, 4 meses de carência, apos o habite-se e
B131: 3 | C131: ar condicionado Lago Norte, 12 vezes na Amazon
B132: 4 | C132: aumento sudoeste, aumentar a partir amanhã terça 07/05
B133: 5 | C133: fazer novas publicações em grupos dos bairros, investir mais no Google
B134: 6 | C134: cancelar a Cactus
B135: 7 | C135: 7 máquinas ficam em 2.000,00. Fazer mais para frente
B136: 8 | C136: inventário 307 para levantar valores não pagos
B137: 9 | C137: Brisas do Lago, reunião dia 07/05 foi remarcada
B142: Metas de vendas
A143: Lojas | B143: Faturamento Maio | C143: Meta 10%
A144: 202 | B144: 13000 | C144: =B144*0.1 -> 1300
A145: 213 | B145: 16500 | C145: =B145*0.1 -> 1650
A146: 307 | B146: 36500 | C146: =B146*0.1 -> 3650
A147: 313 | B147: 13000 | C147: =B147*0.1 -> 1300
A148: Lago | B148: 12700 | C148: =B148*0.1 -> 1270
A149: Sudoeste | B149: 14300 | C149: =B149*0.3 -> 4290
A150: Noroeste | B150: 30800 | C150: =B150*0.1 -> 3080

Sheet Fev
B1: Dia | C1: Lojas | D1: Faturamento dia | E1: Não pago dia | F1: Recebido dia | G1: Não pago Acumulado | H1: Peças | I1: Dia | J1: Lojas | K1: Faturamento | L1: Não pago dia | M1: Recebido dia | N1: Não pago Acumulado | O1: Peças | P1: Dia | Q1: Lojas | R1: Faturamento | S1: Não pago dia | T1: Recebido dia | U1: Não pago Acumulado | V1: Peças | W1: Dia | X1: Lojas | Y1: Faturamento | Z1: Não pago dia | AA1: Recebido dia | AB1: Não pago Acumulado | AC1: Peças | AD1: Dia | AE1: Lojas | AF1: Faturamento | AG1: Não pago dia | AH1: Recebido dia | AI1: Não pago Acumulado | AJ1: Peças | AM1: Lojas | AN1: Faturamento | AO1: Não pago dia | AP1: Recebido | AQ1: Peças
A2: Segunda-feira | C2: Lago Norte | I2: 46055 | J2: Lago Norte | K2: 358.6 | L2: 54.9 | M2: 430.7 | N2: 857 | O2: 33 | P2: 46062 | Q2: Lago Norte | R2: 474.91 | S2: 0 | T2: 474.91 | U2: 1661.4 | V2: 28 | W2: 46069 | X2: Lago Norte | Y2: 451.8 | Z2: 0 | AA2: 451.8 | AB2: 1876.4 | AC2: 18 | AD2: 46076 | AE2: Lago Norte | AF2: 611.61 | AG2: 232.87 | AH2: 433.64 | AI2: 1300.97 | AJ2: 43 | AL2: Faturamento Total das Segundas-feiras | AM2: Lago Norte | AN2: =D2+K2+R2+Y2+AF2 -> 1896.92 | AO2: =E2+L2+S2+Z2+AG2 -> 287.77 | AP2: =F2+M2+T2+AA2+AH2 -> 1791.05 | AQ2: =H2+O2+V2+AC2+AJ2 -> 122
C3: 202 Norte | J3: 202 Norte | K3: 417 | L3: 0 | M3: 517 | N3: 2407.4 | O3: 13 | Q3: 202 Norte | R3: 170 | S3: 45 | T3: 125 | U3: 920.6 | V3: 39 | X3: 202 Norte | Y3: 214 | Z3: 0 | AA3: 480 | AB3: 1177.4 | AC3: 11 | AE3: 202 Norte | AF3: 395.9 | AG3: 305.9 | AH3: 135 | AI3: 2326.1 | AJ3: 17 | AM3: 202 Norte | AN3: =D3+K3+R3+Y3+AF3 -> 1196.9 | AO3: =E3+L3+S3+Z3+AG3 -> 350.9 | AP3: =F3+M3+T3+AA3+AH3 -> 1257 | AQ3: =H3+O3+V3+AC3+AJ3 -> 80
C4: 213 Norte | J4: 213 Norte | Q4: 213 Norte | X4: 213 Norte | AE4: 213 Norte | AM4: 213 Norte | AN4: =D4+K4+R4+Y4+AF4 -> 0 | AO4: =E4+L4+S4+Z4+AG4 -> 0 | AP4: =F4+M4+T4+AA4+AH4 -> 0 | AQ4: =H4+O4+V4+AC4+AJ4 -> 0
C5: 307 Norte | J5: 307 Norte | K5: 2695.4 | L5: 752 | M5: 2115.4 | N5: 5889.43 | O5: 100 | Q5: 307 Norte | R5: 3038 | S5: 853 | T5: 2970.08 | U5: 5906.96 | V5: 150 | X5: 307 Norte | Y5: 1102.7 | Z5: 186.9 | AA5: 1289.91 | AB5: 5087.45 | AC5: 47 | AE5: 307 Norte | AF5: 694.8 | AG5: 132.9 | AH5: 651.9 | AI5: 5474.51 | AJ5: 23 | AM5: 307 Norte | AN5: =D5+K5+R5+Y5+AF5 -> 7530.9 | AO5: =E5+L5+S5+Z5+AG5 -> 1924.8 | AP5: =F5+M5+T5+AA5+AH5 -> 7027.29 | AQ5: =H5+O5+V5+AC5+AJ5 -> 320
C6: 313 Norte | J6: 313 Norte | K6: =3947.6-2664 -> 1283.6 | L6: 0 | M6: 1363.6 | N6: =4623.35-2664 -> 1959.35 | O6: =162-75 -> 87 | Q6: 313 Norte | R6: 962.9 | S6: 60 | T6: 902.9 | U6: 1562.6 | V6: 43 | X6: 313 Norte | Y6: 407.9 | Z6: 0 | AA6: 407.9 | AB6: 1533.6 | AC6: 28 | AE6: 313 Norte | AF6: 1463.3 | AG6: 423 | AH6: 1040.3 | AI6: 1942.1 | AJ6: 57 | AM6: 313 Norte | AN6: =D6+K6+R6+Y6+AF6 -> 4117.7 | AO6: =E6+L6+S6+Z6+AG6 -> 483 | AP6: =F6+M6+T6+AA6+AH6 -> 3714.7 | AQ6: =H6+O6+V6+AC6+AJ6 -> 215
C7: 314 Sul | J7: 314 Sul | Q7: 314 Sul | X7: 314 Sul | AE7: 314 Sul | AM7: 314 Sul | AN7: =D7+K7+R7+Y7+AF7 -> 0 | AO7: =E7+L7+S7+Z7+AG7 -> 0 | AP7: =F7+M7+T7+AA7+AH7 -> 0 | AQ7: =H7+O7+V7+AC7+AJ7 -> 0
C8: Sudoeste | J8: Sudoeste | K8: 817 | L8: 42 | M8: 1051 | N8: 2242.29 | O8: 42 | Q8: Sudoeste | R8: 314.9 | S8: 54.9 | T8: 676.9 | U8: 2066.79 | V8: 25 | X8: Sudoeste | AE8: Sudoeste | AF8: 807.8 | AG8: 807.8 | AH8: 113.35 | AI8: 2703.24 | AJ8: 46 | AM8: Sudoeste | AN8: =D8+K8+R8+Y8+AF8 -> 1939.7 | AO8: =E8+L8+S8+Z8+AG8 -> 904.7 | AP8: =F8+M8+T8+AA8+AH8 -> 1841.25 | AQ8: =H8+O8+V8+AC8+AJ8 -> 113
C9: Noroeste | J9: Noroeste | K9: 2308.7 | L9: 0 | M9: 2843.6 | N9: 6485.54 | O9: 139 | Q9: Noroeste | R9: 4599 | S9: 711 | T9: 3906 | U9: 7330.24 | V9: 195 | X9: Noroeste | Y9: 898.6 | Z9: 164.7 | AA9: 922.9 | AB9: 7214.64 | AC9: 37 | AE9: Noroeste | AF9: 3714.34 | AG9: 776.4 | AH9: 3119.22 | AI9: 7950.16 | AJ9: 138 | AM9: Noroeste | AN9: =D9+K9+R9+Y9+AF9 -> 11520.64 | AO9: =E9+L9+S9+Z9+AG9 -> 1652.1 | AP9: =F9+M9+T9+AA9+AH9 -> 10791.72 | AQ9: =H9+O9+V9+AC9+AJ9 -> 509
C10: Total: | D10: =D2+D3+D4+D5+D6+D7+D8+D9 -> 0 | E10: =E2+E3+E4+E5+E6+E7+E8+E9 -> 0 | F10: =F2+F3+F4+F5+F6+F7+F8+F9 -> 0 | G10: =G2+G3+G4+G5+G6+G7+G8+G9 -> 0 | H10: =H2+H3+H4+H5+H6+H7+H8+H9 -> 0 | J10: Total: | K10: =K2+K3+K4+K5+K6+K7+K8+K9 -> 7880.3 | L10: =L2+L3+L4+L5+L6+L7+L8+L9 -> 848.9 | M10: =M2+M3+M4+M5+M6+M7+M8+M9 -> 8321.3 | N10: =N2+N3+N4+N5+N6+N7+N8+N9 -> 19841.01 | O10: =O2+O3+O4+O5+O6+O7+O8+O9 -> 414 | Q10: Total: | R10: =R2+R3+R4+R5+R6+R7+R8+R9 -> 9559.71 | S10: =S2+S3+S4+S5+S6+S7+S8+S9 -> 1723.9 | T10: =T2+T3+T4+T5+T6+T7+T8+T9 -> 9055.79 | U10: =U2+U3+U4+U5+U6+U7+U8+U9 -> 19448.59 | V10: =V2+V3+V4+V5+V6+V7+V8+V9 -> 480 | X10: Total: | Y10: =Y2+Y3+Y4+Y5+Y6+Y7+Y8+Y9 -> 3075 | Z10: =Z2+Z3+Z4+Z5+Z6+Z7+Z8+Z9 -> 351.6 | AA10: =AA2+AA3+AA4+AA5+AA6+AA7+AA8+AA9 -> 3552.51 | AB10: =AB2+AB3+AB4+AB5+AB6+AB7+AB8+AB9 -> 16889.49 | AC10: =AC2+AC3+AC4+AC5+AC6+AC7+AC8+AC9 -> 141 | AE10: Total: | AF10: =AF2+AF3+AF4+AF5+AF6+AF7+AF8+AF9 -> 7687.75 | AG10: =AG2+AG3+AG4+AG5+AG6+AG7+AG8+AG9 -> 2678.87 | AH10: =AH2+AH3+AH4+AH5+AH6+AH7+AH8+AH9 -> 5493.41 | AI10: =AI2+AI3+AI4+AI5+AI6+AI7+AI8+AI9 -> 21697.08 | AJ10: =AJ2+AJ3+AJ4+AJ5+AJ6+AJ7+AJ8+AJ9 -> 324 | AM10: Total: | AN10: =AN2+AN3+AN4+AN5+AN6+AN7+AN8+AN9 -> 28202.76 | AO10: =AO2+AO3+AO4+AO5+AO6+AO7+AO8+AO9 -> 5603.27 | AP10: =AP2+AP3+AP4+AP5+AP6+AP7+AP8+AP9 -> 26423.01 | AQ10: =AQ2+AQ3+AQ4+AQ5+AQ6+AQ7+AQ8+AQ9 -> 1359
C11: Faturado dia real | D11: =D10-E10 -> 0 | J11: Faturado dia real | K11: =K10-L10 -> 7031.4 | Q11: Faturado dia real | R11: =R10-S10 -> 7835.81 | X11: Faturado dia real | Y11: =Y10-Z10 -> 2723.4 | AE11: Faturado dia real | AF11: =AF10-AG10 -> 5008.88 | AM11: Fat. Real | AN11: =AN10-AO10 -> 22599.49
C12: Recebido dia real | D12: =F10-E10 -> 0 | J12: Recebido dia real | K12: =M10-L10 -> 7472.4 | Q12: Recebido dia real | R12: =T10-S10 -> 7331.89 | X12: Recebido dia real | Y12: =AA10-Z10 -> 3200.91 | AE12: Recebido dia real | AF12: =AH10-AG10 -> 2814.54
B13: Dia | C13: Lojas | D13: Faturamento dia | E13: Não pago dia | F13: Recebido dia | G13: Não pago Acumulado | H13: Peças | I13: Dia | J13: Lojas | K13: Faturamento | L13: Não pago dia | M13: Recebido dia | N13: Não pago Acumulado | O13: Peças | P13: Dia | Q13: Lojas | R13: Faturamento | S13: Não pago dia | T13: Recebido dia | U13: Não pago Acumulado | V13: Peças | W13: Dia | X13: Lojas | Y13: Faturamento | Z13: Não pago dia | AA13: Recebido dia | AB13: Não pago Acumulado | AC13: Peças | AD13: Dia | AE13: Lojas | AF13: Faturamento | AG13: Não pago dia | AH13: Recebido dia | AI13: Não pago Acumulado | AJ13: Peças | AM13: Lojas | AN13: Faturamento | AO13: Não pago dia | AP13: Recebido | AQ13: Peças
A14: Terça-feira | C14: Lago Norte | I14: 46056 | J14: Lago Norte | K14: 573.8 | L14: 30 | M14: 704.8 | N14: 726 | O14: 19 | P14: 46063 | Q14: Lago Norte | R14: 951.5 | S14: 190 | T14: 761.5 | U14: 1851.4 | V14: 35 | W14: 46070 | X14: Lago Norte | AD14: 46077 | AE14: Lago Norte | AF14: 890.7 | AG14: 0 | AH14: 975.7 | AI14: 1215.97 | AJ14: 40 | AL14: Faturamento Total das Terças-feiras | AM14: Lago Norte | AN14: =D14+K14+R14+Y14+AF14 -> 2416 | AO14: =E14+L14+S14+Z14+AG14 -> 220 | AP14: =F14+M14+T14+AA14+AH14 -> 2442 | AQ14: =H14+O14+V14+AC14+AJ14 -> 94
C15: 202 Norte | J15: 202 Norte | K15: 90.2 | L15: 30 | M15: 120.2 | N15: 2377.4 | O15: 15 | Q15: 202 Norte | R15: 927 | S15: 406 | T15: 575 | U15: 1272.6 | V15: 45 | X15: 202 Norte | AE15: 202 Norte | AF15: 447.3 | AG15: 329.4 | AH15: 117.9 | AI15: 2655.5 | AJ15: 21 | AM15: 202 Norte | AN15: =D15+K15+R15+Y15+AF15 -> 1464.5 | AO15: =E15+L15+S15+Z15+AG15 -> 765.4 | AP15: =F15+M15+T15+AA15+AH15 -> 813.1 | AQ15: =H15+O15+V15+AC15+AJ15 -> 81
C16: 213 Norte | J16: 213 Norte | Q16: 213 Norte | X16: 213 Norte | AE16: 213 Norte | AM16: 213 Norte | AN16: =D16+K16+R16+Y16+AF16 -> 0 | AO16: =E16+L16+S16+Z16+AG16 -> 0 | AP16: =F16+M16+T16+AA16+AH16 -> 0 | AQ16: =H16+O16+V16+AC16+AJ16 -> 0
C17: 307 Norte | J17: 307 Norte | K17: 2241.63 | L17: 55.33 | M17: 2365.3 | N17: 5765.76 | O17: 93 | Q17: 307 Norte | R17: 1353.8 | S17: 75 | T17: 1594.2 | U17: 5659.96 | V17: 73 | X17: 307 Norte | AE17: 307 Norte | AF17: 1505.9 | AG17: 80 | AH17: 1473.9 | AI17: 5506.51 | AJ17: 90 | AM17: 307 Norte | AN17: =D17+K17+R17+Y17+AF17 -> 5101.33 | AO17: =E17+L17+S17+Z17+AG17 -> 210.33 | AP17: =F17+M17+T17+AA17+AH17 -> 5433.4 | AQ17: =H17+O17+V17+AC17+AJ17 -> 256
C18: 313 Norte | J18: 313 Norte | K18: 687 | L18: 80 | M18: 1234.55 | N18: =4075.8-2664 -> 1411.8 | O18: 46 | Q18: 313 Norte | R18: 873 | S18: 249 | T18: 734 | U18: 1701.6 | V18: 39 | X18: 313 Norte | AE18: 313 Norte | AF18: 707.9 | AG18: 0 | AH18: 707.9 | AI18: 1942.1 | AJ18: 29 | AM18: 313 Norte | AN18: =D18+K18+R18+Y18+AF18 -> 2267.9 | AO18: =E18+L18+S18+Z18+AG18 -> 329 | AP18: =F18+M18+T18+AA18+AH18 -> 2676.45 | AQ18: =H18+O18+V18+AC18+AJ18 -> 114
C19: 314 Sul | J19: 314 Sul | Q19: 314 Sul | X19: 314 Sul | AE19: 314 Sul | AM19: 314 Sul | AN19: =D19+K19+R19+Y19+AF19 -> 0 | AO19: =E19+L19+S19+Z19+AG19 -> 0 | AP19: =F19+M19+T19+AA19+AH19 -> 0 | AQ19: =H19+O19+V19+AC19+AJ19 -> 0
C20: Sudoeste | J20: Sudoeste | K20: 441.04 | L20: 0 | M20: 476.04 | N20: 2207.29 | O20: 23 | Q20: Sudoeste | R20: 163.9 | S20: 0 | T20: 213.9 | U20: 2016.79 | V20: 11 | X20: Sudoeste | AE20: Sudoeste | AF20: 926 | AG20: 0 | AH20: 1203 | AI20: 2426.24 | AJ20: 25 | AM20: Sudoeste | AN20: =D20+K20+R20+Y20+AF20 -> 1530.94 | AO20: =E20+L20+S20+Z20+AG20 -> 0 | AP20: =F20+M20+T20+AA20+AH20 -> 1892.94 | AQ20: =H20+O20+V20+AC20+AJ20 -> 59
C21: Noroeste | J21: Noroeste | K21: 992.7 | L21: 328.9 | M21: 728.8 | N21: 6749.44 | O21: 53 | Q21: Noroeste | R21: 2034.7 | S21: 68 | T21: 2020.7 | U21: 7344.24 | V21: 139 | X21: Noroeste | AE21: Noroeste | AF21: 1434.4 | AG21: 276 | AH21: 1538.3 | AI21: 7660.26 | AJ21: 90 | AM21: Noroeste | AN21: =D21+K21+R21+Y21+AF21 -> 4461.8 | AO21: =E21+L21+S21+Z21+AG21 -> 672.9 | AP21: =F21+M21+T21+AA21+AH21 -> 4287.8 | AQ21: =H21+O21+V21+AC21+AJ21 -> 282
C22: Total: | D22: =D14+D15+D16+D17+D18+D19+D20+D21 -> 0 | E22: =E14+E15+E16+E17+E18+E19+E20+E21 -> 0 | F22: =F14+F15+F16+F17+F18+F19+F20+F21 -> 0 | G22: =G14+G15+G16+G17+G18+G19+G20+G21 -> 0 | H22: =H14+H15+H16+H17+H18+H19+H20+H21 -> 0 | J22: Total: | K22: =K14+K15+K16+K17+K18+K19+K20+K21 -> 5026.37 | L22: =L14+L15+L16+L17+L18+L19+L20+L21 -> 524.23 | M22: =M14+M15+M16+M17+M18+M19+M20+M21 -> 5629.69 | N22: =N14+N15+N16+N17+N18+N19+N20+N21 -> 19237.69 | O22: =O14+O15+O16+O17+O18+O19+O20+O21 -> 249 | Q22: Total: | R22: =R14+R15+R16+R17+R18+R19+R20+R21 -> 6303.9 | S22: =S14+S15+S16+S17+S18+S19+S20+S21 -> 988 | T22: =T14+T15+T16+T17+T18+T19+T20+T21 -> 5899.3 | U22: =U14+U15+U16+U17+U18+U19+U20+U21 -> 19846.59 | V22: =V14+V15+V16+V17+V18+V19+V20+V21 -> 342 | X22: Total: | Y22: =Y14+Y15+Y16+Y17+Y18+Y19+Y20+Y21 -> 0 | Z22: =Z14+Z15+Z16+Z17+Z18+Z19+Z20+Z21 -> 0 | AA22: =AA14+AA15+AA16+AA17+AA18+AA19+AA20+AA21 -> 0 | AB22: =AB14+AB15+AB16+AB17+AB18+AB19+AB20+AB21 -> 0 | AC22: =AC14+AC15+AC16+AC17+AC18+AC19+AC20+AC21 -> 0 | AE22: Total: | AF22: =AF14+AF15+AF16+AF17+AF18+AF19+AF20+AF21 -> 5912.2 | AG22: =AG14+AG15+AG16+AG17+AG18+AG19+AG20+AG21 -> 685.4 | AH22: =AH14+AH15+AH16+AH17+AH18+AH19+AH20+AH21 -> 6016.7 | AI22: =AI14+AI15+AI16+AI17+AI18+AI19+AI20+AI21 -> 21406.58 | AJ22: =AJ14+AJ15+AJ16+AJ17+AJ18+AJ19+AJ20+AJ21 -> 295 | AM22: Total: | AN22: =AN14+AN15+AN16+AN17+AN18+AN19+AN20+AN21 -> 17242.47 | AO22: =AO14+AO15+AO16+AO17+AO18+AO19+AO20+AO21 -> 2197.63 | AP22: =AP14+AP15+AP16+AP17+AP18+AP19+AP20+AP21 -> 17545.69 | AQ22: =AQ14+AQ15+AQ16+AQ17+AQ18+AQ19+AQ20+AQ21 -> 886
C23: Faturado dia real | D23: =D22-E22 -> 0 | J23: Faturado dia real | K23: =K22-L22 -> 4502.14 | Q23: Faturado dia real | R23: =R22-S22 -> 5315.9 | X23: Faturado dia real | Y23: =Y22-Z22 -> 0 | AE23: Faturado dia real | AF23: =AF22-AG22 -> 5226.8 | AM23: Fat. Real | AN23: =AN22-AO22 -> 15044.84
C24: Recebido dia real | D24: =F22-E22 -> 0 | J24: Recebido dia real | K24: =M22-L22 -> 5105.46 | Q24: Recebido dia real | R24: =T22-S22 -> 4911.3 | X24: Recebido dia real | Y24: =AA22-Z22 -> 0 | AE24: Recebido dia real | AF24: =AH22-AG22 -> 5331.3
B25: Dia | C25: Lojas | D25: Faturamento dia | E25: Não pago dia | F25: Recebido dia | G25: Não pago Acumulado | H25: Peças | I25: Dia | J25: Lojas | K25: Faturamento | L25: Não pago dia | M25: Recebido dia | N25: Não pago Acumulado | O25: Peças | P25: Dia | Q25: Lojas | R25: Faturamento | S25: Não pago dia | T25: Recebido dia | U25: Não pago Acumulado | V25: Peças | W25: Dia | X25: Lojas | Y25: Faturamento | Z25: Não pago dia | AA25: Recebido dia | AB25: Não pago Acumulado | AC25: Peças | AD25: Dia | AE25: Lojas | AF25: Faturamento | AG25: Não pago dia | AH25: Recebido dia | AI25: Não pago Acumulado | AJ25: Peças | AM25: Lojas | AN25: Faturamento | AO25: Não pago dia | AP25: Recebido | AQ25: Peças
A26: Quarta-feira | C26: Lago Norte | I26: 46057 | J26: Lago Norte | K26: 913 | L26: 75 | M26: 838 | N26: 801 | O26: 38 | P26: 46064 | Q26: Lago Norte | R26: 1026 | S26: 0 | T26: 1056 | U26: 1821.4 | V26: 29 | W26: 46071 | X26: Lago Norte | Y26: 996.5 | Z26: 105 | AA26: 1857.1 | AB26: 1015.8 | AC26: 14 | AD26: 46078 | AE26: Lago Norte | AF26: 1136 | AG26: 60 | AH26: 1876 | AI26: 1275.97 | AJ26: 56 | AL26: Faturamento Total das Quartas-feiras | AM26: Lago Norte | AN26: =D26+K26+R26+Y26+AF26 -> 4071.5 | AO26: =E26+L26+S26+Z26+AG26 -> 240 | AP26: =F26+M26+T26+AA26+AH26 -> 5627.1 | AQ26: =H26+O26+V26+AC26+AJ26 -> 137
C27: 202 Norte | J27: 202 Norte | K27: 623.6 | L27: 36 | M27: 587.6 | N27: 2413.4 | O27: 33 | Q27: 202 Norte | R27: 611.8 | S27: 91.9 | T27: 519.9 | U27: 1364.5 | V27: 28 | X27: 202 Norte | Y27: 198 | Z27: 0 | AA27: 250 | AB27: 1125.4 | AC27: 16 | AE27: 202 Norte | AF27: 654.62 | AG27: 473.62 | AH27: 181 | AI27: 3129.12 | AJ27: 20 | AM27: 202 Norte | AN27: =D27+K27+R27+Y27+AF27 -> 2088.02 | AO27: =E27+L27+S27+Z27+AG27 -> 601.52 | AP27: =F27+M27+T27+AA27+AH27 -> 1538.5 | AQ27: =H27+O27+V27+AC27+AJ27 -> 97
C28: 213 Norte | J28: 213 Norte | Q28: 213 Norte | X28: 213 Norte | AE28: 213 Norte | AM28: 213 Norte | AN28: =D28+K28+R28+Y28+AF28 -> 0 | AO28: =E28+L28+S28+Z28+AG28 -> 0 | AP28: =F28+M28+T28+AA28+AH28 -> 0 | AQ28: =H28+O28+V28+AC28+AJ28 -> 0
C29: 307 Norte | J29: 307 Norte | K29: 1985 | L29: 303.8 | M29: 2389 | N29: 5361.76 | O29: 83 | Q29: 307 Norte | R29: 923.4 | S29: 265.5 | T29: 966.8 | U29: 5616.56 | V29: 39 | X29: 307 Norte | Y29: 888.4 | Z29: 65 | AA29: 823.48 | AB29: 5152.45 | AC29: 53 | AE29: 307 Norte | AF29: 2519.7 | AG29: 1152.9 | AH29: 3099.08 | AI29: 4829.56 | AJ29: 55 | AM29: 307 Norte | AN29: =D29+K29+R29+Y29+AF29 -> 6316.5 | AO29: =E29+L29+S29+Z29+AG29 -> 1787.2 | AP29: =F29+M29+T29+AA29+AH29 -> 7278.36 | AQ29: =H29+O29+V29+AC29+AJ29 -> 230
C30: 313 Norte | J30: 313 Norte | K30: 840 | L30: 0 | M30: 920 | N30: =3995.8-2664 -> 1331.8 | O30: 28 | Q30: 313 Norte | R30: 408 | S30: 135 | T30: 582 | U30: 1527.6 | V30: 21 | X30: 313 Norte | Y30: 91 | Z30: 0 | AA30: 145.9 | AB30: 1478.7 | AC30: 6 | AE30: 313 Norte | AF30: 795 | AG30: 46 | AH30: 1174 | AI30: 1563.1 | AJ30: 88 | AM30: 313 Norte | AN30: =D30+K30+R30+Y30+AF30 -> 2134 | AO30: =E30+L30+S30+Z30+AG30 -> 181 | AP30: =F30+M30+T30+AA30+AH30 -> 2821.9 | AQ30: =H30+O30+V30+AC30+AJ30 -> 143
C31: 314 Sul | J31: 314 Sul | Q31: 314 Sul | X31: 314 Sul | AE31: 314 Sul | AM31: 314 Sul | AN31: =D31+K31+R31+Y31+AF31 -> 0 | AO31: =E31+L31+S31+Z31+AG31 -> 0 | AP31: =F31+M31+T31+AA31+AH31 -> 0 | AQ31: =H31+O31+V31+AC31+AJ31 -> 0
C32: Sudoeste | J32: Sudoeste | K32: 1112.9 | L32: 494.9 | M32: 1208.4 | N32: 2111.79 | O32: 52 | Q32: Sudoeste | R32: 178.9 | S32: 74 | T32: 104.9 | U32: 2090.79 | V32: 12 | X32: Sudoeste | Y32: 727.7 | Z32: 0 | AA32: 727.7 | AB32: 2228.89 | AC32: 43 | AE32: Sudoeste | AF32: 239.8 | AG32: 0 | AH32: 688.6 | AI32: 1977.44 | AJ32: 8 | AM32: Sudoeste | AN32: =D32+K32+R32+Y32+AF32 -> 2259.3 | AO32: =E32+L32+S32+Z32+AG32 -> 568.9 | AP32: =F32+M32+T32+AA32+AH32 -> 2729.6 | AQ32: =H32+O32+V32+AC32+AJ32 -> 115
C33: Noroeste | J33: Noroeste | K33: 1101.01 | L33: 177.9 | M33: 1229.01 | N33: 6621.44 | O33: 57 | Q33: Noroeste | R33: 2079.4 | S33: 676.7 | T33: 1897.6 | U33: 7526.04 | V33: 98 | X33: Noroeste | Y33: 1530.4 | Z33: 187 | AA33: 1758 | AB33: 6987.04 | AC33: 82 | AE33: Noroeste | AF33: 2654.5 | AG33: 286.9 | AH33: 2721.6 | AI33: 7593.16 | AJ33: 93 | AM33: Noroeste | AN33: =D33+K33+R33+Y33+AF33 -> 7365.31 | AO33: =E33+L33+S33+Z33+AG33 -> 1328.5 | AP33: =F33+M33+T33+AA33+AH33 -> 7606.21 | AQ33: =H33+O33+V33+AC33+AJ33 -> 330
C34: Total: | D34: =D26+D27+D28+D29+D30+D31+D32+D33 -> 0 | E34: =E26+E27+E28+E29+E30+E31+E32+E33 -> 0 | F34: =F26+F27+F28+F29+F30+F31+F32+F33 -> 0 | G34: =G26+G27+G28+G29+G30+G31+G32+G33 -> 0 | H34: =H26+H27+H28+H29+H30+H31+H32+H33 -> 0 | J34: Total: | K34: =K26+K27+K28+K29+K30+K31+K32+K33 -> 6575.51 | L34: =L26+L27+L28+L29+L30+L31+L32+L33 -> 1087.6 | M34: =M26+M27+M28+M29+M30+M31+M32+M33 -> 7172.01 | N34: =N26+N27+N28+N29+N30+N31+N32+N33 -> 18641.19 | O34: =O26+O27+O28+O29+O30+O31+O32+O33 -> 291 | Q34: Total: | R34: =R26+R27+R28+R29+R30+R31+R32+R33 -> 5227.5 | S34: =S26+S27+S28+S29+S30+S31+S32+S33 -> 1243.1 | T34: =T26+T27+T28+T29+T30+T31+T32+T33 -> 5127.2 | U34: =U26+U27+U28+U29+U30+U31+U32+U33 -> 19946.89 | V34: =V26+V27+V28+V29+V30+V31+V32+V33 -> 227 | X34: Total: | Y34: =Y26+Y27+Y28+Y29+Y30+Y31+Y32+Y33 -> 4432 | Z34: =Z26+Z27+Z28+Z29+Z30+Z31+Z32+Z33 -> 357 | AA34: =AA26+AA27+AA28+AA29+AA30+AA31+AA32+AA33 -> 5562.18 | AB34: =AB26+AB27+AB28+AB29+AB30+AB31+AB32+AB33 -> 17988.28 | AC34: =AC26+AC27+AC28+AC29+AC30+AC31+AC32+AC33 -> 214 | AE34: Total: | AF34: =AF26+AF27+AF28+AF29+AF30+AF31+AF32+AF33 -> 7999.62 | AG34: =AG26+AG27+AG28+AG29+AG30+AG31+AG32+AG33 -> 2019.42 | AH34: =AH26+AH27+AH28+AH29+AH30+AH31+AH32+AH33 -> 9740.28 | AI34: =AI26+AI27+AI28+AI29+AI30+AI31+AI32+AI33 -> 20368.35 | AJ34: =AJ26+AJ27+AJ28+AJ29+AJ30+AJ31+AJ32+AJ33 -> 320 | AM34: Total: | AN34: =AN26+AN27+AN28+AN29+AN30+AN31+AN32+AN33 -> 24234.63 | AO34: =AO26+AO27+AO28+AO29+AO30+AO31+AO32+AO33 -> 4707.12 | AP34: =AP26+AP27+AP28+AP29+AP30+AP31+AP32+AP33 -> 27601.67 | AQ34: =AQ26+AQ27+AQ28+AQ29+AQ30+AQ31+AQ32+AQ33 -> 1052
C35: Faturado dia real | D35: =D34-E34 -> 0 | J35: Faturado dia real | K35: =K34-L34 -> 5487.91 | Q35: Faturado dia real | R35: =R34-S34 -> 3984.4 | X35: Faturado dia real | Y35: =Y34-Z34 -> 4075 | AE35: Faturado dia real | AF35: =AF34-AG34 -> 5980.2 | AM35: Fat. Real | AN35: =AN34-AO34 -> 19527.51
C36: Recebido dia real | D36: =F34-E34 -> 0 | J36: Recebido dia real | K36: =M34-L34 -> 6084.41 | Q36: Recebido dia real | R36: =T34-S34 -> 3884.1 | X36: Recebido dia real | Y36: =AA34-Z34 -> 5205.18 | AE36: Recebido dia real | AF36: =AH34-AG34 -> 7720.86
B37: Dia | C37: Lojas | D37: Faturamento dia | E37: Não pago dia | F37: Recebido dia | G37: Não pago Acumulado | H37: Peças | I37: Dia | J37: Lojas | K37: Faturamento | L37: Não pago dia | M37: Recebido dia | N37: Não pago Acumulado | O37: Peças | P37: Dia | Q37: Lojas | R37: Faturamento | S37: Não pago dia | T37: Recebido dia | U37: Não pago Acumulado | V37: Peças | W37: Dia | X37: Lojas | Y37: Faturamento | Z37: Não pago dia | AA37: Recebido dia | AB37: Não pago Acumulado | AC37: Peças | AD37: Dia | AE37: Lojas | AF37: Faturamento | AG37: Não pago dia | AH37: Recebido dia | AI37: Não pago Acumulado | AJ37: Peças | AM37: Lojas | AN37: Faturamento | AO37: Não pago dia | AP37: Recebido | AQ37: Peças
A38: Quinta-feira | C38: Lago Norte | I38: 45693 | J38: Lago Norte | K38: 668.91 | L38: 30 | M38: 713.91 | N38: 756 | O38: 30 | P38: 46065 | Q38: Lago Norte | R38: 394.8 | S38: 85 | T38: 339.8 | U38: 1876.4 | V38: 30 | W38: 46072 | X38: Lago Norte | Y38: 626 | Z38: 156 | AA38: 624.9 | AB38: 1016.9 | AC38: 17 | AD38: 46079 | AE38: Lago Norte | AF38: 417.8 | AG38: 0 | AH38: 482.8 | AI38: 1210.97 | AJ38: 21 | AL38: Faturamento Total das Quintas-feiras | AM38: Lago Norte | AN38: =D38+K38+R38+Y38+AF38 -> 2107.51 | AO38: =E38+L38+S38+Z38+AG38 -> 271 | AP38: =F38+M38+T38+AA38+AH38 -> 2161.41 | AQ38: =H38+O38+V38+AC38+AJ38 -> 98
C39: 202 Norte | J39: 202 Norte | K39: 1349.9 | L39: 0 | M39: 1349.9 | N39: 2413.4 | O39: 25 | Q39: 202 Norte | R39: 1673.2 | S39: 409.9 | T39: 1481.3 | U39: 1556.1 | V39: 54 | X39: 202 Norte | Y39: 338.8 | Z39: 109.8 | AA39: 229 | AB39: 1235.2 | AC39: 17 | AE39: 202 Norte | AF39: 670.9 | AG39: 0 | AH39: 670.9 | AI39: 3129.12 | AJ39: 20 | AM39: 202 Norte | AN39: =D39+K39+R39+Y39+AF39 -> 4032.8 | AO39: =E39+L39+S39+Z39+AG39 -> 519.7 | AP39: =F39+M39+T39+AA39+AH39 -> 3731.1 | AQ39: =H39+O39+V39+AC39+AJ39 -> 116
C40: 213 Norte | J40: 213 Norte | Q40: 213 Norte | X40: 213 Norte | AE40: 213 Norte | AM40: 213 Norte | AN40: =D40+K40+R40+Y40+AF40 -> 0 | AO40: =E40+L40+S40+Z40+AG40 -> 0 | AP40: =F40+M40+T40+AA40+AH40 -> 0 | AQ40: =H40+O40+V40+AC40+AJ40 -> 0
C41: 307 Norte | J41: 307 Norte | K41: 1131.7 | L41: 541.1 | M41: 926.5 | N41: 5566.96 | O41: 49 | Q41: 307 Norte | R41: 1403.4 | S41: 109 | T41: 1294.4 | U41: 5725.56 | V41: 97 | X41: 307 Norte | Y41: 2691.16 | Z41: 1305.66 | AA41: 2334 | AB41: 5509.61 | AC41: 121 | AE41: 307 Norte | AF41: 1358.2 | AG41: 18 | AH41: 1340.2 | AI41: 4847.56 | AJ41: 54 | AM41: 307 Norte | AN41: =D41+K41+R41+Y41+AF41 -> 6584.46 | AO41: =E41+L41+S41+Z41+AG41 -> 1973.76 | AP41: =F41+M41+T41+AA41+AH41 -> 5895.1 | AQ41: =H41+O41+V41+AC41+AJ41 -> 321
C42: 313 Norte | J42: 313 Norte | K42: 988.46 | L42: 404.9 | M42: 936.56 | N42: 1383.7 | O42: 45 | Q42: 313 Norte | R42: 463 | S42: 68 | T42: 457 | U42: 1533.6 | V42: 24 | X42: 313 Norte | Y42: 317.28 | Z42: 0 | AA42: 317.28 | AB42: 1478.7 | AC42: 14 | AE42: 313 Norte | AF42: 1254 | AG42: 371.9 | AH42: 1018.8 | AI42: 1799.1 | AM42: 313 Norte | AN42: =D42+K42+R42+Y42+AF42 -> 3022.74 | AO42: =E42+L42+S42+Z42+AG42 -> 844.8 | AP42: =F42+M42+T42+AA42+AH42 -> 2729.64 | AQ42: =H42+O42+V42+AC42+AJ42 -> 83
C43: 314 Sul | J43: 314 Sul | Q43: 314 Sul | X43: 314 Sul | AE43: 314 Sul | AM43: 314 Sul | AN43: =D43+K43+R43+Y43+AF43 -> 0 | AO43: =E43+L43+S43+Z43+AG43 -> 0 | AP43: =F43+M43+T43+AA43+AH43 -> 0 | AQ43: =H43+O43+V43+AC43+AJ43 -> 0
C44: Sudoeste | J44: Sudoeste | K44: 586.9 | L44: 90 | M44: 496.9 | N44: 2201.79 | O44: 26 | Q44: Sudoeste | R44: 513.8 | S44: 0 | T44: 726.7 | U44: 1877.89 | V44: 35 | X44: Sudoeste | Y44: 209.9 | Z44: 54.9 | AA44: 155 | AB44: 2283.79 | AC44: 28 | AE44: Sudoeste | AF44: 564.9 | AG44: 0 | AH44: 640.9 | AI44: 1963.44 | AJ44: 23 | AM44: Sudoeste | AN44: =D44+K44+R44+Y44+AF44 -> 1875.5 | AO44: =E44+L44+S44+Z44+AG44 -> 144.9 | AP44: =F44+M44+T44+AA44+AH44 -> 2019.5 | AQ44: =H44+O44+V44+AC44+AJ44 -> 112
C45: Noroeste | J45: Noroeste | K45: 1226.7 | L45: 335.7 | M45: 1316.5 | N45: 6531.64 | O45: 74 | Q45: Noroeste | R45: 1324.63 | S45: 444.7 | T45: 1438.83 | U45: 7411.84 | V45: 153 | X45: Noroeste | Y45: 920 | Z45: 168 | AA45: 913.9 | AB45: 6993.14 | AC45: 30 | AE45: Noroeste | AF45: 1944 | AG45: 312.1 | AH45: 1981.8 | AI45: 7555.36 | AJ45: 104 | AM45: Noroeste | AN45: =D45+K45+R45+Y45+AF45 -> 5415.33 | AO45: =E45+L45+S45+Z45+AG45 -> 1260.5 | AP45: =F45+M45+T45+AA45+AH45 -> 5651.03 | AQ45: =H45+O45+V45+AC45+AJ45 -> 361
C46: Total: | D46: =D38+D39+D40+D41+D42+D43+D44+D45 -> 0 | E46: =E38+E39+E40+E41+E42+E43+E44+E45 -> 0 | F46: =F38+F39+F40+F41+F42+F43+F44+F45 -> 0 | G46: =G38+G39+G40+G41+G42+G43+G44+G45 -> 0 | H46: =H38+H39+H40+H41+H42+H43+H44+H45 -> 0 | J46: Total: | K46: =K38+K39+K40+K41+K42+K43+K44+K45 -> 5952.57 | L46: =L38+L39+L40+L41+L42+L43+L44+L45 -> 1401.7 | M46: =M38+M39+M40+M41+M42+M43+M44+M45 -> 5740.27 | N46: =N38+N39+N40+N41+N42+N43+N44+N45 -> 18853.49 | O46: =O38+O39+O40+O41+O42+O43+O44+O45 -> 249 | Q46: Total: | R46: =R38+R39+R40+R41+R42+R43+R44+R45 -> 5772.83 | S46: =S38+S39+S40+S41+S42+S43+S44+S45 -> 1116.6 | T46: =T38+T39+T40+T41+T42+T43+T44+T45 -> 5738.03 | U46: =U38+U39+U40+U41+U42+U43+U44+U45 -> 19981.39 | V46: =V38+V39+V40+V41+V42+V43+V44+V45 -> 393 | X46: Total: | Y46: =Y38+Y39+Y40+Y41+Y42+Y43+Y44+Y45 -> 5103.14 | Z46: =Z38+Z39+Z40+Z41+Z42+Z43+Z44+Z45 -> 1794.36 | AA46: =AA38+AA39+AA40+AA41+AA42+AA43+AA44+AA45 -> 4574.08 | AB46: =AB38+AB39+AB40+AB41+AB42+AB43+AB44+AB45 -> 18517.34 | AC46: =AC38+AC39+AC40+AC41+AC42+AC43+AC44+AC45 -> 227 | AE46: Total: | AF46: =AF38+AF39+AF40+AF41+AF42+AF43+AF44+AF45 -> 6209.8 | AG46: =AG38+AG39+AG40+AG41+AG42+AG43+AG44+AG45 -> 702 | AH46: =AH38+AH39+AH40+AH41+AH42+AH43+AH44+AH45 -> 6135.4 | AI46: =AI38+AI39+AI40+AI41+AI42+AI43+AI44+AI45 -> 20505.55 | AJ46: =AJ38+AJ39+AJ40+AJ41+AJ42+AJ43+AJ44+AJ45 -> 222 | AM46: Total: | AN46: =AN38+AN39+AN40+AN41+AN42+AN43+AN44+AN45 -> 23038.34 | AO46: =AO38+AO39+AO40+AO41+AO42+AO43+AO44+AO45 -> 5014.66 | AP46: =AP38+AP39+AP40+AP41+AP42+AP43+AP44+AP45 -> 22187.78 | AQ46: =AQ38+AQ39+AQ40+AQ41+AQ42+AQ43+AQ44+AQ45 -> 1091
C47: Faturado dia real | D47: =D46-E46 -> 0 | J47: Faturado dia real | K47: =K46-L46 -> 4550.87 | Q47: Faturado dia real | R47: =R46-S46 -> 4656.23 | X47: Faturado dia real | Y47: =Y46-Z46 -> 3308.78 | AE47: Faturado dia real | AF47: =AF46-AG46 -> 5507.8 | AM47: Fat. Real | AN47: =AN46-AO46 -> 18023.68
C48: Recebido dia real | D48: =F46-E46 -> 0 | J48: Recebido dia real | K48: =M46-L46 -> 4338.57 | Q48: Recebido dia real | R48: =T46-S46 -> 4621.43 | X48: Recebido dia real | Y48: =AA46-Z46 -> 2779.72 | AE48: Recebido dia real | AF48: =AH46-AG46 -> 5433.4
B49: Dia | C49: Lojas | D49: Faturamento dia | E49: Não pago dia | F49: Recebido dia | G49: Não pago Acumulado | H49: Peças | I49: Dia | J49: Lojas | K49: Faturamento | L49: Não pago dia | M49: Recebido dia | N49: Não pago Acumulado | O49: Peças | P49: Dia | Q49: Lojas | R49: Faturamento | S49: Não pago dia | T49: Recebido dia | U49: Não pago Acumulado | V49: Peças | W49: Dia | X49: Lojas | Y49: Faturamento | Z49: Não pago dia | AA49: Recebido dia | AB49: Não pago Acumulado | AC49: Peças | AD49: Dia | AE49: Lojas | AF49: Faturamento | AG49: Não pago dia | AH49: Recebido dia | AI49: Não pago Acumulado | AJ49: Peças | AM49: Lojas | AN49: Faturamento | AO49: Não pago dia | AP49: Recebido | AQ49: Peças
A50: Sexta-feira | C50: Lago Norte | I50: 46059 | J50: Lago Norte | K50: 1954.4 | L50: 850.6 | M50: 1150.8 | N50: 1557.6 | O50: 74 | P50: 46066 | Q50: Lago Norte | R50: 291 | S50: 0 | T50: 291 | U50: 1876.4 | W50: 46073 | X50: Lago Norte | Y50: 858.9 | Z50: 308 | AA50: 768.8 | AB50: 1107 | AC50: 40 | AD50: 46080 | AE50: Lago Norte | AF50: 975.6 | AG50: 659.6 | AH50: 330 | AI50: 1856.57 | AJ50: 39 | AL50: Faturamento Total das Sextas-feiras | AM50: Lago Norte | AN50: =D50+K50+R50+Y50+AF50 -> 4079.9 | AO50: =E50+L50+S50+Z50+AG50 -> 1818.2 | AP50: =F50+M50+T50+AA50+AH50 -> 2540.6 | AQ50: =H50+O50+V50+AC50+AJ50 -> 153
C51: 202 Norte | J51: 202 Norte | K51: 1007.7 | L51: 218 | M51: 2545.5 | N51: 875.6 | O51: 49 | Q51: 202 Norte | R51: 1417.9 | S51: 0 | T51: 1547.9 | U51: 1426.4 | V51: 42 | X51: 202 Norte | Y51: 1753.9 | Z51: 778 | AA51: 1075.8 | AB51: 1913.3 | AC51: 73 | AE51: 202 Norte | AF51: 259.59 | AG51: 210.59 | AH51: 85 | AI51: 3339.71 | AJ51: 33 | AM51: 202 Norte | AN51: =D51+K51+R51+Y51+AF51 -> 4439.09 | AO51: =E51+L51+S51+Z51+AG51 -> 1206.59 | AP51: =F51+M51+T51+AA51+AH51 -> 5254.2 | AQ51: =H51+O51+V51+AC51+AJ51 -> 197
C52: 213 Norte | J52: 213 Norte | Q52: 213 Norte | X52: 213 Norte | AE52: 213 Norte | AM52: 213 Norte | AN52: =D52+K52+R52+Y52+AF52 -> 0 | AO52: =E52+L52+S52+Z52+AG52 -> 0 | AP52: =F52+M52+T52+AA52+AH52 -> 0 | AQ52: =H52+O52+V52+AC52+AJ52 -> 0
C53: 307 Norte | J53: 307 Norte | K53: 532.4 | L53: 330 | M53: 322.4 | N53: 5776.96 | O53: 34 | Q53: 307 Norte | R53: 1142 | S53: 0 | T53: 1440.9 | U53: 5426.66 | V53: 66 | X53: 307 Norte | Y53: 896 | Z53: 0 | AA53: 896 | AB53: 5509.61 | AC53: 25 | AE53: 307 Norte | AF53: 1358.2 | AG53: 18 | AH53: 1340.2 | AI53: 4847.56 | AJ53: 54 | AM53: 307 Norte | AN53: =D53+K53+R53+Y53+AF53 -> 3928.6 | AO53: =E53+L53+S53+Z53+AG53 -> 348 | AP53: =F53+M53+T53+AA53+AH53 -> 3999.5 | AQ53: =H53+O53+V53+AC53+AJ53 -> 179
C54: 313 Norte | J54: 313 Norte | K54: 1341.7 | L54: 135.9 | M54: 1284.8 | N54: 1440.6 | O54: 37 | Q54: 313 Norte | R54: 1241.8 | S54: 0 | T54: 1241.8 | U54: 1533.6 | V54: 56 | X54: 313 Norte | Y54: 744.7 | Z54: 0 | AA54: 744.7 | AB54: 1478.7 | AC54: 29 | AE54: 313 Norte | AF54: 476.4 | AG54: 54 | AH54: 422.4 | AI54: 1853.1 | AJ54: 43 | AM54: 313 Norte | AN54: =D54+K54+R54+Y54+AF54 -> 3804.6 | AO54: =E54+L54+S54+Z54+AG54 -> 189.9 | AP54: =F54+M54+T54+AA54+AH54 -> 3693.7 | AQ54: =H54+O54+V54+AC54+AJ54 -> 165
C55: 314 Sul | J55: 314 Sul | Q55: 314 Sul | X55: 314 Sul | AE55: 314 Sul | AM55: 314 Sul | AN55: =D55+K55+R55+Y55+AF55 -> 0 | AO55: =E55+L55+S55+Z55+AG55 -> 0 | AP55: =F55+M55+T55+AA55+AH55 -> 0 | AQ55: =H55+O55+V55+AC55+AJ55 -> 0
C56: Sudoeste | J56: Sudoeste | K56: 407.9 | L56: 277 | M56: 130.9 | N56: 2478.79 | O56: 18 | Q56: Sudoeste | R56: 217.9 | S56: 0 | T56: 272.8 | U56: 1822.99 | V56: 9 | X56: Sudoeste | Y56: 877.6 | Z56: 74 | AA56: 803.6 | AB56: 2357.79 | AC56: 26 | AE56: Sudoeste | AF56: 139.5 | AG56: 52 | AH56: 197.5 | AI56: 1905.44 | AJ56: 11 | AM56: Sudoeste | AN56: =D56+K56+R56+Y56+AF56 -> 1642.9 | AO56: =E56+L56+S56+Z56+AG56 -> 403 | AP56: =F56+M56+T56+AA56+AH56 -> 1404.8 | AQ56: =H56+O56+V56+AC56+AJ56 -> 64
C57: Noroeste | J57: Noroeste | K57: 1774.9 | L57: 243 | M57: 1742.8 | N57: 6563.74 | O57: 121 | Q57: Noroeste | R57: 2024.6 | S57: 237 | T57: 2118.5 | U57: 7317.94 | V57: 104 | X57: Noroeste | Y57: 999.9 | Z57: 247 | AA57: 931.8 | AB57: 7061.24 | AC57: 76 | AE57: Noroeste | AF57: 5007.9 | AG57: 613.9 | AH57: 5455.4 | AI57: 6942.86 | AJ57: 183 | AM57: Noroeste | AN57: =D57+K57+R57+Y57+AF57 -> 9807.3 | AO57: =E57+L57+S57+Z57+AG57 -> 1340.9 | AP57: =F57+M57+T57+AA57+AH57 -> 10248.5 | AQ57: =H57+O57+V57+AC57+AJ57 -> 484
C58: Total: | D58: =D50+D51+D52+D53+D54+D55+D56+D57 -> 0 | E58: =E50+E51+E52+E53+E54+E55+E56+E57 -> 0 | F58: =F50+F51+F52+F53+F54+F55+F56+F57 -> 0 | G58: =G50+G51+G52+G53+G54+G55+G56+G57 -> 0 | H58: =H50+H51+H52+H53+H54+H55+H56+H57 -> 0 | J58: Total: | K58: =K50+K51+K52+K53+K54+K55+K56+K57 -> 7019 | L58: =L50+L51+L52+L53+L54+L55+L56+L57 -> 2054.5 | M58: =M50+M51+M52+M53+M54+M55+M56+M57 -> 7177.2 | N58: =N50+N51+N52+N53+N54+N55+N56+N57 -> 18693.29 | O58: =O50+O51+O52+O53+O54+O55+O56+O57 -> 333 | Q58: Total: | R58: =R50+R51+R52+R53+R54+R55+R56+R57 -> 6335.2 | S58: =S50+S51+S52+S53+S54+S55+S56+S57 -> 237 | T58: =T50+T51+T52+T53+T54+T55+T56+T57 -> 6912.9 | U58: =U50+U51+U52+U53+U54+U55+U56+U57 -> 19403.99 | V58: =V50+V51+V52+V53+V54+V55+V56+V57 -> 277 | X58: Total: | Y58: =Y50+Y51+Y52+Y53+Y54+Y55+Y56+Y57 -> 6131 | Z58: =Z50+Z51+Z52+Z53+Z54+Z55+Z56+Z57 -> 1407 | AA58: =AA50+AA51+AA52+AA53+AA54+AA55+AA56+AA57 -> 5220.7 | AB58: =AB50+AB51+AB52+AB53+AB54+AB55+AB56+AB57 -> 19427.64 | AC58: =AC50+AC51+AC52+AC53+AC54+AC55+AC56+AC57 -> 269 | AE58: Total: | AF58: =AF50+AF51+AF52+AF53+AF54+AF55+AF56+AF57 -> 8217.19 | AG58: =AG50+AG51+AG52+AG53+AG54+AG55+AG56+AG57 -> 1608.09 | AH58: =AH50+AH51+AH52+AH53+AH54+AH55+AH56+AH57 -> 7830.5 | AI58: =AI50+AI51+AI52+AI53+AI54+AI55+AI56+AI57 -> 20745.24 | AJ58: =AJ50+AJ51+AJ52+AJ53+AJ54+AJ55+AJ56+AJ57 -> 363 | AM58: Total: | AN58: =AN50+AN51+AN52+AN53+AN54+AN55+AN56+AN57 -> 27702.39 | AO58: =AO50+AO51+AO52+AO53+AO54+AO55+AO56+AO57 -> 5306.59 | AP58: =AP50+AP51+AP52+AP53+AP54+AP55+AP56+AP57 -> 27141.3 | AQ58: =AQ50+AQ51+AQ52+AQ53+AQ54+AQ55+AQ56+AQ57 -> 1242
C59: Faturado dia real | D59: =D58-E58 -> 0 | J59: Faturado dia real | K59: =K58-L58 -> 4964.5 | Q59: Faturado dia real | R59: =R58-S58 -> 6098.2 | X59: Faturado dia real | Y59: =Y58-Z58 -> 4724 | AE59: Faturado dia real | AF59: =AF58-AG58 -> 6609.1 | AM59: Fat. Real | AN59: =AN58-AO58 -> 22395.8
C60: Recebido dia real | D60: =F58-E58 -> 0 | J60: Recebido dia real | K60: =M58-L58 -> 5122.7 | Q60: Recebido dia real | R60: =T58-S58 -> 6675.9 | X60: Recebido dia real | Y60: =AA58-Z58 -> 3813.7 | AE60: Recebido dia real | AF60: =AH58-AG58 -> 6222.41
B61: Dia | C61: Lojas | D61: Faturamento dia | E61: Não pago dia | F61: Recebido dia | G61: Não pago Acumulado | H61: Peças | I61: Dia | J61: Lojas | K61: Faturamento | L61: Não pago dia | M61: Recebido dia | N61: Não pago Acumulado | O61: Peças | P61: Dia | Q61: Lojas | R61: Faturamento | S61: Não pago dia | T61: Recebido dia | U61: Não pago Acumulado | V61: Peças | W61: Dia | X61: Lojas | Y61: Faturamento | Z61: Não pago dia | AA61: Recebido dia | AB61: Não pago Acumulado | AC61: Peças | AD61: Dia | AE61: Lojas | AF61: Faturamento | AG61: Não pago dia | AH61: Recebido dia | AI61: Não pago Acumulado | AJ61: Peças | AM61: Lojas | AN61: Faturamento | AO61: Não pago dia | AP61: Recebido | AQ61: Peças
A62: Sábado | C62: Lago Norte | I62: 46060 | J62: Lago Norte | K62: 1871.7 | L62: 267.8 | M62: 1765.9 | N62: 1661.4 | O62: 53 | P62: 46067 | Q62: Lago Norte | R62: 369.1 | S62: 0 | T62: 369.1 | U62: 1876.4 | V62: 26 | W62: 46074 | X62: Lago Norte | Y62: 683.7 | Z62: 16 | AA62: 667.7 | AB62: 1123 | AC62: 41 | AD62: 46081 | AE62: Lago Norte | AL62: Faturamento Total dos Sábados | AM62: Lago Norte | AN62: =D62+K62+R62+Y62+AF62 -> 2924.5 | AO62: =E62+L62+S62+Z62+AG62 -> 283.8 | AP62: =F62+M62+T62+AA62+AH62 -> 2802.7 | AQ62: =H62+O62+V62+AC62+AJ62 -> 120
C63: 202 Norte | J63: 202 Norte | K63: 1145 | L63: 0 | M63: 1145 | N63: 875.6 | O63: 37 | Q63: 202 Norte | R63: 466 | S63: 27 | T63: 439 | U63: 1453.4 | V63: 15 | X63: 202 Norte | Y63: 562.4 | Z63: 151.9 | AA63: 410.5 | AB63: 2065.2 | AC63: 33 | AE63: 202 Norte | AM63: 202 Norte | AN63: =D63+K63+R63+Y63+AF63 -> 2173.4 | AO63: =E63+L63+S63+Z63+AG63 -> 178.9 | AP63: =F63+M63+T63+AA63+AH63 -> 1994.5 | AQ63: =H63+O63+V63+AC63+AJ63 -> 85
C64: 213 Norte | J64: 213 Norte | Q64: 213 Norte | X64: 213 Norte | AE64: 213 Norte | AM64: 213 Norte | AN64: =D64+K64+R64+Y64+AF64 -> 0 | AO64: =E64+L64+S64+Z64+AG64 -> 0 | AP64: =F64+M64+T64+AA64+AH64 -> 0 | AQ64: =H64+O64+V64+AC64+AJ64 -> 0
C65: 307 Norte | J65: 307 Norte | K65: 1409.4 | L65: 312 | M65: 1347.5 | N65: 5838.86 | O65: 81 | Q65: 307 Norte | R65: 662.7 | S65: 122.9 | T65: 814.7 | U65: 5274.66 | V65: 63 | X65: 307 Norte | Y65: 1223.06 | Z65: 0 | AA65: 1301.06 | AB65: 5431.61 | AC65: 66 | AE65: 307 Norte | AM65: 307 Norte | AN65: =D65+K65+R65+Y65+AF65 -> 3295.16 | AO65: =E65+L65+S65+Z65+AG65 -> 434.9 | AP65: =F65+M65+T65+AA65+AH65 -> 3463.26 | AQ65: =H65+O65+V65+AC65+AJ65 -> 210
C66: 313 Norte | J66: 313 Norte | K66: 1336.9 | L66: 62 | M66: 1274.9 | N66: 1502.6 | O66: 73 | Q66: 313 Norte | R66: 755.9 | S66: 0 | T66: 755.9 | U66: 1533.6 | V66: 64 | X66: 313 Norte | Y66: 1050.4 | Z66: 70.4 | AA66: 1010 | AB66: 1519.1 | AC66: 52 | AE66: 313 Norte | AM66: 313 Norte | AN66: =D66+K66+R66+Y66+AF66 -> 3143.2 | AO66: =E66+L66+S66+Z66+AG66 -> 132.4 | AP66: =F66+M66+T66+AA66+AH66 -> 3040.8 | AQ66: =H66+O66+V66+AC66+AJ66 -> 189
C67: 314 Sul | J67: 314 Sul | Q67: 314 Sul | X67: 314 Sul | AE67: 314 Sul | AM67: 314 Sul | AN67: =D67+K67+R67+Y67+AF67 -> 0 | AO67: =E67+L67+S67+Z67+AG67 -> 0 | AP67: =F67+M67+T67+AA67+AH67 -> 0 | AQ67: =H67+O67+V67+AC67+AJ67 -> 0
C68: Sudoeste | J68: Sudoeste | K68: 563 | L68: 0 | M68: 613 | N68: 2428.79 | O68: 23 | Q68: Sudoeste | R68: 929.8 | S68: 405.9 | T68: 523.9 | U68: 2228.89 | V68: 28 | X68: Sudoeste | Y68: 54.9 | Z68: 0 | AA68: 403.9 | AB68: 2008.79 | AC68: 11 | AE68: Sudoeste | AM68: Sudoeste | AN68: =D68+K68+R68+Y68+AF68 -> 1547.7 | AO68: =E68+L68+S68+Z68+AG68 -> 405.9 | AP68: =F68+M68+T68+AA68+AH68 -> 1540.8 | AQ68: =H68+O68+V68+AC68+AJ68 -> 62
C69: Noroeste | J69: Noroeste | K69: 2505.7 | L69: 256.3 | M69: 2432.2 | N69: 6637.24 | O69: 115 | Q69: Noroeste | R69: 244.9 | S69: 0 | T69: 323.9 | U69: 7238.94 | V69: 58 | X69: Noroeste | Y69: 769 | Z69: 566 | AA69: 380.2 | AB69: 7450.04 | AC69: 67 | AE69: Noroeste | AM69: Noroeste | AN69: =D69+K69+R69+Y69+AF69 -> 3519.6 | AO69: =E69+L69+S69+Z69+AG69 -> 822.3 | AP69: =F69+M69+T69+AA69+AH69 -> 3136.3 | AQ69: =H69+O69+V69+AC69+AJ69 -> 240
C70: Total: | D70: =D62+D63+D64+D65+D66+D67+D68+D69 -> 0 | E70: =E62+E63+E64+E65+E66+E67+E68+E69 -> 0 | F70: =F62+F63+F64+F65+F66+F67+F68+F69 -> 0 | G70: =G62+G63+G64+G65+G66+G67+G68+G69 -> 0 | H70: =H62+H63+H64+H65+H66+H67+H68+H69 -> 0 | J70: Total: | K70: =K62+K63+K64+K65+K66+K67+K68+K69 -> 8831.7 | L70: =L62+L63+L64+L65+L66+L67+L68+L69 -> 898.1 | M70: =M62+M63+M64+M65+M66+M67+M68+M69 -> 8578.5 | N70: =N62+N63+N64+N65+N66+N67+N68+N69 -> 18944.49 | O70: =O62+O63+O64+O65+O66+O67+O68+O69 -> 382 | Q70: Total: | R70: =R62+R63+R64+R65+R66+R67+R68+R69 -> 3428.4 | S70: =S62+S63+S64+S65+S66+S67+S68+S69 -> 555.8 | T70: =T62+T63+T64+T65+T66+T67+T68+T69 -> 3226.5 | U70: =U62+U63+U64+U65+U66+U67+U68+U69 -> 19605.89 | V70: =V62+V63+V64+V65+V66+V67+V68+V69 -> 254 | X70: Total: | Y70: =Y62+Y63+Y64+Y65+Y66+Y67+Y68+Y69 -> 4343.46 | Z70: =Z62+Z63+Z64+Z65+Z66+Z67+Z68+Z69 -> 804.3 | AA70: =AA62+AA63+AA64+AA65+AA66+AA67+AA68+AA69 -> 4173.36 | AB70: =AB62+AB63+AB64+AB65+AB66+AB67+AB68+AB69 -> 19597.74 | AC70: =AC62+AC63+AC64+AC65+AC66+AC67+AC68+AC69 -> 270 | AE70: Total: | AF70: =AF62+AF63+AF64+AF65+AF66+AF67+AF68+AF69 -> 0 | AG70: =AG62+AG63+AG64+AG65+AG66+AG67+AG68+AG69 -> 0 | AH70: =AH62+AH63+AH64+AH65+AH66+AH67+AH68+AH69 -> 0 | AI70: =AI62+AI63+AI64+AI65+AI66+AI67+AI68+AI69 -> 0 | AJ70: =AJ62+AJ63+AJ64+AJ65+AJ66+AJ67+AJ68+AJ69 -> 0 | AM70: Total: | AN70: =AN62+AN63+AN64+AN65+AN66+AN67+AN68+AN69 -> 16603.56 | AO70: =AO62+AO63+AO64+AO65+AO66+AO67+AO68+AO69 -> 2258.2 | AP70: =AP62+AP63+AP64+AP65+AP66+AP67+AP68+AP69 -> 15978.36 | AQ70: =AQ62+AQ63+AQ64+AQ65+AQ66+AQ67+AQ68+AQ69 -> 906
C71: Faturado dia real | D71: =D70-E70 -> 0 | J71: Faturado dia real | K71: =K70-L70 -> 7933.6 | Q71: Faturado dia real | R71: =R70-S70 -> 2872.6 | X71: Faturado dia real | Y71: =Y70-Z70 -> 3539.16 | AE71: Faturado dia real | AF71: =AF70-AG70 -> 0 | AM71: Fat. Real | AN71: =AN70-AO70 -> 14345.36
C72: Recebido dia real | D72: =F70-E70 -> 0 | J72: Recebido dia real | K72: =M70-L70 -> 7680.4 | Q72: Recebido dia real | R72: =T70-S70 -> 2670.7 | X72: Recebido dia real | Y72: =AA70-Z70 -> 3369.06 | AE72: Recebido dia real | AF72: =AH70-AG70 -> 0
B73: Dia | C73: Lojas | D73: Faturamento | E73: Não pago dia | F73: Recebido dia | G73: Não pago Acumulado | H73: Peças | I73: Dia | J73: Lojas | K73: Faturamento | L73: Não pago dia | M73: Recebido dia | N73: Não pago Acumulado | O73: Peças | P73: Dia | Q73: Lojas | R73: Faturamento | S73: Não pago dia | T73: Recebido dia | U73: Não pago Acumulado | V73: Peças | W73: Dia | X73: Lojas | Y73: Faturamento | Z73: Não pago dia | AA73: Recebido dia | AB73: Não pago Acumulado | AC73: Peças | AD73: Dia | AE73: Lojas | AF73: Faturamento | AG73: Não pago dia | AH73: Recebido dia | AI73: Não pago Acumulado | AJ73: Peças | AM73: Lojas | AN73: Faturamento | AO73: Não pago dia | AP73: Recebido | AQ73: Peças
A74: Domingo | B74: 46054 | C74: Lago Norte | I74: 46061 | P74: 46068 | W74: 45710 | X74: Lago Norte | AL74: Faturamento Total dos Domingos
C75: 202 Norte | X75: 202 Norte
C76: 213 Norte | X76: 213 Norte
C77: 307 Norte | X77: 307 Norte
C78: 313 Norte | X78: 313 Norte
C79: 314 Sul | X79: 314 Sul
C80: Sudoeste | X80: Sudoeste
C81: Noroeste | J81: Noroeste -Dani | Q81: Noroeste | X81: Noroeste | AE81: Noroeste | AM81: Noroeste | AN81: =D81+K81+R81+Y81+AF81 -> 0 | AO81: =E81+L81+S81+Z81+AG81 -> 0 | AP81: =F81+M81+T81+AA81+AH81 -> 0 | AQ81: =H81+O81+V81+AC81+AJ81 -> 0
C82: Total: | D82: =D74+D75+D76+D77+D78+D79+D80+D81 -> 0 | E82: =E74+E75+E76+E77+E78+E79+E80+E81 -> 0 | F82: =F74+F75+F76+F77+F78+F79+F80+F81 -> 0 | G82: =G74+G75+G76+G77+G78+G79+G80+G81 -> 0 | H82: =H74+H75+H76+H77+H78+H79+H80+H81 -> 0 | J82: Total: | K82: =K74+K75+K76+K77+K78+K79+K80+K81 -> 0 | L82: =L74+L75+L76+L77+L78+L79+L80+L81 -> 0 | M82: =M74+M75+M76+M77+M78+M79+M80+M81 -> 0 | N82: =N74+N75+N76+N77+N78+N79+N80+N81 -> 0 | O82: =O74+O75+O76+O77+O78+O79+O80+O81 -> 0 | Q82: Total: | R82: =R74+R75+R76+R77+R78+R79+R80+R81 -> 0 | S82: =S74+S75+S76+S77+S78+S79+S80+S81 -> 0 | T82: =T74+T75+T76+T77+T78+T79+T80+T81 -> 0 | U82: =U74+U75+U76+U77+U78+U79+U80+U81 -> 0 | V82: =V74+V75+V76+V77+V78+V79+V80+V81 -> 0 | X82: Total: | Y82: =Y74+Y75+Y76+Y77+Y78+Y79+Y80+Y81 -> 0 | Z82: =Z74+Z75+Z76+Z77+Z78+Z79+Z80+Z81 -> 0 | AA82: =AA74+AA75+AA76+AA77+AA78+AA79+AA80+AA81 -> 0 | AB82: =AB74+AB75+AB76+AB77+AB78+AB79+AB80+AB81 -> 0 | AC82: =AC74+AC75+AC76+AC77+AC78+AC79+AC80+AC81 -> 0 | AE82: Total: | AF82: =AF74+AF75+AF76+AF77+AF78+AF79+AF80+AF81 -> 0 | AG82: =AG74+AG75+AG76+AG77+AG78+AG79+AG80+AG81 -> 0 | AH82: =AH74+AH75+AH76+AH77+AH78+AH79+AH80+AH81 -> 0 | AI82: =AI74+AI75+AI76+AI77+AI78+AI79+AI80+AI81 -> 0 | AJ82: =AJ74+AJ75+AJ76+AJ77+AJ78+AJ79+AJ80+AJ81 -> 0 | AM82: Total: | AN82: =AN74+AN75+AN76+AN77+AN78+AN79+AN80+AN81 -> 0 | AO82: =AO74+AO75+AO76+AO77+AO78+AO79+AO80+AO81 -> 0 | AP82: =AP74+AP75+AP76+AP77+AP78+AP79+AP80+AP81 -> 0 | AQ82: =AQ74+AQ75+AQ76+AQ77+AQ78+AQ79+AQ80+AQ81 -> 0
C83: Faturado dia real | D83: =D82-E82 -> 0 | J83: Faturado dia real | K83: =K82-L82 -> 0 | Q83: Faturado dia real | R83: =R82-S82 -> 0 | X83: Faturado dia real | Y83: =Y82-Z82 -> 0 | AE83: Faturado dia real | AF83: =AF82-AG82 -> 0 | AM83: Fat. Real | AN83: =AN82-AO82 -> 0
C84: Recebido dia real | D84: =F82-E82 -> 0 | J84: Recebido dia real | K84: =M82-L82 -> 0 | Q84: Recebido dia real | R84: =T82-S82 -> 0 | X84: Recebido dia real | Y84: =AA82-Z82 -> 0 | AE84: Recebido dia real | AF84: =AH82-AG82 -> 0
C87: Faturamento 4° semana Janeiro | J87: Faturamento 4° semana Janeiro | Q87: Faturamento 4° semana Janeiro | X87: Faturamento 4° semana Janeiro | AE87: Faturamento 4 1/2° semana Janeiro
C88: Faturamento | D88: =D10+D22+D34+D46+D58+D70+D82 -> 0 | J88: Faturamento | K88: =K10+K22+K34+K46+K58+K70+K82 -> 41285.45 | Q88: Faturamento | R88: =R10+R22+R34+R46+R58+R70+R82 -> 36627.54 | X88: Faturamento | Y88: =Y10+Y22+Y34+Y46+Y58+Y70+Y82 -> 23084.6 | AE88: Faturamento | AF88: =AF10+AF22+AF34+AF46+AF58+AF70+AF82 -> 36026.56 | AN88: {=AN10+AN22+AN34+AN46+AN58+AN70} -> 137024.15 | AP88: {=AP10+AP22+AP34+AP46+AP58+AP70} -> 136877.81
C89: Não pago dia | D89: =E10+E22+E34+E46+E58+E70+E82 -> 0 | J89: Não pago dia | K89: =L10+L22+L34+L46+L58+L70+L82 -> 6815.03 | Q89: Não pago dia | R89: =S10+S22+S34+S46+S58+S70+S82 -> 5864.4 | X89: Não pago dia | Y89: =Z10+Z22+Z34+Z46+Z58+Z70+Z82 -> 4714.26 | AE89: Não pago dia | AF89: =AG10+AG22+AG34+AG46+AG58+AG70+AG82 -> 7693.78
C90: Recebido | D90: =F10+F22+F34+F46+F58+F70+F82 -> 0 | J90: Recebido | K90: =M10+M22+M34+M46+M58+M70+M82 -> 42618.97 | Q90: Recebido | R90: =T10+T22+T34+T46+T58+T70+T82 -> 35959.72 | X90: Recebido | Y90: =AA10+AA22+AA34+AA46+AA58+AA70+AA82 -> 23082.83 | AE90: Recebido | AF90: =AH10+AH22+AH34+AH46+AH58+AH70+AH82 -> 35216.29
C91: Fat. Real | D91: {=D11:E11+D23:E23+D35:E35+D47:E47+D59:E59+D71:E71+D83:F83} -> 0 | J91: Fat. Real | K91: {=K11:L11+K23:L23+K35:L35+K47:L47+K59:L59+K71:L71+K83:M83} -> 34470.42 | Q91: Fat. Real | R91: {=R11:S11+R23:S23+R35:S35+R47:S47+R59:S59+R71:S71+R83:T83} -> 30763.14 | X91: Fat. Real | Y91: {=Y11:Z11+Y23:Z23+Y35:Z35+Y47:Z47+Y59:Z59+Y71:Z71+Y83:AA83} -> 18370.34 | AE91: Fat. Real | AF91: {=AF11:AG11+AF23:AG23+AF35:AG35+AF47:AG47+AF59:AG59+AF71:AG71+AF83:AH83} -> 28332.78
C92: Recebido Real | D92: {=D12:F12+D24:F24+D36:F36+D48:F48+D60:F60+D72:F72+D84:F84} -> 0 | J92: Recebido Real | K92: {=K12:M12+K24:M24+K36:M36+K48:M48+K60:M60+K72:M72+K84:M84} -> 35803.94 | Q92: Recebido Real | R92: {=R12:T12+R24:T24+R36:T36+R48:T48+R60:T60+R72:T72+R84:T84} -> 30095.32 | X92: Recebido Real | Y92: {=Y12:AA12+Y24:AA24+Y36:AA36+Y48:AA48+Y60:AA60+Y72:AA72+Y84:AA84} -> 18368.57 | AE92: Recebido Real | AF92: {=AF12:AH12+AF24:AH24+AF36:AH36+AF48:AH48+AF60:AH60+AF72:AH72+AF84:AH84} -> 27522.51
C93: N° Total de Peças | D93: {=H10+H22+H34+H46+H58+H70+H82} -> 0 | J93: N° Total de Peças | K93: {=O10+O22+O34+O46+O58+O70+O82} -> 1918 | Q93: N° Total de Peças | R93: {=V10+V22+V34+V46+V58+V70+V82} -> 1973 | X93: N° Total de Peças | Y93: {=AC10+AC22+AC34+AC46+AC58+AC70+AC82} -> 1121 | AE93: N° Total de Peças | AF93: {=AJ10+AJ22+AJ34+AJ46+AJ58+AJ70+AJ82} -> 1524
C96: Faturamento por Loja na 1° Semana | J96: Faturamento por Loja na 2° Semana | Q96: Faturamento por Loja na 3° Semana | X96: Faturamento por Loja na 4° Semana | AE96: Faturamento por Loja na 4° 1/2 Semana
C97: Lojas | D97: Faturamento | E97: Não pago dia | F97: Recebimento | G97: Real da semana | H97: Peças | J97: Lojas | K97: Faturamento | L97: Não pago dia | M97: Recebimento | N97: Real da semana | O97: Peças | Q97: Lojas | R97: Faturamento | S97: Não pago dia | T97: Recebimento | U97: Real da semana | V97: Peças | X97: Lojas | Y97: Faturamento | Z97: Não pago dia | AA97: Recebimento | AB97: Real da semana | AC97: Peças | AE97: Lojas | AF97: Faturamento | AG97: Não pago dia | AH97: Recebimento | AI97: Real da semana | AJ97: Peças
C98: Lago Norte | D98: =D2+D14+D26+D38+D50+D62 -> 0 | E98: =E2+E14+E26+E38+E50+E62 -> 0 | F98: =F2+F14+F26+F38+F50+F62 -> 0 | G98: =F98-E98 -> 0 | H98: =H2+H14+H26+H38+H50+H62 -> 0 | J98: Lago Norte | K98: =K2+K14+K26+K38+K50+K62 -> 6340.41 | L98: =L2+L14+L26+L38+L50+L62 -> 1308.3 | M98: =M2+M14+M26+M38+M50+M62 -> 5604.11 | N98: =M98-L98 -> 4295.81 | O98: =O2+O14+O26+O38+O50+O62 -> 247 | Q98: Lago Norte | R98: =R2+R14+R26+R38+R50+R62 -> 3507.31 | S98: =S2+S14+S26+S38+S50+S62 -> 275 | T98: =T2+T14+T26+T38+T50+T62 -> 3292.31 | U98: =T98-S98 -> 3017.31 | V98: =V2+V14+V26+V38+V50+V62 -> 148 | X98: Lago Norte | Y98: =Y2+Y14+Y26+Y38+Y50+Y62 -> 3616.9 | Z98: =Z2+Z14+Z26+Z38+Z50+Z62 -> 585 | AA98: =AA2+AA14+AA26+AA38+AA50+AA62 -> 4370.3 | AB98: =AA98-Z98 -> 3785.3 | AC98: =AC2+AC14+AC26+AC38+AC50+AC62 -> 130 | AE98: Lago Norte | AF98: =AF2+AF14+AF26+AF38+AF50+AF62 -> 4031.71 | AG98: =AG2+AG14+AG26+AG38+AG50+AG62 -> 952.47 | AH98: =AH2+AH14+AH26+AH38+AH50+AH62 -> 4098.14 | AI98: =AH98-AG98 -> 3145.67 | AJ98: =AJ2+AJ14+AJ26+AJ38+AJ50+AJ62 -> 199
C99: 202 Norte | D99: =D3+D15+D27+D39+D51+D63 -> 0 | E99: =E3+E15+E27+E39+E51+E63 -> 0 | F99: =F3+F15+F27+F39+F51+F63 -> 0 | G99: =F99-E99 -> 0 | H99: =H3+H15+H27+H39+H51+H63 -> 0 | J99: 202 Norte | K99: =K3+K15+K27+K39+K51+K63 -> 4633.4 | L99: =L3+L15+L27+L39+L51+L63 -> 284 | M99: =M3+M15+M27+M39+M51+M63 -> 6265.2 | N99: =M99-L99 -> 5981.2 | O99: =O3+O15+O27+O39+O51+O63 -> 172 | Q99: 202 Norte | R99: =R3+R15+R27+R39+R51+R63 -> 5265.9 | S99: =S3+S15+S27+S39+S51+S63 -> 979.8 | T99: =T3+T15+T27+T39+T51+T63 -> 4688.1 | U99: =T99-S99 -> 3708.3 | V99: =V3+V15+V27+V39+V51+V63 -> 223 | X99: 202 Norte | Y99: =Y3+Y15+Y27+Y39+Y51+Y63 -> 3067.1 | Z99: =Z3+Z15+Z27+Z39+Z51+Z63 -> 1039.7 | AA99: =AA3+AA15+AA27+AA39+AA51+AA63 -> 2445.3 | AB99: =AA99-Z99 -> 1405.6 | AC99: =AC3+AC15+AC27+AC39+AC51+AC63 -> 150 | AE99: 202 Norte | AF99: =AF3+AF15+AF27+AF39+AF51+AF63 -> 2428.31 | AG99: =AG3+AG15+AG27+AG39+AG51+AG63 -> 1319.51 | AH99: =AH3+AH15+AH27+AH39+AH51+AH63 -> 1189.8 | AI99: =AH99-AG99 -> -129.71 | AJ99: =AJ3+AJ15+AJ27+AJ39+AJ51+AJ63 -> 111
C100: 213 Norte | D100: =D4+D16+D28+D40+D52+D64 -> 0 | E100: =E4+E16+E28+E40+E52+E64 -> 0 | F100: =F4+F16+F28+F40+F52+F64 -> 0 | G100: =F100-E100 -> 0 | H100: =H4+H16+H28+H40+H52+H64 -> 0 | J100: 213 Norte | K100: =K4+K16+K28+K40+K52+K64 -> 0 | L100: =L4+L16+L28+L40+L52+L64 -> 0 | M100: =M4+M16+M28+M40+M52+M64 -> 0 | N100: =M100-L100 -> 0 | O100: =O4+O16+O28+O40+O52+O64 -> 0 | Q100: 213 Norte | R100: =R4+R16+R28+R40+R52+R64 -> 0 | S100: =S4+S16+S28+S40+S52+S64 -> 0 | T100: =T4+T16+T28+T40+T52+T64 -> 0 | U100: =T100-S100 -> 0 | V100: =V4+V16+V28+V40+V52+V64 -> 0 | X100: 213 Norte | Y100: =Y4+Y16+Y28+Y40+Y52+Y64 -> 0 | Z100: =Z4+Z16+Z28+Z40+Z52+Z64 -> 0 | AA100: =AA4+AA16+AA28+AA40+AA52+AA64 -> 0 | AB100: =AA100-Z100 -> 0 | AC100: =AC4+AC16+AC28+AC40+AC52+AC64 -> 0 | AE100: 213 Norte | AF100: =AF4+AF16+AF28+AF40+AF52+AF64 -> 0 | AG100: =AG4+AG16+AG28+AG40+AG52+AG64 -> 0 | AH100: =AH4+AH16+AH28+AH40+AH52+AH64 -> 0 | AI100: =AH100-AG100 -> 0 | AJ100: =AJ4+AJ16+AJ28+AJ40+AJ52+AJ64 -> 0
C101: 307 Norte | D101: =D5+D17+D29+D41+D53+D65 -> 0 | E101: =E5+E17+E29+E41+E53+E65 -> 0 | F101: =F5+F17+F29+F41+F53+F65 -> 0 | G101: =F101-E101 -> 0 | H101: =H5+H17+H29+H41+H53+H65 -> 0 | J101: 307 Norte | K101: =K5+K17+K29+K41+K53+K65 -> 9995.53 | L101: =L5+L17+L29+L41+L53+L65 -> 2294.23 | M101: =M5+M17+M29+M41+M53+M65 -> 9466.1 | N101: =M101-L101 -> 7171.87 | O101: =O5+O17+O29+O41+O53+O65 -> 440 | Q101: 307 Norte | R101: =R5+R17+R29+R41+R53+R65 -> 8523.3 | S101: =S5+S17+S29+S41+S53+S65 -> 1425.4 | T101: =T5+T17+T29+T41+T53+T65 -> 9081.08 | U101: =T101-S101 -> 7655.68 | V101: =V5+V17+V29+V41+V53+V65 -> 488 | X101: 307 Norte | Y101: =Y5+Y17+Y29+Y41+Y53+Y65 -> 6801.32 | Z101: =Z5+Z17+Z29+Z41+Z53+Z65 -> 1557.56 | AA101: =AA5+AA17+AA29+AA41+AA53+AA65 -> 6644.45 | AB101: =AA101-Z101 -> 5086.89 | AC101: =AC5+AC17+AC29+AC41+AC53+AC65 -> 312 | AE101: 307 Norte | AF101: =AF5+AF17+AF29+AF41+AF53+AF65 -> 7436.8 | AG101: =AG5+AG17+AG29+AG41+AG53+AG65 -> 1401.8 | AH101: =AH5+AH17+AH29+AH41+AH53+AH65 -> 7905.28 | AI101: =AH101-AG101 -> 6503.48 | AJ101: =AJ5+AJ17+AJ29+AJ41+AJ53+AJ65 -> 276
C102: 313 Norte | D102: =D6+D18+D30+D42+D54+D66 -> 0 | E102: =E6+E18+E30+E42+E54+E66 -> 0 | F102: =F6+F18+F30+F42+F54+F66 -> 0 | G102: =F102-E102 -> 0 | H102: =H6+H18+H30+H42+H54+H66 -> 0 | J102: 313 Norte | K102: =K6+K18+K30+K42+K54+K66 -> 6477.66 | L102: =L6+L18+L30+L42+L54+L66 -> 682.8 | M102: =M6+M18+M30+M42+M54+M66 -> 7014.41 | N102: =M102-L102 -> 6331.61 | O102: =O6+O18+O30+O42+O54+O66 -> 316 | Q102: 313 Norte | R102: =R6+R18+R30+R42+R54+R66 -> 4704.6 | S102: =S6+S18+S30+S42+S54+S66 -> 512 | T102: =T6+T18+T30+T42+T54+T66 -> 4673.6 | U102: =T102-S102 -> 4161.6 | V102: =V6+V18+V30+V42+V54+V66 -> 247 | X102: 313 Norte | Y102: =Y6+Y18+Y30+Y42+Y54+Y66 -> 2611.28 | Z102: =Z6+Z18+Z30+Z42+Z54+Z66 -> 70.4 | AA102: =AA6+AA18+AA30+AA42+AA54+AA66 -> 2625.78 | AB102: =AA102-Z102 -> 2555.38 | AC102: =AC6+AC18+AC30+AC42+AC54+AC66 -> 129 | AE102: 313 Norte | AF102: =AF6+AF18+AF30+AF42+AF54+AF66 -> 4696.6 | AG102: =AG6+AG18+AG30+AG42+AG54+AG66 -> 894.9 | AH102: =AH6+AH18+AH30+AH42+AH54+AH66 -> 4363.4 | AI102: =AH102-AG102 -> 3468.5 | AJ102: =AJ6+AJ18+AJ30+AJ42+AJ54+AJ66 -> 217
C103: 314 Sul | D103: =D7+D19+D31+D43+D55+D67 -> 0 | E103: =E7+E19+E31+E43+E55+E67 -> 0 | F103: =F7+F19+F31+F43+F55+F67 -> 0 | G103: =F103-E103 -> 0 | H103: =H7+H19+H31+H43+H55+H67 -> 0 | J103: 314 Sul | K103: =K7+K19+K31+K43+K55+K67 -> 0 | L103: =L7+L19+L31+L43+L55+L67 -> 0 | M103: =M7+M19+M31+M43+M55+M67 -> 0 | N103: =M103-L103 -> 0 | O103: =O7+O19+O31+O43+O55+O67 -> 0 | Q103: 314 Sul | R103: =R7+R19+R31+R43+R55+R67 -> 0 | S103: =S7+S19+S31+S43+S55+S67 -> 0 | T103: =T7+T19+T31+T43+T55+T67 -> 0 | U103: =T103-S103 -> 0 | V103: =V7+V19+V31+V43+V55+V67 -> 0 | X103: 314 Sul | Y103: =Y7+Y19+Y31+Y43+Y55+Y67 -> 0 | Z103: =Z7+Z19+Z31+Z43+Z55+Z67 -> 0 | AA103: =AA7+AA19+AA31+AA43+AA55+AA67 -> 0 | AB103: =AA103-Z103 -> 0 | AC103: =AC7+AC19+AC31+AC43+AC55+AC67 -> 0 | AE103: 314 Sul | AF103: =AF7+AF19+AF31+AF43+AF55+AF67 -> 0 | AG103: =AG7+AG19+AG31+AG43+AG55+AG67 -> 0 | AH103: =AH7+AH19+AH31+AH43+AH55+AH67 -> 0 | AI103: =AH103-AG103 -> 0 | AJ103: =AJ7+AJ19+AJ31+AJ43+AJ55+AJ67 -> 0
C104: Sudoeste | D104: =D8+D20+D32+D44+D56+D68 -> 0 | E104: =E8+E20+E32+E44+E56+E68 -> 0 | F104: =F8+F20+F32+F44+F56+F68 -> 0 | G104: =F104-E104 -> 0 | H104: =H8+H20+H32+H44+H56+H68 -> 0 | J104: Sudoeste | K104: =K8+K20+K32+K44+K56+K68 -> 3928.74 | L104: =L8+L20+L32+L44+L56+L68 -> 903.9 | M104: =M8+M20+M32+M44+M56+M68 -> 3976.24 | N104: =M104-L104 -> 3072.34 | O104: =O8+O20+O32+O44+O56+O68 -> 184 | Q104: Sudoeste | R104: =R8+R20+R32+R44+R56+R68 -> 2319.2 | S104: =S8+S20+S32+S44+S56+S68 -> 534.8 | T104: =T8+T20+T32+T44+T56+T68 -> 2519.1 | U104: =T104-S104 -> 1984.3 | V104: =V8+V20+V32+V44+V56+V68 -> 120 | X104: Sudoeste | Y104: =Y8+Y20+Y32+Y44+Y56+Y68 -> 1870.1 | Z104: =Z8+Z20+Z32+Z44+Z56+Z68 -> 128.9 | AA104: =AA8+AA20+AA32+AA44+AA56+AA68 -> 2090.2 | AB104: =AA104-Z104 -> 1961.3 | AC104: =AC8+AC20+AC32+AC44+AC56+AC68 -> 108 | AE104: Sudoeste | AF104: =AF8+AF20+AF32+AF44+AF56+AF68 -> 2678 | AG104: =AG8+AG20+AG32+AG44+AG56+AG68 -> 859.8 | AH104: =AH8+AH20+AH32+AH44+AH56+AH68 -> 2843.35 | AI104: =AH104-AG104 -> 1983.55 | AJ104: =AJ8+AJ20+AJ32+AJ44+AJ56+AJ68 -> 113
...

Sheet Meta faturamento 2025
A2: Meta Faturamento Maio
A4: Loja | B4: Fat. Anterior | C4: % a aumentar | E4: Meta Mês | F4: Valor faturado até o momento (dentro do mês) | H4: Valor que falta para atingir a meta | I4: Valor a ser faturado no dia para atingir a meta
A6: 202N | B6: ='Faturamento '!E40 -> 0 | C6: 0.1 | D6: =B6*C6 -> 0 | E6: =B6+D6 -> 0 | F6: ='Faturamento '!F40 -> 0 | H6: =E6-F6 -> 0 | I6: =H6/3 -> 0
A7: 213N | B7: ='Faturamento '!E41 -> 0 | C7: 0.1 | D7: =B7*C7 -> 0 | E7: =B7+D7 -> 0 | F7: ='Faturamento '!F41 -> 0 | H7: =E7-F7 -> 0 | I7: =H7/3 -> 0
A8: 307N | B8: ='Faturamento '!E42 -> 0 | C8: 0.1 | D8: =B8*C8 -> 0 | E8: =B8+D8 -> 0 | F8: ='Faturamento '!F42 -> 0 | H8: =E8-F8 -> 0 | I8: =H8/3 -> 0
A9: 313N | B9: ='Faturamento '!E43 -> 0 | C9: 0.1 | D9: =B9*C9 -> 0 | E9: =B9+D9 -> 0 | F9: ='Faturamento '!F43 -> 0 | H9: =E9-F9 -> 0 | I9: =H9/3 -> 0
A10: Lago | B10: ='Faturamento '!E45 -> 0 | C10: 0.1 | D10: =B10*C10 -> 0 | E10: =B10+D10 -> 0 | F10: ='Faturamento '!F45 -> 0 | H10: =E10-F10 -> 0 | I10: =H10/3 -> 0
A11: Noroeste | B11: ='Faturamento '!E47 -> 0 | C11: 0.1 | D11: =B11*C11 -> 0 | E11: =B11+D11 -> 0 | F11: ='Faturamento '!F47 -> 0 | H11: =E11-F11 -> 0 | I11: =H11/3 -> 0
A12: Sudoeste | B12: ='Faturamento '!E46 -> 0 | C12: 0.2 | D12: =B12*C12 -> 0 | E12: =B12+D12 -> 0 | F12: ='Faturamento '!F46 -> 0 | H12: =E12-F12 -> 0 | I12: =H12/3 -> 0
A16: Meta Faturamento Junho
A18: Loja | B18: Fat. Anterior | C18: % a aumentar | E18: Meta Mês | F18: Valor faturado até o momento (dentro do mês) | H18: Valor que falta para atingir a meta | I18: Valor a ser faturado no dia para atingir a meta
A20: 202N | B20: ='Faturamento '!F40 -> 0 | C20: 0.1 | D20: =B20*C20 -> 0 | E20: =B20+D20 -> 0 | F20: ='Faturamento '!G40 -> 0 | H20: =E20-F20 -> 0 | I20: =H20/3 -> 0 | J20: Meta batida (receberá 100% = 1% do faturamento)
A21: 213N | B21: ='Faturamento '!F41 -> 0 | C21: 0.1 | D21: =B21*C21 -> 0 | E21: =B21+D21 -> 0 | F21: ='Faturamento '!G41 -> 0 | H21: =E21-F21 -> 0 | I21: =H21/3 -> 0
A22: 307N | B22: ='Faturamento '!F42 -> 0 | C22: 0.1 | D22: =B22*C22 -> 0 | E22: =B22+D22 -> 0 | F22: ='Faturamento '!G42 -> 0 | H22: =E22-F22 -> 0 | I22: =H22/3 -> 0
A23: 313N | B23: ='Faturamento '!F43 -> 0 | C23: 0.1 | D23: =B23*C23 -> 0 | E23: =B23+D23 -> 0 | F23: ='Faturamento '!G43 -> 0 | H23: =E23-F23 -> 0 | I23: =H23/3 -> 0 | J23: Receberá valor proporcional, 94,56% = 0,9456% do faturamento.
A24: Lago | B24: ='Faturamento '!F45 -> 0 | C24: 0.1 | D24: =B24*C24 -> 0 | E24: =B24+D24 -> 0 | F24: ='Faturamento '!G45 -> 0 | H24: =E24-F24 -> 0 | I24: =H24/3 -> 0
A25: Noroeste | B25: ='Faturamento '!F47 -> 0 | C25: 0.1 | D25: =B25*C25 -> 0 | E25: =B25+D25 -> 0 | F25: ='Faturamento '!G47 -> 0 | H25: =E25-F25 -> 0 | I25: =H25/3 -> 0 | J25: Meta batida (receberá 100% = 1% do faturamento)
A26: Sudoeste | B26: ='Faturamento '!F46 -> 0 | C26: 0.1 | D26: =B26*C26 -> 0 | E26: =B26+D26 -> 0 | F26: ='Faturamento '!G46 -> 0 | H26: =E26-F26 -> 0 | I26: =H26/3 -> 0 | J26: Meta batida (receberá 100% = 1% do faturamento)
A30: Meta Dani | B30: R$ 21.890,98 | E30: 21890.98 | F30: =Jun!D63+Jun!K8+Jun!K30+Jun!K52+Jun!K74+Jun!R19+Jun!R41+Jun!R63+Jun!Y8+Jun!Y30+Jun!AF19+Jun!AF41+Jun!AF63+456 -> #REF! | H30: =E30-F30 -> #REF! | J30: =F30*10% -> #REF!
A31: Meta Ingrid | B31: R$ 17.090,24 | E31: 17090.24 | F31: =Jun!D74+Jun!K19+Jun!K41+Jun!K63+Jun!R8+Jun!R30+Jun!R52+Jun!R74+Jun!Y19+Jun!Y41+Jun!Y52+Jun!Y63+Jun!AF8+Jun!AF30+Jun!AF52+Jun!AF74 -> #REF! | H31: =E31-F31 -> #REF! | J31: =F31*10% -> #REF!
F33: =F30+F31 -> #REF!
F34: =F25-F33 -> #REF! | G34: Luana
A39: Meta Faturamento Julho
A41: Loja | B41: Fat. Anterior | C41: % a aumentar | E41: Meta Mês | F41: Valor faturado até o momento (dentro do mês) | H41: Valor que falta para atingir a meta | I41: Valor a ser faturado no dia para atingir a meta
A43: 202N | B43: ='Faturamento '!G40 -> 0 | C43: 0.1 | D43: =B43*C43 -> 0 | E43: =B43+D43 -> 0 | F43: ='Faturamento '!H40 -> 0 | H43: =F43-E43 -> 0 | I43: =H43/3 -> 0 | J43: =F43*100/E43 -> #DIV/0!
A44: 213N | B44: ='Faturamento '!G41 -> 0 | C44: 0.1 | D44: =B44*C44 -> 0 | E44: =B44+D44 -> 0 | F44: ='Faturamento '!H41 -> 0 | H44: =F44-E44 -> 0 | I44: =H44/3 -> 0 | J44: =F44*100/E44 -> #DIV/0!
A45: 307N | B45: ='Faturamento '!G42 -> 0 | C45: 0.1 | D45: =B45*C45 -> 0 | E45: =B45+D45 -> 0 | F45: ='Faturamento '!H42 -> 0 | H45: =F45-E45 -> 0 | I45: =H45/3 -> 0 | J45: =F45*100/E45 -> #DIV/0!
A46: 313N | B46: ='Faturamento '!G43 -> 0 | C46: 0.1 | D46: =B46*C46 -> 0 | E46: =B46+D46 -> 0 | F46: ='Faturamento '!H43 -> 0 | H46: =F46-E46 -> 0 | I46: =H46/3 -> 0 | J46: =F46*100/E46 -> #DIV/0!
A47: Lago | B47: ='Faturamento '!G45 -> 0 | C47: 0.1 | D47: =B47*C47 -> 0 | E47: =B47+D47 -> 0 | F47: ='Faturamento '!H45 -> 0 | H47: =F47-E47 -> 0 | I47: =H47/3 -> 0 | J47: =F47*100/E47 -> #DIV/0!
A48: Noroeste | B48: ='Faturamento '!G47 -> 0 | C48: 0.1 | D48: =B48*C48 -> 0 | E48: =B48+D48+0.01 -> 0.01 | F48: ='Faturamento '!H47 -> 0 | H48: =F48-E48 -> -0.01 | I48: =H48/3 -> -0.0033333333 | J48: =F48*100/E48 -> 0
A49: Sudoeste | B49: ='Faturamento '!G46 -> 0 | C49: 0.1 | D49: =B49*C49 -> 0 | E49: =B49+D49 -> 0 | F49: ='Faturamento '!H46 -> 0 | H49: =F49-E49 -> 0 | I49: =H49/3 -> 0 | J49: =F49*100/E49 -> #DIV/0!
A51: Meta Dani | B51: =F30 -> #REF! | E51: =#REF! -> #REF! | F51: =Jul!D8+Jul!D30+Jul!D52+Jul!D74+Jul!K19+Jul!K41+Jul!K63+Jul!R8+Jul!R30+Jul!R63+Jul!R74+Jul!Y19+Jul!Y41+Jul!Y63+Jul!AF8+Jul!AF30 -> #REF! | H51: =F51-E51 -> #REF! | J51: =F51*100/E51 -> #REF!
A52: Meta Ingrid | B52: =F31 -> #REF! | E52: =#REF! -> #REF! | F52: =Jul!D19+Jul!D41+Jul!D63+Jul!K8+Jul!K30+Jul!K52+Jul!K74+Jul!R19+Jul!R41+Jul!R52+Jul!Y8+Jul!Y30+Jul!Y52+Jul!AF19 -> #REF! | H52: =F52-E52 -> #REF! | J52: =F52*100/E52 -> #REF!
A56: Meta Faturamento Agosto
A58: Loja | B58: Fat. Anterior | C58: % a aumentar | E58: Meta Mês | F58: Valor faturado até o momento (dentro do mês) | H58: Valor que falta para atingir a meta | I58: Valor a ser faturado no dia para atingir a meta
A60: 202N | B60: ='Faturamento '!H40 -> 0 | C60: 0.1 | D60: =B60*C60 -> 0 | E60: =B60+D60 -> 0 | F60: ='Faturamento '!I40 -> 0 | H60: =F60-E60 -> 0 | I60: =H60/3 -> 0
A61: 213N | B61: ='Faturamento '!H41 -> 0 | C61: 0.1 | D61: =B61*C61 -> 0 | E61: =B61+D61 -> 0 | F61: ='Faturamento '!I41 -> 0 | H61: =F61-E61 -> 0 | I61: =H61/3 -> 0 | J61: 197.54
A62: 307N | B62: ='Faturamento '!H42 -> 0 | C62: 0.05 | D62: =B62*C62 -> 0 | E62: =B62+D62 -> 0 | F62: ='Faturamento '!I42 -> 0 | H62: =F62-E62 -> 0 | I62: =H62/3 -> 0
A63: 313N | B63: ='Faturamento '!H43 -> 0 | C63: 0.1 | D63: =B63*C63 -> 0 | E63: =B63+D63 -> 0 | F63: ='Faturamento '!I43 -> 0 | H63: =F63-E63 -> 0 | I63: =H63/3 -> 0
A64: 314S | E64: 5000 | F64: ='Faturamento '!I44 -> 0 | H64: =F64-E64 -> -5000
A65: Lago | B65: ='Faturamento '!H45 -> 0 | C65: 0.1 | D65: =B65*C65 -> 0 | E65: =B65+D65 -> 0 | F65: ='Faturamento '!I45 -> 0 | H65: =F65-E65 -> 0 | I65: =H65/3 -> 0 | J65: 182.41
A66: Noroeste | B66: ='Faturamento '!H47 -> 0 | C66: 0.05 | D66: =B66*C66 -> 0 | E66: =B66+D66+0.01 -> 0.01 | F66: ='Faturamento '!I47 -> 0 | H66: =F66-E66 -> -0.01 | I66: =H66/3 -> -0.0033333333
A67: Sudoeste | B67: ='Faturamento '!H46 -> 0 | C67: 0.1 | D67: =B67*C67 -> 0 | E67: =B67+D67 -> 0 | F67: ='Faturamento '!I46 -> 0 | H67: =F67-E67 -> 0 | I67: =H67/3 -> 0
A69: Meta Dani | B69: 29000 | C69: 0 | E69: =B69*C69 -> 0 | F69: =B69+E69 -> 29000 | G69: =#REF! -> #REF! | H69: =G69-F69 -> #REF! | J69: 288.69
A70: Meta Ingrid | B70: 29000 | C70: 0 | E70: =B70*C70 -> 0 | F70: =B70+E70 -> 29000 | G70: =#REF! -> #REF! | H70: =G70-F70 -> #REF!
A75: Meta Faturamento Setembro
A77: Loja | B77: Fat. Anterior | C77: % a aumentar | E77: Valor a aumentar | F77: Meta Mês | G77: Valor faturado até o momento (dentro do mês) | I77: Valor que falta para atingir a meta
A79: 202N | B79: ='Faturamento '!I40 -> 0 | C79: 0.05 | D79: =B79*C79 -> 0 | E79: =B79*C79 -> 0 | F79: =B79+E79 -> 0 | G79: ='Faturamento '!J40 -> 0 | I79: =G79-F79 -> 0 | J79: =G79*100/F79 -> #DIV/0!
A80: 213N | B80: ='Faturamento '!I41 -> 0 | C80: 0.05 | D80: =B80*C80 -> 0 | E80: =B80*C80 -> 0 | F80: =B80+E80 -> 0 | G80: ='Faturamento '!J41 -> 0 | I80: =G80-F80 -> 0 | J80: =G80*100/F80 -> #DIV/0!
A81: 307N | B81: ='Faturamento '!I42 -> 0 | C81: 0.05 | D81: =B81*C81 -> 0 | E81: =B81*C81 -> 0 | F81: =B81+E81 -> 0 | G81: ='Faturamento '!J42 -> 0 | I81: =G81-F81 -> 0 | J81: =G81*100/F81 -> #DIV/0! | K81: 373.48
A82: 313N | B82: ='Faturamento '!I43 -> 0 | C82: 0.1 | D82: =B82*C82 -> 0 | E82: =B82*C82 -> 0 | F82: =B82+E82 -> 0 | G82: ='Faturamento '!J43 -> 0 | I82: =G82-F82 -> 0 | J82: =G82*100/F82 -> #DIV/0! | K82: 144.18
A83: 314S | B83: ='Faturamento '!I44 -> 0 | C83: 0.35 | E83: =B83*C83 -> 0 | F83: =B83+E83 -> 0 | G83: ='Faturamento '!J44 -> 0 | I83: =G83-F83 -> 0 | J83: =G83*100/F83 -> #DIV/0! | K83: 86.95
A84: Lago | B84: ='Faturamento '!I45 -> 0 | C84: 0.05 | D84: =B84*C84 -> 0 | E84: =B84*C84 -> 0 | F84: =B84+E84 -> 0 | G84: ='Faturamento '!J45 -> 0 | I84: =G84-F84 -> 0 | J84: =G84*100/F84 -> #DIV/0!
A85: Noroeste | B85: ='Faturamento '!I47 -> 0 | C85: 0.05 | D85: =B85*C85 -> 0 | E85: =B85*C85 -> 0 | F85: =B85+E85 -> 0 | G85: ='Faturamento '!J47 -> 0 | I85: =G85-F85 -> 0 | J85: =G85*100/F85 -> #DIV/0! | K85: 531.45 | L85: 2 | M85: =K85/L85 -> 265.725
A86: Sudoeste | B86: ='Faturamento '!I46 -> 0 | C86: 0.1 | D86: =B86*C86 -> 0 | E86: =B86*C86 -> 0 | F86: =B86+E86 -> 0 | G86: ='Faturamento '!J46 -> 0 | I86: =G86-F86 -> 0 | J86: =G86*100/F86 -> #DIV/0!
A89: Meta Faturamento Outubro
A91: Loja | B91: Fat. Anterior | C91: % a aumentar | E91: Valor a aumentar | F91: Meta Mês | G91: Valor faturado até o momento (dentro do mês) | I91: Valor que falta para atingir a meta | L91: % atingido
A93: 202N | B93: ='Faturamento '!J40 -> 0 | C93: 0.05 | D93: =B93*C93 -> 0 | E93: =B93*C93 -> 0 | F93: =B93+E93 -> 0 | G93: ='Faturamento '!K40 -> 0 | I93: =G93-F93 -> 0 | J93: 1 | K93: =I93/J93 -> 0 | L93: =G93*100/F93 -> #DIV/0! | M93: =G93*1% -> 0 | P93: 202N
A94: 213N | B94: ='Faturamento '!J41 -> 0 | C94: 0.05 | D94: =B94*C94 -> 0 | E94: =B94*C94 -> 0 | F94: =B94+E94 -> 0 | G94: ='Faturamento '!K41 -> 0 | I94: =G94-F94 -> 0 | J94: 1 | K94: =I94/J94 -> 0 | L94: =G94*100/F94 -> #DIV/0! | M94: =G94*1% -> 0 | P94: 213N
A95: 307N | B95: ='Faturamento '!J42 -> 0 | C95: 0.05 | D95: =B95*C95 -> 0 | E95: =B95*C95 -> 0 | F95: =B95+E95 -> 0 | G95: ='Faturamento '!K42 -> 0 | I95: =G95-F95 -> 0 | L95: =G95*100/F95 -> #DIV/0! | M95: =G95*1% -> 0 | P95: 307N
A96: 313N | B96: ='Faturamento '!J43 -> 0 | C96: 0.1 | D96: =B96*C96 -> 0 | E96: =B96*C96 -> 0 | F96: =B96+E96 -> 0 | G96: ='Faturamento '!K43 -> 0 | I96: =G96-F96 -> 0 | J96: 1 | K96: =I96/J96 -> 0 | L96: =G96*100/F96 -> #DIV/0! | M96: =G96*1% -> 0 | P96: 313N
A97: 314S | B97: ='Faturamento '!J44 -> 0 | C97: 0.35 | E97: =B97*C97 -> 0 | F97: =B97+E97 -> 0 | G97: ='Faturamento '!K44 -> 0 | I97: =G97-F97 -> 0 | L97: =G97*100/F97 -> #DIV/0! | M97: =G97*1% -> 0 | O97: 120.76 | P97: 314S | R97: 20.8
A98: Lago | B98: ='Faturamento '!J45 -> 0 | C98: 0.05 | D98: =B98*C98 -> 0 | E98: =B98*C98 -> 0 | F98: =B98+E98 -> 0 | G98: ='Faturamento '!K45 -> 0 | I98: =G98-F98 -> 0 | L98: =G98*100/F98 -> #DIV/0! | M98: =G98*1% -> 0 | O98: 187.84 | P98: Lago | R98: 57.84
A99: Noroeste | B99: ='Faturamento '!J47 -> 0 | C99: 0.05 | D99: =B99*C99 -> 0 | E99: =B99*C99 -> 0 | F99: =B99+E99 -> 0 | G99: ='Faturamento '!K47 -> 0 | I99: =G99-F99 -> 0 | J99: 1 | K99: =I99/J99 -> 0 | L99: =G99*100/F99 -> #DIV/0! | M99: =G99*1% -> 0 | N99: 2 | O99: 33.75 | P99: Noroeste
A100: Sudoeste | B100: ='Faturamento '!J46 -> 0 | C100: 0.1 | D100: =B100*C100 -> 0 | E100: =B100*C100 -> 0 | F100: =B100+E100 -> 0 | G100: ='Faturamento '!K46 -> 0 | I100: =G100-F100 -> 0 | L100: =G100*100/F100 -> #DIV/0! | M100: =G100*1% -> 0 | O100: 0 | P100: Sudoeste | R100: =SUM(R97:R98) -> 78.64
O101: =SUM(O94:O100) -> 342.35
L103: =M99/2 -> 0 | M103: =L103-O99 -> -33.75
A104: Meta Faturamento Novembro
A106: Loja | B106: Fat. Anterior | C106: % a aumentar | E106: Valor a aumentar | F106: Meta Mês | G106: Valor faturado até o momento (dentro do mês) | I106: Valor que falta para atingir a meta
A108: 202N | B108: ='Faturamento '!K40 -> 0 | C108: 0.1246 | D108: =F108-B108 -> 15000 | E108: =D108 -> 15000 | F108: 15000 | G108: ='Faturamento '!L40 -> 0 | I108: =G108-F108 -> -15000 | J108: =G108*100/F108 -> 0
A109: 213N | B109: ='Faturamento '!K41 -> 0 | C109: 0.02 | D109: =F109-B109 -> 18000 | E109: =D109 -> 18000 | F109: 18000 | G109: ='Faturamento '!L41 -> 0 | I109: =G109-F109 -> -18000 | J109: =G109*100/F109 -> 0 | K109: Dani | L109: 17 | M109: =L112/K112*L109 -> 222.51867
A110: 307N | B110: ='Faturamento '!K42 -> 0 | C110: 0.01 | D110: =F110-B110 -> 43000 | E110: =D110 -> 43000 | F110: 43000 | G110: ='Faturamento '!L42 -> 0 | I110: =G110-F110 -> -43000 | J110: =G110*100/F110 -> 0 | K110: Luana | L110: =30-L109 -> 13 | M110: =L112/30*L110 -> 170.16133
A111: 313N | B111: ='Faturamento '!K43 -> 0 | C111: 0.2 | D111: =F111-B111 -> 14000 | E111: =D111 -> 14000 | F111: 14000 | G111: ='Faturamento '!L43 -> 0 | I111: =G111-F111 -> -14000 | J111: =G111*100/F111 -> 0
A112: 314S | B112: ='Faturamento '!K44 -> 0 | C112: 0.3 | D112: =F112-B112 -> 15000 | E112: =D112 -> 15000 | F112: 15000 | G112: ='Faturamento '!L44 -> 0 | I112: =G112-F112 -> -15000 | J112: =G112*100/F112 -> 0 | K112: 30 | L112: 392.68
A113: Lago | B113: ='Faturamento '!K45 -> 0 | C113: 0.05 | D113: =F113-B113 -> 19000 | E113: =D113 -> 19000 | F113: 19000 | G113: ='Faturamento '!L45 -> 0 | I113: =G113-F113 -> -19000 | J113: =G113*100/F113 -> 0 | K113: =L109*L112/K112 -> 222.51867
A114: Noroeste | B114: ='Faturamento '!K47 -> 0 | C114: 0.015 | D114: =F114-B114 -> 58000 | E114: =D114 -> 58000 | F114: 58000 | G114: ='Faturamento '!L47 -> 0 | I114: =G114-F114 -> -58000 | J114: =G114*100/F114 -> 0
A115: Sudoeste | B115: ='Faturamento '!K46 -> 0 | C115: 0.1 | D115: =F115-B115 -> 20000 | E115: =D115 -> 20000 | F115: 20000 | G115: ='Faturamento '!L46 -> 0 | I115: =G115-F115 -> -20000 | J115: =G115*100/F115 -> 0
F117: =SUM(F106:F115) -> 202000 | G117: =SUM(G106:G115) -> 0 | I117: =G117*100/F117 -> 0
A121: Meta Faturamento Dezembro
A123: Loja | B123: Fat. Anterior | C123: % a aumentar | E123: Valor real a aumentar | F123: Meta Mês | G123: Valor faturado até o momento (dentro do mês) | I123: Valor que falta para atingir a meta
A125: 202N | B125: ='Faturamento '!L40 -> 0 | C125: 0.05 | D125: =B125*C125 -> 0 | E125: =F125-B125 -> 17500 | F125: 17500 | G125: ='Faturamento '!M40 -> 0 | I125: =G125-F125 -> -17500 | J125: =G125*100/F125 -> 0
A126: 213N | B126: ='Faturamento '!L41 -> 0 | C126: 0.3 | D126: =B126*C126 -> 0 | E126: =F126-B126 -> 17000 | F126: 17000 | G126: ='Faturamento '!M41 -> 0 | I126: =G126-F126 -> -17000 | J126: =G126*100/F126 -> 0
A127: 307N | B127: ='Faturamento '!L42 -> 0 | C127: 0.02 | D127: =B127*C127 -> 0 | E127: =F127-B127 -> 41000 | F127: 41000 | G127: ='Faturamento '!M42 -> 0 | I127: =G127-F127 -> -41000 | J127: =G127*100/F127 -> 0
A128: 313N | B128: ='Faturamento '!L43 -> 0 | C128: 0.1 | D128: =B128*C128 -> 0 | E128: =F128-B128 -> 15500 | F128: 15500 | G128: ='Faturamento '!M43 -> 0 | I128: =G128-F128 -> -15500 | J128: =G128*100/F128 -> 0
A129: 314S | B129: ='Faturamento '!L44 -> 0 | C129: 0.3 | D129: =B129*C129 -> 0 | E129: =F129-B129 -> 15000 | F129: 15000 | G129: ='Faturamento '!M44 -> 0 | I129: =G129-F129 -> -15000 | J129: =G129*100/F129 -> 0
A130: Lago | B130: ='Faturamento '!L45 -> 0 | C130: 0.05 | D130: =B130*C130 -> 0 | E130: =F130-B130 -> 21000 | F130: 21000 | G130: ='Faturamento '!M45 -> 0 | I130: =G130-F130 -> -21000 | J130: =G130*100/F130 -> 0
A131: Noroeste | B131: ='Faturamento '!L47 -> 0 | C131: 0.05 | D131: =B131*C131 -> 0 | E131: =F131-B131 -> 52000 | F131: 52000 | G131: ='Faturamento '!M47 -> 0 | I131: =G131-F131 -> -52000 | J131: =G131*100/F131 -> 0
A132: Sudoeste | B132: ='Faturamento '!L46 -> 0 | C132: 0.1 | D132: =B132*C132 -> 0 | E132: =F132-B132 -> 18000 | F132: 18000 | G132: ='Faturamento '!M46 -> 0 | I132: =G132-F132 -> -18000 | J132: =G132*100/F132 -> 0
F134: =SUM(F123:F132) -> 197000 | G134: =SUM(G123:G132) -> 0
A138: Meta Faturamento Janeiro
A140: Loja | B140: Fat. Anterior | C140: % a aumentar | E140: Valor real a aumentar | F140: Meta Mês | G140: Valor faturado até o momento (dentro do mês) | I140: Valor que falta para atingir a meta
A142: 202N | B142: ='Faturamento '!L57 | C142: 0.05 | D142: =B142*C142 -> 0 | E142: =F142-B142 -> 15000 | F142: 15000 | G142: =Jan!D128 -> 14956.86 | I142: =G142-F142 -> -43.14 | J142: =G142*100/F142 -> 99.7124
A143: 213N | B143: ='Faturamento '!L58 | C143: 0.3 | D143: =B143*C143 -> 0 | E143: =F143-B143 -> 18000 | F143: 18000 | G143: =Jan!D129 -> 0 | I143: =G143-F143 -> -18000 | J143: =G143*100/F143 -> 0
A144: 307N | B144: ='Faturamento '!L59 | C144: 0.02 | D144: =B144*C144 -> 0 | E144: =F144-B144 -> 41000 | F144: 41000 | G144: =Jan!D130 -> 48020.92 | I144: =G144-F144 -> 7020.92 | J144: =G144*100/F144 -> 117.1242
A145: 313N | B145: ='Faturamento '!L60 | C145: 0.1 | D145: =B145*C145 -> 0 | E145: =F145-B145 -> 15000 | F145: 15000 | G145: =Jan!D131 -> 30515.35 | I145: =G145-F145 -> 15515.35 | J145: =G145*100/F145 -> 203.43567
A146: 314S | B146: ='Faturamento '!L61 | C146: 0.3 | D146: =B146*C146 -> 0 | E146: =F146-B146 -> 15000 | F146: 15000 | G146: =Jan!D132 -> 0 | I146: =G146-F146 -> -15000 | J146: =G146*100/F146 -> 0
A147: Lago | B147: ='Faturamento '!L62 | C147: 0.05 | D147: =B147*C147 -> 0 | E147: =F147-B147 -> 18000 | F147: 18000 | G147: =Jan!D127 -> 19569.73 | I147: =G147-F147 -> 1569.73 | J147: =G147*100/F147 -> 108.72072
A148: Noroeste | B148: ='Faturamento '!L64 | C148: 0.05 | D148: =B148*C148 -> 0 | E148: =F148-B148 -> 52000 | F148: 52000 | G148: =Jan!D134 -> 63686.35 | I148: =G148-F148 -> 11686.35 | J148: =G148*100/F148 -> 122.47375
A149: Sudoeste | B149: ='Faturamento '!L63 | C149: 0.1 | D149: =B149*C149 -> 0 | E149: =F149-B149 -> 19000 | F149: 19000 | G149: =Jan!D133 -> 19482.65 | I149: =G149-F149 -> 482.65 | J149: =G149*100/F149 -> 102.54026
A152: Meta não pago Acumulado | D152: Meta de Faturamento
...

Sheet Mar
B1: Dia | C1: Lojas | D1: Faturamento dia | E1: Não pago dia | F1: Recebido dia | G1: Não pago Acumulado | H1: Peças | I1: Dia | J1: Lojas | K1: Faturamento | L1: Não pago dia | M1: Recebido dia | N1: Não pago Acumulado | O1: Peças | P1: Dia | Q1: Lojas | R1: Faturamento | S1: Não pago dia | T1: Recebido dia | U1: Não pago Acumulado | V1: Peças | W1: Dia | X1: Lojas | Y1: Faturamento | Z1: Não pago dia | AA1: Recebido dia | AB1: Não pago Acumulado | AC1: Peças | AD1: Dia | AE1: Lojas | AF1: Faturamento | AG1: Não pago dia | AH1: Recebido dia | AI1: Não pago Acumulado | AJ1: Peças | AM1: Lojas | AN1: Faturamento | AO1: Não pago dia | AP1: Recebido | AQ1: Peças
A2: Segunda-feira | B2: 45747 | C2: Lago Norte | I2: 45719 | J2: Lago Norte | P2: 45726 | Q2: Lago Norte | W2: 45733 | X2: Lago Norte | AD2: 45740 | AE2: Lago Norte | AL2: Faturamento Total das Segundas-feiras | AM2: Lago Norte | AN2: =D2+K2+R2+Y2+AF2 -> 0 | AO2: =E2+L2+S2+Z2+AG2 -> 0 | AP2: =F2+M2+T2+AA2+AH2 -> 0 | AQ2: =H2+O2+V2+AC2+AJ2 -> 0
C3: 202 Norte | J3: 202 Norte | Q3: 202 Norte | X3: 202 Norte | AE3: 202 Norte | AM3: 202 Norte | AN3: =D3+K3+R3+Y3+AF3 -> 0 | AO3: =E3+L3+S3+Z3+AG3 -> 0 | AP3: =F3+M3+T3+AA3+AH3 -> 0 | AQ3: =H3+O3+V3+AC3+AJ3 -> 0
C4: 213 Norte | J4: 213 Norte | Q4: 213 Norte | X4: 213 Norte | AE4: 213 Norte | AM4: 213 Norte | AN4: =D4+K4+R4+Y4+AF4 -> 0 | AO4: =E4+L4+S4+Z4+AG4 -> 0 | AP4: =F4+M4+T4+AA4+AH4 -> 0 | AQ4: =H4+O4+V4+AC4+AJ4 -> 0
C5: 307 Norte | J5: 307 Norte | Q5: 307 Norte | X5: 307 Norte | AE5: 307 Norte | AM5: 307 Norte | AN5: =D5+K5+R5+Y5+AF5 -> 0 | AO5: =E5+L5+S5+Z5+AG5 -> 0 | AP5: =F5+M5+T5+AA5+AH5 -> 0 | AQ5: =H5+O5+V5+AC5+AJ5 -> 0
C6: 313 Norte | J6: 313 Norte | Q6: 313 Norte | X6: 313 Norte | AE6: 313 Norte | AM6: 313 Norte | AN6: =D6+K6+R6+Y6+AF6 -> 0 | AO6: =E6+L6+S6+Z6+AG6 -> 0 | AP6: =F6+M6+T6+AA6+AH6 -> 0 | AQ6: =H6+O6+V6+AC6+AJ6 -> 0
C7: 314 Sul | J7: 314 Sul | Q7: 314 Sul | X7: 314 Sul | AE7: 314 Sul | AM7: 314 Sul | AN7: =D7+K7+R7+Y7+AF7 -> 0 | AO7: =E7+L7+S7+Z7+AG7 -> 0 | AP7: =F7+M7+T7+AA7+AH7 -> 0 | AQ7: =H7+O7+V7+AC7+AJ7 -> 0
C8: Sudoeste | J8: Sudoeste | Q8: Sudoeste | X8: Sudoeste | AE8: Sudoeste | AM8: Sudoeste | AN8: =D8+K8+R8+Y8+AF8 -> 0 | AO8: =E8+L8+S8+Z8+AG8 -> 0 | AP8: =F8+M8+T8+AA8+AH8 -> 0 | AQ8: =H8+O8+V8+AC8+AJ8 -> 0
C9: Noroeste | J9: Noroeste | Q9: Noroeste | X9: Noroeste | AE9: Noroeste | AM9: Noroeste | AN9: =D9+K9+R9+Y9+AF9 -> 0 | AO9: =E9+L9+S9+Z9+AG9 -> 0 | AP9: =F9+M9+T9+AA9+AH9 -> 0 | AQ9: =H9+O9+V9+AC9+AJ9 -> 0
C10: Total: | D10: =D2+D3+D4+D5+D6+D7+D8+D9 -> 0 | E10: =E2+E3+E4+E5+E6+E7+E8+E9 -> 0 | F10: =F2+F3+F4+F5+F6+F7+F8+F9 -> 0 | G10: =G2+G3+G4+G5+G6+G7+G8+G9 -> 0 | H10: =H2+H3+H4+H5+H6+H7+H8+H9 -> 0 | J10: Total: | K10: =K2+K3+K4+K5+K6+K7+K8+K9 -> 0 | L10: =L2+L3+L4+L5+L6+L7+L8+L9 -> 0 | M10: =M2+M3+M4+M5+M6+M7+M8+M9 -> 0 | N10: =N2+N3+N4+N5+N6+N7+N8+N9 -> 0 | O10: =O2+O3+O4+O5+O6+O7+O8+O9 -> 0 | Q10: Total: | R10: =R2+R3+R4+R5+R6+R7+R8+R9 -> 0 | S10: =S2+S3+S4+S5+S6+S7+S8+S9 -> 0 | T10: =T2+T3+T4+T5+T6+T7+T8+T9 -> 0 | U10: =U2+U3+U4+U5+U6+U7+U8+U9 -> 0 | V10: =V2+V3+V4+V5+V6+V7+V8+V9 -> 0 | X10: Total: | Y10: =Y2+Y3+Y4+Y5+Y6+Y7+Y8+Y9 -> 0 | Z10: =Z2+Z3+Z4+Z5+Z6+Z7+Z8+Z9 -> 0 | AA10: =AA2+AA3+AA4+AA5+AA6+AA7+AA8+AA9 -> 0 | AB10: =AB2+AB3+AB4+AB5+AB6+AB7+AB8+AB9 -> 0 | AC10: =AC2+AC3+AC4+AC5+AC6+AC7+AC8+AC9 -> 0 | AE10: Total: | AF10: =AF2+AF3+AF4+AF5+AF6+AF7+AF8+AF9 -> 0 | AG10: =AG2+AG3+AG4+AG5+AG6+AG7+AG8+AG9 -> 0 | AH10: =AH2+AH3+AH4+AH5+AH6+AH7+AH8+AH9 -> 0 | AI10: =AI2+AI3+AI4+AI5+AI6+AI7+AI8+AI9 -> 0 | AJ10: =AJ2+AJ3+AJ4+AJ5+AJ6+AJ7+AJ8+AJ9 -> 0 | AM10: Total: | AN10: =AN2+AN3+AN4+AN5+AN6+AN7+AN8+AN9 -> 0 | AO10: =AO2+AO3+AO4+AO5+AO6+AO7+AO8+AO9 -> 0 | AP10: =AP2+AP3+AP4+AP5+AP6+AP7+AP8+AP9 -> 0 | AQ10: =AQ2+AQ3+AQ4+AQ5+AQ6+AQ7+AQ8+AQ9 -> 0
C11: Faturado dia real | D11: =D10-E10 -> 0 | J11: Faturado dia real | K11: =K10-L10 -> 0 | Q11: Faturado dia real | R11: =R10-S10 -> 0 | X11: Faturado dia real | Y11: =Y10-Z10 -> 0 | AE11: Faturado dia real | AF11: =AF10-AG10 -> 0 | AM11: Fat. Real | AN11: =AN10-AO10 -> 0
C12: Recebido dia real | D12: =F10-E10 -> 0 | J12: Recebido dia real | K12: =M10-L10 -> 0 | Q12: Recebido dia real | R12: =T10-S10 -> 0 | X12: Recebido dia real | Y12: =AA10-Z10 -> 0 | AE12: Recebido dia real | AF12: =AH10-AG10 -> 0
B13: Dia | C13: Lojas | D13: Faturamento dia | E13: Não pago dia | F13: Recebido dia | G13: Não pago Acumulado | H13: Peças | I13: Dia | J13: Lojas | K13: Faturamento | L13: Não pago dia | M13: Recebido dia | N13: Não pago Acumulado | O13: Peças | P13: Dia | Q13: Lojas | R13: Faturamento | S13: Não pago dia | T13: Recebido dia | U13: Não pago Acumulado | V13: Peças | W13: Dia | X13: Lojas | Y13: Faturamento | Z13: Não pago dia | AA13: Recebido dia | AB13: Não pago Acumulado | AC13: Peças | AD13: Dia | AE13: Lojas | AF13: Faturamento | AG13: Não pago dia | AH13: Recebido dia | AI13: Não pago Acumulado | AJ13: Peças | AM13: Lojas | AN13: Faturamento | AO13: Não pago dia | AP13: Recebido | AQ13: Peças
A14: Terça-feira | C14: Lago Norte | I14: 04/03/2025 - Carnaval | J14: Lago Norte | P14: 45727 | Q14: Lago Norte | W14: 45734 | X14: Lago Norte | AD14: 45741 | AE14: Lago Norte | AL14: Faturamento Total das Terças-feiras | AM14: Lago Norte | AN14: =D14+K14+R14+Y14+AF14 -> 0 | AO14: =E14+L14+S14+Z14+AG14 -> 0 | AP14: =F14+M14+T14+AA14+AH14 -> 0 | AQ14: =H14+O14+V14+AC14+AJ14 -> 0
C15: 202 Norte | J15: 202 Norte | Q15: 202 Norte | X15: 202 Norte | AE15: 202 Norte | AM15: 202 Norte | AN15: =D15+K15+R15+Y15+AF15 -> 0 | AO15: =E15+L15+S15+Z15+AG15 -> 0 | AP15: =F15+M15+T15+AA15+AH15 -> 0 | AQ15: =H15+O15+V15+AC15+AJ15 -> 0
C16: 213 Norte | J16: 213 Norte | Q16: 213 Norte | X16: 213 Norte | AE16: 213 Norte | AM16: 213 Norte | AN16: =D16+K16+R16+Y16+AF16 -> 0 | AO16: =E16+L16+S16+Z16+AG16 -> 0 | AP16: =F16+M16+T16+AA16+AH16 -> 0 | AQ16: =H16+O16+V16+AC16+AJ16 -> 0
C17: 307 Norte | J17: 307 Norte | Q17: 307 Norte | X17: 307 Norte | AE17: 307 Norte | AM17: 307 Norte | AN17: =D17+K17+R17+Y17+AF17 -> 0 | AO17: =E17+L17+S17+Z17+AG17 -> 0 | AP17: =F17+M17+T17+AA17+AH17 -> 0 | AQ17: =H17+O17+V17+AC17+AJ17 -> 0
C18: 313 Norte | J18: 313 Norte | Q18: 313 Norte | X18: 313 Norte | AE18: 313 Norte | AM18: 313 Norte | AN18: =D18+K18+R18+Y18+AF18 -> 0 | AO18: =E18+L18+S18+Z18+AG18 -> 0 | AP18: =F18+M18+T18+AA18+AH18 -> 0 | AQ18: =H18+O18+V18+AC18+AJ18 -> 0
C19: 314 Sul | J19: 314 Sul | Q19: 314 Sul | X19: 314 Sul | AE19: 314 Sul | AM19: 314 Sul | AN19: =D19+K19+R19+Y19+AF19 -> 0 | AO19: =E19+L19+S19+Z19+AG19 -> 0 | AP19: =F19+M19+T19+AA19+AH19 -> 0 | AQ19: =H19+O19+V19+AC19+AJ19 -> 0
C20: Sudoeste | J20: Sudoeste | Q20: Sudoeste | X20: Sudoeste | AE20: Sudoeste | AM20: Sudoeste | AN20: =D20+K20+R20+Y20+AF20 -> 0 | AO20: =E20+L20+S20+Z20+AG20 -> 0 | AP20: =F20+M20+T20+AA20+AH20 -> 0 | AQ20: =H20+O20+V20+AC20+AJ20 -> 0
C21: Noroeste | J21: Noroeste | Q21: Noroeste | X21: Noroeste | AE21: Noroeste | AM21: Noroeste | AN21: =D21+K21+R21+Y21+AF21 -> 0 | AO21: =E21+L21+S21+Z21+AG21 -> 0 | AP21: =F21+M21+T21+AA21+AH21 -> 0 | AQ21: =H21+O21+V21+AC21+AJ21 -> 0
C22: Total: | D22: =D14+D15+D16+D17+D18+D19+D20+D21 -> 0 | E22: =E14+E15+E16+E17+E18+E19+E20+E21 -> 0 | F22: =F14+F15+F16+F17+F18+F19+F20+F21 -> 0 | G22: =G14+G15+G16+G17+G18+G19+G20+G21 -> 0 | H22: =H14+H15+H16+H17+H18+H19+H20+H21 -> 0 | J22: Total: | K22: =K14+K15+K16+K17+K18+K19+K20+K21 -> 0 | L22: =L14+L15+L16+L17+L18+L19+L20+L21 -> 0 | M22: =M14+M15+M16+M17+M18+M19+M20+M21 -> 0 | N22: =N14+N15+N16+N17+N18+N19+N20+N21 -> 0 | O22: =O14+O15+O16+O17+O18+O19+O20+O21 -> 0 | Q22: Total: | R22: =R14+R15+R16+R17+R18+R19+R20+R21 -> 0 | S22: =S14+S15+S16+S17+S18+S19+S20+S21 -> 0 | T22: =T14+T15+T16+T17+T18+T19+T20+T21 -> 0 | U22: =U14+U15+U16+U17+U18+U19+U20+U21 -> 0 | V22: =V14+V15+V16+V17+V18+V19+V20+V21 -> 0 | X22: Total: | Y22: =Y14+Y15+Y16+Y17+Y18+Y19+Y20+Y21 -> 0 | Z22: =Z14+Z15+Z16+Z17+Z18+Z19+Z20+Z21 -> 0 | AA22: =AA14+AA15+AA16+AA17+AA18+AA19+AA20+AA21 -> 0 | AB22: =AB14+AB15+AB16+AB17+AB18+AB19+AB20+AB21 -> 0 | AC22: =AC14+AC15+AC16+AC17+AC18+AC19+AC20+AC21 -> 0 | AE22: Total: | AF22: =AF14+AF15+AF16+AF17+AF18+AF19+AF20+AF21 -> 0 | AG22: =AG14+AG15+AG16+AG17+AG18+AG19+AG20+AG21 -> 0 | AH22: =AH14+AH15+AH16+AH17+AH18+AH19+AH20+AH21 -> 0 | AI22: =AI14+AI15+AI16+AI17+AI18+AI19+AI20+AI21 -> 0 | AJ22: =AJ14+AJ15+AJ16+AJ17+AJ18+AJ19+AJ20+AJ21 -> 0 | AM22: Total: | AN22: =AN14+AN15+AN16+AN17+AN18+AN19+AN20+AN21 -> 0 | AO22: =AO14+AO15+AO16+AO17+AO18+AO19+AO20+AO21 -> 0 | AP22: =AP14+AP15+AP16+AP17+AP18+AP19+AP20+AP21 -> 0 | AQ22: =AQ14+AQ15+AQ16+AQ17+AQ18+AQ19+AQ20+AQ21 -> 0
C23: Faturado dia real | D23: =D22-E22 -> 0 | J23: Faturado dia real | K23: =K22-L22 -> 0 | Q23: Faturado dia real | R23: =R22-S22 -> 0 | X23: Faturado dia real | Y23: =Y22-Z22 -> 0 | AE23: Faturado dia real | AF23: =AF22-AG22 -> 0 | AM23: Fat. Real | AN23: =AN22-AO22 -> 0
C24: Recebido dia real | D24: =F22-E22 -> 0 | J24: Recebido dia real | K24: =M22-L22 -> 0 | Q24: Recebido dia real | R24: =T22-S22 -> 0 | X24: Recebido dia real | Y24: =AA22-Z22 -> 0 | AE24: Recebido dia real | AF24: =AH22-AG22 -> 0
B25: Dia | C25: Lojas | D25: Faturamento dia | E25: Não pago dia | F25: Recebido dia | G25: Não pago Acumulado | H25: Peças | I25: Dia | J25: Lojas | K25: Faturamento | L25: Não pago dia | M25: Recebido dia | N25: Não pago Acumulado | O25: Peças | P25: Dia | Q25: Lojas | R25: Faturamento | S25: Não pago dia | T25: Recebido dia | U25: Não pago Acumulado | V25: Peças | W25: Dia | X25: Lojas | Y25: Faturamento | Z25: Não pago dia | AA25: Recebido dia | AB25: Não pago Acumulado | AC25: Peças | AD25: Dia | AE25: Lojas | AF25: Faturamento | AG25: Não pago dia | AH25: Recebido dia | AI25: Não pago Acumulado | AJ25: Peças | AM25: Lojas | AN25: Faturamento | AO25: Não pago dia | AP25: Recebido | AQ25: Peças
A26: Quarta-feira | C26: Lago Norte | I26: 45721 | J26: Lago Norte | P26: 45728 | Q26: Lago Norte | W26: 45735 | X26: Lago Norte | AD26: 45742 | AE26: Lago Norte | AL26: Faturamento Total das Quartas-feiras | AM26: Lago Norte | AN26: =D26+K26+R26+Y26+AF26 -> 0 | AO26: =E26+L26+S26+Z26+AG26 -> 0 | AP26: =F26+M26+T26+AA26+AH26 -> 0 | AQ26: =H26+O26+V26+AC26+AJ26 -> 0
C27: 202 Norte | J27: 202 Norte | Q27: 202 Norte | X27: 202 Norte | AE27: 202 Norte | AM27: 202 Norte | AN27: =D27+K27+R27+Y27+AF27 -> 0 | AO27: =E27+L27+S27+Z27+AG27 -> 0 | AP27: =F27+M27+T27+AA27+AH27 -> 0 | AQ27: =H27+O27+V27+AC27+AJ27 -> 0
C28: 213 Norte | J28: 213 Norte | Q28: 213 Norte | X28: 213 Norte | AE28: 213 Norte | AM28: 213 Norte | AN28: =D28+K28+R28+Y28+AF28 -> 0 | AO28: =E28+L28+S28+Z28+AG28 -> 0 | AP28: =F28+M28+T28+AA28+AH28 -> 0 | AQ28: =H28+O28+V28+AC28+AJ28 -> 0
C29: 307 Norte | J29: 307 Norte | Q29: 307 Norte | X29: 307 Norte | AE29: 307 Norte | AM29: 307 Norte | AN29: =D29+K29+R29+Y29+AF29 -> 0 | AO29: =E29+L29+S29+Z29+AG29 -> 0 | AP29: =F29+M29+T29+AA29+AH29 -> 0 | AQ29: =H29+O29+V29+AC29+AJ29 -> 0
C30: 313 Norte | J30: 313 Norte | Q30: 313 Norte | X30: 313 Norte | AE30: 313 Norte | AM30: 313 Norte | AN30: =D30+K30+R30+Y30+AF30 -> 0 | AO30: =E30+L30+S30+Z30+AG30 -> 0 | AP30: =F30+M30+T30+AA30+AH30 -> 0 | AQ30: =H30+O30+V30+AC30+AJ30 -> 0
C31: 314 Sul | J31: 314 Sul | Q31: 314 Sul | X31: 314 Sul | AE31: 314 Sul | AM31: 314 Sul | AN31: =D31+K31+R31+Y31+AF31 -> 0 | AO31: =E31+L31+S31+Z31+AG31 -> 0 | AP31: =F31+M31+T31+AA31+AH31 -> 0 | AQ31: =H31+O31+V31+AC31+AJ31 -> 0
C32: Sudoeste | J32: Sudoeste | Q32: Sudoeste | X32: Sudoeste | AE32: Sudoeste | AM32: Sudoeste | AN32: =D32+K32+R32+Y32+AF32 -> 0 | AO32: =E32+L32+S32+Z32+AG32 -> 0 | AP32: =F32+M32+T32+AA32+AH32 -> 0 | AQ32: =H32+O32+V32+AC32+AJ32 -> 0
C33: Noroeste | J33: Noroeste | Q33: Noroeste | X33: Noroeste | AE33: Noroeste | AM33: Noroeste | AN33: =D33+K33+R33+Y33+AF33 -> 0 | AO33: =E33+L33+S33+Z33+AG33 -> 0 | AP33: =F33+M33+T33+AA33+AH33 -> 0 | AQ33: =H33+O33+V33+AC33+AJ33 -> 0
C34: Total: | D34: =D26+D27+D28+D29+D30+D31+D32+D33 -> 0 | E34: =E26+E27+E28+E29+E30+E31+E32+E33 -> 0 | F34: =F26+F27+F28+F29+F30+F31+F32+F33 -> 0 | G34: =G26+G27+G28+G29+G30+G31+G32+G33 -> 0 | H34: =H26+H27+H28+H29+H30+H31+H32+H33 -> 0 | J34: Total: | Q34: Total: | R34: =R26+R27+R28+R29+R30+R31+R32+R33 -> 0 | S34: =S26+S27+S28+S29+S30+S31+S32+S33 -> 0 | T34: =T26+T27+T28+T29+T30+T31+T32+T33 -> 0 | U34: =U26+U27+U28+U29+U30+U31+U32+U33 -> 0 | V34: =V26+V27+V28+V29+V30+V31+V32+V33 -> 0 | X34: Total: | Y34: =Y26+Y27+Y28+Y29+Y30+Y31+Y32+Y33 -> 0 | Z34: =Z26+Z27+Z28+Z29+Z30+Z31+Z32+Z33 -> 0 | AA34: =AA26+AA27+AA28+AA29+AA30+AA31+AA32+AA33 -> 0 | AB34: =AB26+AB27+AB28+AB29+AB30+AB31+AB32+AB33 -> 0 | AC34: =AC26+AC27+AC28+AC29+AC30+AC31+AC32+AC33 -> 0 | AE34: Total: | AF34: =AF26+AF27+AF28+AF29+AF30+AF31+AF32+AF33 -> 0 | AG34: =AG26+AG27+AG28+AG29+AG30+AG31+AG32+AG33 -> 0 | AH34: =AH26+AH27+AH28+AH29+AH30+AH31+AH32+AH33 -> 0 | AI34: =AI26+AI27+AI28+AI29+AI30+AI31+AI32+AI33 -> 0 | AJ34: =AJ26+AJ27+AJ28+AJ29+AJ30+AJ31+AJ32+AJ33 -> 0 | AM34: Total: | AN34: =AN26+AN27+AN28+AN29+AN30+AN31+AN32+AN33 -> 0 | AO34: =AO26+AO27+AO28+AO29+AO30+AO31+AO32+AO33 -> 0 | AP34: =AP26+AP27+AP28+AP29+AP30+AP31+AP32+AP33 -> 0 | AQ34: =AQ26+AQ27+AQ28+AQ29+AQ30+AQ31+AQ32+AQ33 -> 0
C35: Faturado dia real | D35: =D34-E34 -> 0 | J35: Faturado dia real | K35: =K34-L34 -> 0 | Q35: Faturado dia real | R35: =R34-S34 -> 0 | X35: Faturado dia real | Y35: =Y34-Z34 -> 0 | AE35: Faturado dia real | AF35: =AF34-AG34 -> 0 | AM35: Fat. Real | AN35: =AN34-AO34 -> 0
C36: Recebido dia real | D36: =F34-E34 -> 0 | J36: Recebido dia real | K36: =M34-L34 -> 0 | Q36: Recebido dia real | R36: =T34-S34 -> 0 | X36: Recebido dia real | Y36: =AA34-Z34 -> 0 | AE36: Recebido dia real | AF36: =AH34-AG34 -> 0
B37: Dia | C37: Lojas | D37: Faturamento dia | E37: Não pago dia | F37: Recebido dia | G37: Não pago Acumulado | H37: Peças | I37: Dia | J37: Lojas | K37: Faturamento | L37: Não pago dia | M37: Recebido dia | N37: Não pago Acumulado | O37: Peças | P37: Dia | Q37: Lojas | R37: Faturamento | S37: Não pago dia | T37: Recebido dia | U37: Não pago Acumulado | V37: Peças | W37: Dia | X37: Lojas | Y37: Faturamento | Z37: Não pago dia | AA37: Recebido dia | AB37: Não pago Acumulado | AC37: Peças | AD37: Dia | AE37: Lojas | AF37: Faturamento | AG37: Não pago dia | AH37: Recebido dia | AI37: Não pago Acumulado | AJ37: Peças | AM37: Lojas | AN37: Faturamento | AO37: Não pago dia | AP37: Recebido | AQ37: Peças
A38: Quinta-feira | C38: Lago Norte | I38: 45722 | J38: Lago Norte | P38: 45729 | Q38: Lago Norte | W38: 45736 | X38: Lago Norte | AD38: 45743 | AE38: Lago Norte | AL38: Faturamento Total das Quintas-feiras | AM38: Lago Norte | AN38: =D38+K38+R38+Y38+AF38 -> 0 | AO38: =E38+L38+S38+Z38+AG38 -> 0 | AP38: =F38+M38+T38+AA38+AH38 -> 0 | AQ38: =H38+O38+V38+AC38+AJ38 -> 0
C39: 202 Norte | J39: 202 Norte | Q39: 202 Norte | X39: 202 Norte | AE39: 202 Norte | AM39: 202 Norte | AN39: =D39+K39+R39+Y39+AF39 -> 0 | AO39: =E39+L39+S39+Z39+AG39 -> 0 | AP39: =F39+M39+T39+AA39+AH39 -> 0 | AQ39: =H39+O39+V39+AC39+AJ39 -> 0
C40: 213 Norte | J40: 213 Norte | Q40: 213 Norte | X40: 213 Norte | AE40: 213 Norte | AM40: 213 Norte | AN40: =D40+K40+R40+Y40+AF40 -> 0 | AO40: =E40+L40+S40+Z40+AG40 -> 0 | AP40: =F40+M40+T40+AA40+AH40 -> 0 | AQ40: =H40+O40+V40+AC40+AJ40 -> 0
C41: 307 Norte | J41: 307 Norte | Q41: 307 Norte | X41: 307 Norte | AE41: 307 Norte | AM41: 307 Norte | AN41: =D41+K41+R41+Y41+AF41 -> 0 | AO41: =E41+L41+S41+Z41+AG41 -> 0 | AP41: =F41+M41+T41+AA41+AH41 -> 0 | AQ41: =H41+O41+V41+AC41+AJ41 -> 0
C42: 313 Norte | J42: 313 Norte | Q42: 313 Norte | X42: 313 Norte | AE42: 313 Norte | AM42: 313 Norte | AN42: =D42+K42+R42+Y42+AF42 -> 0 | AO42: =E42+L42+S42+Z42+AG42 -> 0 | AP42: =F42+M42+T42+AA42+AH42 -> 0 | AQ42: =H42+O42+V42+AC42+AJ42 -> 0
C43: 314 Sul | J43: 314 Sul | Q43: 314 Sul | X43: 314 Sul | AE43: 314 Sul | AM43: 314 Sul | AN43: =D43+K43+R43+Y43+AF43 -> 0 | AO43: =E43+L43+S43+Z43+AG43 -> 0 | AP43: =F43+M43+T43+AA43+AH43 -> 0 | AQ43: =H43+O43+V43+AC43+AJ43 -> 0
C44: Sudoeste | J44: Sudoeste | Q44: Sudoeste | X44: Sudoeste | AE44: Sudoeste | AM44: Sudoeste | AN44: =D44+K44+R44+Y44+AF44 -> 0 | AO44: =E44+L44+S44+Z44+AG44 -> 0 | AP44: =F44+M44+T44+AA44+AH44 -> 0 | AQ44: =H44+O44+V44+AC44+AJ44 -> 0
C45: Noroeste | J45: Noroeste | Q45: Noroeste | X45: Noroeste | AE45: Noroeste | AM45: Noroeste | AN45: =D45+K45+R45+Y45+AF45 -> 0 | AO45: =E45+L45+S45+Z45+AG45 -> 0 | AP45: =F45+M45+T45+AA45+AH45 -> 0 | AQ45: =H45+O45+V45+AC45+AJ45 -> 0
C46: Total: | D46: =D38+D39+D40+D41+D42+D43+D44+D45 -> 0 | E46: =E38+E39+E40+E41+E42+E43+E44+E45 -> 0 | F46: =F38+F39+F40+F41+F42+F43+F44+F45 -> 0 | G46: =G38+G39+G40+G41+G42+G43+G44+G45 -> 0 | H46: =H38+H39+H40+H41+H42+H43+H44+H45 -> 0 | J46: Total: | K46: =K38+K39+K40+K41+K42+K43+K44+K45 -> 0 | L46: =L38+L39+L40+L41+L42+L43+L44+L45 -> 0 | M46: =M38+M39+M40+M41+M42+M43+M44+M45 -> 0 | N46: =N38+N39+N40+N41+N42+N43+N44+N45 -> 0 | O46: =O38+O39+O40+O41+O42+O43+O44+O45 -> 0 | Q46: Total: | R46: =R38+R39+R40+R41+R42+R43+R44+R45 -> 0 | S46: =S38+S39+S40+S41+S42+S43+S44+S45 -> 0 | T46: =T38+T39+T40+T41+T42+T43+T44+T45 -> 0 | U46: =U38+U39+U40+U41+U42+U43+U44+U45 -> 0 | V46: =V38+V39+V40+V41+V42+V43+V44+V45 -> 0 | X46: Total: | Y46: =Y38+Y39+Y40+Y41+Y42+Y43+Y44+Y45 -> 0 | Z46: =Z38+Z39+Z40+Z41+Z42+Z43+Z44+Z45 -> 0 | AA46: =AA38+AA39+AA40+AA41+AA42+AA43+AA44+AA45 -> 0 | AB46: =AB38+AB39+AB40+AB41+AB42+AB43+AB44+AB45 -> 0 | AC46: =AC38+AC39+AC40+AC41+AC42+AC43+AC44+AC45 -> 0 | AE46: Total: | AF46: =AF38+AF39+AF40+AF41+AF42+AF43+AF44+AF45 -> 0 | AG46: =AG38+AG39+AG40+AG41+AG42+AG43+AG44+AG45 -> 0 | AH46: =AH38+AH39+AH40+AH41+AH42+AH43+AH44+AH45 -> 0 | AI46: =AI38+AI39+AI40+AI41+AI42+AI43+AI44+AI45 -> 0 | AJ46: =AJ38+AJ39+AJ40+AJ41+AJ42+AJ43+AJ44+AJ45 -> 0 | AM46: Total: | AN46: =AN38+AN39+AN40+AN41+AN42+AN43+AN44+AN45 -> 0 | AO46: =AO38+AO39+AO40+AO41+AO42+AO43+AO44+AO45 -> 0 | AP46: =AP38+AP39+AP40+AP41+AP42+AP43+AP44+AP45 -> 0 | AQ46: =AQ38+AQ39+AQ40+AQ41+AQ42+AQ43+AQ44+AQ45 -> 0
C47: Faturado dia real | D47: =D46-E46 -> 0 | J47: Faturado dia real | K47: =K46-L46 -> 0 | Q47: Faturado dia real | R47: =R46-S46 -> 0 | X47: Faturado dia real | Y47: =Y46-Z46 -> 0 | AE47: Faturado dia real | AF47: =AF46-AG46 -> 0 | AM47: Fat. Real | AN47: =AN46-AO46 -> 0
C48: Recebido dia real | D48: =F46-E46 -> 0 | J48: Recebido dia real | K48: =M46-L46 -> 0 | Q48: Recebido dia real | R48: =T46-S46 -> 0 | X48: Recebido dia real | Y48: =AA46-Z46 -> 0 | AE48: Recebido dia real | AF48: =AH46-AG46 -> 0
B49: Dia | C49: Lojas | D49: Faturamento dia | E49: Não pago dia | F49: Recebido dia | G49: Não pago Acumulado | H49: Peças | I49: Dia | J49: Lojas | K49: Faturamento | L49: Não pago dia | M49: Recebido dia | N49: Não pago Acumulado | O49: Peças | P49: Dia | Q49: Lojas | R49: Faturamento | S49: Não pago dia | T49: Recebido dia | U49: Não pago Acumulado | V49: Peças | W49: Dia | X49: Lojas | Y49: Faturamento | Z49: Não pago dia | AA49: Recebido dia | AB49: Não pago Acumulado | AC49: Peças | AD49: Dia | AE49: Lojas | AF49: Faturamento | AG49: Não pago dia | AH49: Recebido dia | AI49: Não pago Acumulado | AJ49: Peças | AM49: Lojas | AN49: Faturamento | AO49: Não pago dia | AP49: Recebido | AQ49: Peças
A50: Sexta-feira | C50: Lago Norte | I50: 45723 | J50: Lago Norte | P50: 45730 | Q50: Lago Norte | W50: 45737 | X50: Lago Norte | AD50: 45744 | AE50: Lago Norte | AL50: Faturamento Total das Sextas-feiras | AM50: Lago Norte | AN50: =D50+K50+R50+Y50+AF50 -> 0 | AO50: =E50+L50+S50+Z50+AG50 -> 0 | AP50: =F50+M50+T50+AA50+AH50 -> 0 | AQ50: =H50+O50+V50+AC50+AJ50 -> 0
C51: 202 Norte | J51: 202 Norte | Q51: 202 Norte | X51: 202 Norte | AE51: 202 Norte | AM51: 202 Norte | AN51: =D51+K51+R51+Y51+AF51 -> 0 | AO51: =E51+L51+S51+Z51+AG51 -> 0 | AP51: =F51+M51+T51+AA51+AH51 -> 0 | AQ51: =H51+O51+V51+AC51+AJ51 -> 0
C52: 213 Norte | J52: 213 Norte | Q52: 213 Norte | X52: 213 Norte | AE52: 213 Norte | AM52: 213 Norte | AN52: =D52+K52+R52+Y52+AF52 -> 0 | AO52: =E52+L52+S52+Z52+AG52 -> 0 | AP52: =F52+M52+T52+AA52+AH52 -> 0 | AQ52: =H52+O52+V52+AC52+AJ52 -> 0
C53: 307 Norte | J53: 307 Norte | Q53: 307 Norte | X53: 307 Norte | AE53: 307 Norte | AM53: 307 Norte | AN53: =D53+K53+R53+Y53+AF53 -> 0 | AO53: =E53+L53+S53+Z53+AG53 -> 0 | AP53: =F53+M53+T53+AA53+AH53 -> 0 | AQ53: =H53+O53+V53+AC53+AJ53 -> 0
C54: 313 Norte | J54: 313 Norte | Q54: 313 Norte | X54: 313 Norte | AE54: 313 Norte | AM54: 313 Norte | AN54: =D54+K54+R54+Y54+AF54 -> 0 | AO54: =E54+L54+S54+Z54+AG54 -> 0 | AP54: =F54+M54+T54+AA54+AH54 -> 0 | AQ54: =H54+O54+V54+AC54+AJ54 -> 0
C55: 314 Sul | J55: 314 Sul | Q55: 314 Sul | X55: 314 Sul | AE55: 314 Sul | AM55: 314 Sul | AN55: =D55+K55+R55+Y55+AF55 -> 0 | AO55: =E55+L55+S55+Z55+AG55 -> 0 | AP55: =F55+M55+T55+AA55+AH55 -> 0 | AQ55: =H55+O55+V55+AC55+AJ55 -> 0
C56: Sudoeste | J56: Sudoeste | Q56: Sudoeste | X56: Sudoeste | AE56: Sudoeste | AM56: Sudoeste | AN56: =D56+K56+R56+Y56+AF56 -> 0 | AO56: =E56+L56+S56+Z56+AG56 -> 0 | AP56: =F56+M56+T56+AA56+AH56 -> 0 | AQ56: =H56+O56+V56+AC56+AJ56 -> 0
C57: Noroeste | J57: Noroeste | Q57: Noroeste | X57: Noroeste | AE57: Noroeste | AM57: Noroeste | AN57: =D57+K57+R57+Y57+AF57 -> 0 | AO57: =E57+L57+S57+Z57+AG57 -> 0 | AP57: =F57+M57+T57+AA57+AH57 -> 0 | AQ57: =H57+O57+V57+AC57+AJ57 -> 0
C58: Total: | D58: =D50+D51+D52+D53+D54+D55+D56+D57 -> 0 | E58: =E50+E51+E52+E53+E54+E55+E56+E57 -> 0 | F58: =F50+F51+F52+F53+F54+F55+F56+F57 -> 0 | G58: =G50+G51+G52+G53+G54+G55+G56+G57 -> 0 | H58: =H50+H51+H52+H53+H54+H55+H56+H57 -> 0 | J58: Total: | K58: =K50+K51+K52+K53+K54+K55+K56+K57 -> 0 | L58: =L50+L51+L52+L53+L54+L55+L56+L57 -> 0 | M58: =M50+M51+M52+M53+M54+M55+M56+M57 -> 0 | N58: =N50+N51+N52+N53+N54+N55+N56+N57 -> 0 | O58: =O50+O51+O52+O53+O54+O55+O56+O57 -> 0 | Q58: Total: | R58: =R50+R51+R52+R53+R54+R55+R56+R57 -> 0 | S58: =S50+S51+S52+S53+S54+S55+S56+S57 -> 0 | T58: =T50+T51+T52+T53+T54+T55+T56+T57 -> 0 | U58: =U50+U51+U52+U53+U54+U55+U56+U57 -> 0 | V58: =V50+V51+V52+V53+V54+V55+V56+V57 -> 0 | X58: Total: | Y58: =Y50+Y51+Y52+Y53+Y54+Y55+Y56+Y57 -> 0 | Z58: =Z50+Z51+Z52+Z53+Z54+Z55+Z56+Z57 -> 0 | AA58: =AA50+AA51+AA52+AA53+AA54+AA55+AA56+AA57 -> 0 | AB58: =AB50+AB51+AB52+AB53+AB54+AB55+AB56+AB57 -> 0 | AC58: =AC50+AC51+AC52+AC53+AC54+AC55+AC56+AC57 -> 0 | AE58: Total: | AF58: =AF50+AF51+AF52+AF53+AF54+AF55+AF56+AF57 -> 0 | AG58: =AG50+AG51+AG52+AG53+AG54+AG55+AG56+AG57 -> 0 | AH58: =AH50+AH51+AH52+AH53+AH54+AH55+AH56+AH57 -> 0 | AI58: =AI50+AI51+AI52+AI53+AI54+AI55+AI56+AI57 -> 0 | AJ58: =AJ50+AJ51+AJ52+AJ53+AJ54+AJ55+AJ56+AJ57 -> 0 | AM58: Total: | AN58: =AN50+AN51+AN52+AN53+AN54+AN55+AN56+AN57 -> 0 | AO58: =AO50+AO51+AO52+AO53+AO54+AO55+AO56+AO57 -> 0 | AP58: =AP50+AP51+AP52+AP53+AP54+AP55+AP56+AP57 -> 0 | AQ58: =AQ50+AQ51+AQ52+AQ53+AQ54+AQ55+AQ56+AQ57 -> 0
C59: Faturado dia real | D59: =D58-E58 -> 0 | J59: Faturado dia real | K59: =K58-L58 -> 0 | Q59: Faturado dia real | R59: =R58-S58 -> 0 | X59: Faturado dia real | Y59: =Y58-Z58 -> 0 | AE59: Faturado dia real | AF59: =AF58-AG58 -> 0 | AM59: Fat. Real | AN59: =AN58-AO58 -> 0
C60: Recebido dia real | D60: =F58-E58 -> 0 | J60: Recebido dia real | K60: =M58-L58 -> 0 | Q60: Recebido dia real | R60: =T58-S58 -> 0 | X60: Recebido dia real | Y60: =AA58-Z58 -> 0 | AE60: Recebido dia real | AF60: =AH58-AG58 -> 0
B61: Dia | C61: Lojas | D61: Faturamento dia | E61: Não pago dia | F61: Recebido dia | G61: Não pago Acumulado | H61: Peças | I61: Dia | J61: Lojas | K61: Faturamento | L61: Não pago dia | M61: Recebido dia | N61: Não pago Acumulado | O61: Peças | P61: Dia | Q61: Lojas | R61: Faturamento | S61: Não pago dia | T61: Recebido dia | U61: Não pago Acumulado | V61: Peças | W61: Dia | X61: Lojas | Y61: Faturamento | Z61: Não pago dia | AA61: Recebido dia | AB61: Não pago Acumulado | AC61: Peças | AD61: Dia | AE61: Lojas | AF61: Faturamento | AG61: Não pago dia | AH61: Recebido dia | AI61: Não pago Acumulado | AJ61: Peças | AM61: Lojas | AN61: Faturamento | AO61: Não pago dia | AP61: Recebido | AQ61: Peças
A62: Sábado | B62: 45717 | C62: Lago Norte | I62: 45724 | J62: Lago Norte | P62: 45731 | Q62: Lago Norte | W62: 45738 | X62: Lago Norte | AD62: 45745 | AE62: Lago Norte | AL62: Faturamento Total dos Sábados | AM62: Lago Norte | AN62: =D62+K62+R62+Y62+AF62 -> 0 | AO62: =E62+L62+S62+Z62+AG62 -> 0 | AP62: =F62+M62+T62+AA62+AH62 -> 0 | AQ62: =H62+O62+V62+AC62+AJ62 -> 0
C63: 202 Norte | J63: 202 Norte | Q63: 202 Norte | X63: 202 Norte | AE63: 202 Norte | AM63: 202 Norte | AN63: =D63+K63+R63+Y63+AF63 -> 0 | AO63: =E63+L63+S63+Z63+AG63 -> 0 | AP63: =F63+M63+T63+AA63+AH63 -> 0 | AQ63: =H63+O63+V63+AC63+AJ63 -> 0
C64: 213 Norte | J64: 213 Norte | Q64: 213 Norte | X64: 213 Norte | AE64: 213 Norte | AM64: 213 Norte | AN64: =D64+K64+R64+Y64+AF64 -> 0 | AO64: =E64+L64+S64+Z64+AG64 -> 0 | AP64: =F64+M64+T64+AA64+AH64 -> 0 | AQ64: =H64+O64+V64+AC64+AJ64 -> 0
C65: 307 Norte | J65: 307 Norte | Q65: 307 Norte | X65: 307 Norte | AE65: 307 Norte | AM65: 307 Norte | AN65: =D65+K65+R65+Y65+AF65 -> 0 | AO65: =E65+L65+S65+Z65+AG65 -> 0 | AP65: =F65+M65+T65+AA65+AH65 -> 0 | AQ65: =H65+O65+V65+AC65+AJ65 -> 0
C66: 313 Norte | J66: 313 Norte | Q66: 313 Norte | X66: 313 Norte | AE66: 313 Norte | AM66: 313 Norte | AN66: =D66+K66+R66+Y66+AF66 -> 0 | AO66: =E66+L66+S66+Z66+AG66 -> 0 | AP66: =F66+M66+T66+AA66+AH66 -> 0 | AQ66: =H66+O66+V66+AC66+AJ66 -> 0
C67: 314 Sul | J67: 314 Sul | Q67: 314 Sul | X67: 314 Sul | AE67: 314 Sul | AM67: 314 Sul | AN67: =D67+K67+R67+Y67+AF67 -> 0 | AO67: =E67+L67+S67+Z67+AG67 -> 0 | AP67: =F67+M67+T67+AA67+AH67 -> 0 | AQ67: =H67+O67+V67+AC67+AJ67 -> 0
C68: Sudoeste | J68: Sudoeste | Q68: Sudoeste | X68: Sudoeste | AE68: Sudoeste | AM68: Sudoeste | AN68: =D68+K68+R68+Y68+AF68 -> 0 | AO68: =E68+L68+S68+Z68+AG68 -> 0 | AP68: =F68+M68+T68+AA68+AH68 -> 0 | AQ68: =H68+O68+V68+AC68+AJ68 -> 0
C69: Noroeste | J69: Noroeste | Q69: Noroeste | X69: Noroeste | AE69: Noroeste | AM69: Noroeste | AN69: =D69+K69+R69+Y69+AF69 -> 0 | AO69: =E69+L69+S69+Z69+AG69 -> 0 | AP69: =F69+M69+T69+AA69+AH69 -> 0 | AQ69: =H69+O69+V69+AC69+AJ69 -> 0
C70: Total: | D70: =D62+D63+D64+D65+D66+D67+D68+D69 -> 0 | E70: =E62+E63+E64+E65+E66+E67+E68+E69 -> 0 | F70: =F62+F63+F64+F65+F66+F67+F68+F69 -> 0 | G70: =G62+G63+G64+G65+G66+G67+G68+G69 -> 0 | H70: =H62+H63+H64+H65+H66+H67+H68+H69 -> 0 | J70: Total: | K70: =K62+K63+K64+K65+K66+K67+K68+K69 -> 0 | L70: =L62+L63+L64+L65+L66+L67+L68+L69 -> 0 | M70: =M62+M63+M64+M65+M66+M67+M68+M69 -> 0 | N70: =N62+N63+N64+N65+N66+N67+N68+N69 -> 0 | O70: =O62+O63+O64+O65+O66+O67+O68+O69 -> 0 | Q70: Total: | R70: =R62+R63+R64+R65+R66+R67+R68+R69 -> 0 | S70: =S62+S63+S64+S65+S66+S67+S68+S69 -> 0 | T70: =T62+T63+T64+T65+T66+T67+T68+T69 -> 0 | U70: =U62+U63+U64+U65+U66+U67+U68+U69 -> 0 | V70: =V62+V63+V64+V65+V66+V67+V68+V69 -> 0 | X70: Total: | Y70: =Y62+Y63+Y64+Y65+Y66+Y67+Y68+Y69 -> 0 | Z70: =Z62+Z63+Z64+Z65+Z66+Z67+Z68+Z69 -> 0 | AA70: =AA62+AA63+AA64+AA65+AA66+AA67+AA68+AA69 -> 0 | AB70: =AB62+AB63+AB64+AB65+AB66+AB67+AB68+AB69 -> 0 | AC70: =AC62+AC63+AC64+AC65+AC66+AC67+AC68+AC69 -> 0 | AE70: Total: | AF70: =AF62+AF63+AF64+AF65+AF66+AF67+AF68+AF69 -> 0 | AG70: =AG62+AG63+AG64+AG65+AG66+AG67+AG68+AG69 -> 0 | AH70: =AH62+AH63+AH64+AH65+AH66+AH67+AH68+AH69 -> 0 | AI70: =AI62+AI63+AI64+AI65+AI66+AI67+AI68+AI69 -> 0 | AJ70: =AJ62+AJ63+AJ64+AJ65+AJ66+AJ67+AJ68+AJ69 -> 0 | AM70: Total: | AN70: =AN62+AN63+AN64+AN65+AN66+AN67+AN68+AN69 -> 0 | AO70: =AO62+AO63+AO64+AO65+AO66+AO67+AO68+AO69 -> 0 | AP70: =AP62+AP63+AP64+AP65+AP66+AP67+AP68+AP69 -> 0 | AQ70: =AQ62+AQ63+AQ64+AQ65+AQ66+AQ67+AQ68+AQ69 -> 0
C71: Faturado dia real | D71: =D70-E70 -> 0 | J71: Faturado dia real | K71: =K70-L70 -> 0 | Q71: Faturado dia real | R71: =R70-S70 -> 0 | X71: Faturado dia real | Y71: =Y70-Z70 -> 0 | AE71: Faturado dia real | AF71: =AF70-AG70 -> 0 | AM71: Fat. Real | AN71: =AN70-AO70 -> 0
C72: Recebido dia real | D72: =F70-E70 -> 0 | J72: Recebido dia real | K72: =M70-L70 -> 0 | Q72: Recebido dia real | R72: =T70-S70 -> 0 | X72: Recebido dia real | Y72: =AA70-Z70 -> 0 | AE72: Recebido dia real | AF72: =AH70-AG70 -> 0
B73: Dia | C73: Lojas | D73: Faturamento | E73: Não pago dia | F73: Recebido dia | G73: Não pago Acumulado | H73: Peças | I73: Dia | J73: Lojas | K73: Faturamento | L73: Não pago dia | M73: Recebido dia | N73: Não pago Acumulado | O73: Peças | P73: Dia | Q73: Lojas | R73: Faturamento | S73: Não pago dia | T73: Recebido dia | U73: Não pago Acumulado | V73: Peças | W73: Dia | X73: Lojas | Y73: Faturamento | Z73: Não pago dia | AA73: Recebido dia | AB73: Não pago Acumulado | AC73: Peças | AD73: Dia | AE73: Lojas | AF73: Faturamento | AG73: Não pago dia | AH73: Recebido dia | AI73: Não pago Acumulado | AJ73: Peças | AM73: Lojas | AN73: Faturamento | AO73: Não pago dia | AP73: Recebido | AQ73: Peças
A74: Domingo | B74: 45718 | C74: Lago Norte | I74: 45725 | P74: 45732 | W74: 45739 | AD74: 45746 | AL74: Faturamento Total dos Domingos
C75: 202 Norte
C76: 213 Norte
C77: 307 Norte
C78: 313 Norte
C79: 314 Sul
C80: Sudoeste
C81: Noroeste | J81: Noroeste -Dani | Q81: Noroeste | X81: Noroeste | AE81: Noroeste | AM81: Noroeste | AN81: =D81+K81+R81+Y81+AF81 -> 0 | AO81: =E81+L81+S81+Z81+AG81 -> 0 | AP81: =F81+M81+T81+AA81+AH81 -> 0 | AQ81: =H81+O81+V81+AC81+AJ81 -> 0
C82: Total: | D82: =D74+D75+D76+D77+D78+D79+D80+D81 -> 0 | E82: =E74+E75+E76+E77+E78+E79+E80+E81 -> 0 | F82: =F74+F75+F76+F77+F78+F79+F80+F81 -> 0 | G82: =G74+G75+G76+G77+G78+G79+G80+G81 -> 0 | H82: =H74+H75+H76+H77+H78+H79+H80+H81 -> 0 | J82: Total: | K82: =K74+K75+K76+K77+K78+K79+K80+K81 -> 0 | L82: =L74+L75+L76+L77+L78+L79+L80+L81 -> 0 | M82: =M74+M75+M76+M77+M78+M79+M80+M81 -> 0 | N82: =N74+N75+N76+N77+N78+N79+N80+N81 -> 0 | O82: =O74+O75+O76+O77+O78+O79+O80+O81 -> 0 | Q82: Total: | R82: =R74+R75+R76+R77+R78+R79+R80+R81 -> 0 | S82: =S74+S75+S76+S77+S78+S79+S80+S81 -> 0 | T82: =T74+T75+T76+T77+T78+T79+T80+T81 -> 0 | U82: =U74+U75+U76+U77+U78+U79+U80+U81 -> 0 | V82: =V74+V75+V76+V77+V78+V79+V80+V81 -> 0 | X82: Total: | Y82: =Y74+Y75+Y76+Y77+Y78+Y79+Y80+Y81 -> 0 | Z82: =Z74+Z75+Z76+Z77+Z78+Z79+Z80+Z81 -> 0 | AA82: =AA74+AA75+AA76+AA77+AA78+AA79+AA80+AA81 -> 0 | AB82: =AB74+AB75+AB76+AB77+AB78+AB79+AB80+AB81 -> 0 | AC82: =AC74+AC75+AC76+AC77+AC78+AC79+AC80+AC81 -> 0 | AE82: Total: | AF82: =AF74+AF75+AF76+AF77+AF78+AF79+AF80+AF81 -> 0 | AG82: =AG74+AG75+AG76+AG77+AG78+AG79+AG80+AG81 -> 0 | AH82: =AH74+AH75+AH76+AH77+AH78+AH79+AH80+AH81 -> 0 | AI82: =AI74+AI75+AI76+AI77+AI78+AI79+AI80+AI81 -> 0 | AJ82: =AJ74+AJ75+AJ76+AJ77+AJ78+AJ79+AJ80+AJ81 -> 0 | AM82: Total: | AN82: =AN74+AN75+AN76+AN77+AN78+AN79+AN80+AN81 -> 0 | AO82: =AO74+AO75+AO76+AO77+AO78+AO79+AO80+AO81 -> 0 | AP82: =AP74+AP75+AP76+AP77+AP78+AP79+AP80+AP81 -> 0 | AQ82: =AQ74+AQ75+AQ76+AQ77+AQ78+AQ79+AQ80+AQ81 -> 0
C83: Faturado dia real | D83: =D82-E82 -> 0 | J83: Faturado dia real | K83: =K82-L82 -> 0 | Q83: Faturado dia real | R83: =R82-S82 -> 0 | X83: Faturado dia real | Y83: =Y82-Z82 -> 0 | AE83: Faturado dia real | AF83: =AF82-AG82 -> 0 | AM83: Fat. Real | AN83: =AN82-AO82 -> 0
C84: Recebido dia real | D84: =F82-E82 -> 0 | J84: Recebido dia real | K84: =M82-L82 -> 0 | Q84: Recebido dia real | R84: =T82-S82 -> 0 | X84: Recebido dia real | Y84: =AA82-Z82 -> 0 | AE84: Recebido dia real | AF84: =AH82-AG82 -> 0
C87: Faturamento 4° semana Janeiro | J87: Faturamento 4° semana Janeiro | Q87: Faturamento 4° semana Janeiro | X87: Faturamento 4° semana Janeiro | AE87: Faturamento 4 1/2° semana Janeiro
C88: Faturamento | D88: =D10+D22+D34+D46+D58+D70+D82 -> 0 | J88: Faturamento | K88: =K10+K22+K34+K46+K58+K70+K82 -> 0 | Q88: Faturamento | R88: =R10+R22+R34+R46+R58+R70+R82 -> 0 | X88: Faturamento | Y88: =Y10+Y22+Y34+Y46+Y58+Y70+Y82 -> 0 | AE88: Faturamento | AF88: =AF10+AF22+AF34+AF46+AF58+AF70+AF82 -> 0 | AN88: {=AN10+AN22+AN34+AN46+AN58+AN70} -> 0 | AP88: {=AP10+AP22+AP34+AP46+AP58+AP70} -> 0
C89: Não pago dia | D89: =E10+E22+E34+E46+E58+E70+E82 -> 0 | J89: Não pago dia | K89: =L10+L22+L34+L46+L58+L70+L82 -> 0 | Q89: Não pago dia | R89: =S10+S22+S34+S46+S58+S70+S82 -> 0 | X89: Não pago dia | Y89: =Z10+Z22+Z34+Z46+Z58+Z70+Z82 -> 0 | AE89: Não pago dia | AF89: =AG10+AG22+AG34+AG46+AG58+AG70+AG82 -> 0
C90: Recebido | D90: =F10+F22+F34+F46+F58+F70+F82 -> 0 | J90: Recebido | K90: =M10+M22+M34+M46+M58+M70+M82 -> 0 | Q90: Recebido | R90: =T10+T22+T34+T46+T58+T70+T82 -> 0 | X90: Recebido | Y90: =AA10+AA22+AA34+AA46+AA58+AA70+AA82 -> 0 | AE90: Recebido | AF90: =AH10+AH22+AH34+AH46+AH58+AH70+AH82 -> 0
C91: Fat. Real | D91: {=D11:E11+D23:E23+D35:E35+D47:E47+D59:E59+D71:E71+D83:F83} -> 0 | J91: Fat. Real | K91: {=K11:L11+K23:L23+K35:L35+K47:L47+K59:L59+K71:L71+K83:M83} -> 0 | Q91: Fat. Real | R91: {=R11:S11+R23:S23+R35:S35+R47:S47+R59:S59+R71:S71+R83:T83} -> 0 | X91: Fat. Real | Y91: {=Y11:Z11+Y23:Z23+Y35:Z35+Y47:Z47+Y59:Z59+Y71:Z71+Y83:AA83} -> 0 | AE91: Fat. Real | AF91: {=AF11:AG11+AF23:AG23+AF35:AG35+AF47:AG47+AF59:AG59+AF71:AG71+AF83:AH83} -> 0
C92: Recebido Real | D92: {=D12:F12+D24:F24+D36:F36+D48:F48+D60:F60+D72:F72+D84:F84} -> 0 | J92: Recebido Real | K92: {=K12:M12+K24:M24+K36:M36+K48:M48+K60:M60+K72:M72+K84:M84} -> 0 | Q92: Recebido Real | R92: {=R12:T12+R24:T24+R36:T36+R48:T48+R60:T60+R72:T72+R84:T84} -> 0 | X92: Recebido Real | Y92: {=Y12:AA12+Y24:AA24+Y36:AA36+Y48:AA48+Y60:AA60+Y72:AA72+Y84:AA84} -> 0 | AE92: Recebido Real | AF92: {=AF12:AH12+AF24:AH24+AF36:AH36+AF48:AH48+AF60:AH60+AF72:AH72+AF84:AH84} -> 0
C93: N° Total de Peças | D93: {=H10+H22+H34+H46+H58+H70+H82} -> 0 | J93: N° Total de Peças | K93: {=O10+O22+O34+O46+O58+O70+O82} -> 0 | Q93: N° Total de Peças | R93: {=V10+V22+V34+V46+V58+V70+V82} -> 0 | X93: N° Total de Peças | Y93: {=AC10+AC22+AC34+AC46+AC58+AC70+AC82} -> 0 | AE93: N° Total de Peças | AF93: {=AJ10+AJ22+AJ34+AJ46+AJ58+AJ70+AJ82} -> 0
C96: Faturamento por Loja na 1° Semana | J96: Faturamento por Loja na 2° Semana | Q96: Faturamento por Loja na 3° Semana | X96: Faturamento por Loja na 4° Semana | AE96: Faturamento por Loja na 4° 1/2 Semana
C97: Lojas | D97: Faturamento | E97: Não pago dia | F97: Recebimento | G97: Real da semana | H97: Peças | J97: Lojas | K97: Faturamento | L97: Não pago dia | M97: Recebimento | N97: Real da semana | O97: Peças | Q97: Lojas | R97: Faturamento | S97: Não pago dia | T97: Recebimento | U97: Real da semana | V97: Peças | X97: Lojas | Y97: Faturamento | Z97: Não pago dia | AA97: Recebimento | AB97: Real da semana | AC97: Peças | AE97: Lojas | AF97: Faturamento | AG97: Não pago dia | AH97: Recebimento | AI97: Real da semana | AJ97: Peças
C98: Lago Norte | D98: =D2+D14+D26+D38+D50+D62 -> 0 | E98: =E2+E14+E26+E38+E50+E62 -> 0 | F98: =F2+F14+F26+F38+F50+F62 -> 0 | G98: =F98-E98 -> 0 | H98: =H2+H14+H26+H38+H50+H62 -> 0 | J98: Lago Norte | K98: =K2+K14+K26+K38+K50+K62 -> 0 | L98: =L2+L14+L26+L38+L50+L62 -> 0 | M98: =M2+M14+M26+M38+M50+M62 -> 0 | N98: =M98-L98 -> 0 | O98: =O2+O14+O26+O38+O50+O62 -> 0 | Q98: Lago Norte | R98: =R2+R14+R26+R38+R50+R62 -> 0 | S98: =S2+S14+S26+S38+S50+S62 -> 0 | T98: =T2+T14+T26+T38+T50+T62 -> 0 | U98: =T98-S98 -> 0 | V98: =V2+V14+V26+V38+V50+V62 -> 0 | X98: Lago Norte | Y98: =Y2+Y14+Y26+Y38+Y50+Y62 -> 0 | Z98: =Z2+Z14+Z26+Z38+Z50+Z62 -> 0 | AA98: =AA2+AA14+AA26+AA38+AA50+AA62 -> 0 | AB98: =AA98-Z98 -> 0 | AC98: =AC2+AC14+AC26+AC38+AC50+AC62 -> 0 | AE98: Lago Norte | AF98: =AF2+AF14+AF26+AF38+AF50+AF62 -> 0 | AG98: =AG2+AG14+AG26+AG38+AG50+AG62 -> 0 | AH98: =AH2+AH14+AH26+AH38+AH50+AH62 -> 0 | AI98: =AH98-AG98 -> 0 | AJ98: =AJ2+AJ14+AJ26+AJ38+AJ50+AJ62 -> 0
C99: 202 Norte | D99: =D3+D15+D27+D39+D51+D63 -> 0 | E99: =E3+E15+E27+E39+E51+E63 -> 0 | F99: =F3+F15+F27+F39+F51+F63 -> 0 | G99: =F99-E99 -> 0 | H99: =H3+H15+H27+H39+H51+H63 -> 0 | J99: 202 Norte | K99: =K3+K15+K27+K39+K51+K63 -> 0 | L99: =L3+L15+L27+L39+L51+L63 -> 0 | M99: =M3+M15+M27+M39+M51+M63 -> 0 | N99: =M99-L99 -> 0 | O99: =O3+O15+O27+O39+O51+O63 -> 0 | Q99: 202 Norte | R99: =R3+R15+R27+R39+R51+R63 -> 0 | S99: =S3+S15+S27+S39+S51+S63 -> 0 | T99: =T3+T15+T27+T39+T51+T63 -> 0 | U99: =T99-S99 -> 0 | V99: =V3+V15+V27+V39+V51+V63 -> 0 | X99: 202 Norte | Y99: =Y3+Y15+Y27+Y39+Y51+Y63 -> 0 | Z99: =Z3+Z15+Z27+Z39+Z51+Z63 -> 0 | AA99: =AA3+AA15+AA27+AA39+AA51+AA63 -> 0 | AB99: =AA99-Z99 -> 0 | AC99: =AC3+AC15+AC27+AC39+AC51+AC63 -> 0 | AE99: 202 Norte | AF99: =AF3+AF15+AF27+AF39+AF51+AF63 -> 0 | AG99: =AG3+AG15+AG27+AG39+AG51+AG63 -> 0 | AH99: =AH3+AH15+AH27+AH39+AH51+AH63 -> 0 | AI99: =AH99-AG99 -> 0 | AJ99: =AJ3+AJ15+AJ27+AJ39+AJ51+AJ63 -> 0
C100: 213 Norte | D100: =D4+D16+D28+D40+D52+D64 -> 0 | E100: =E4+E16+E28+E40+E52+E64 -> 0 | F100: =F4+F16+F28+F40+F52+F64 -> 0 | G100: =F100-E100 -> 0 | H100: =H4+H16+H28+H40+H52+H64 -> 0 | J100: 213 Norte | K100: =K4+K16+K28+K40+K52+K64 -> 0 | L100: =L4+L16+L28+L40+L52+L64 -> 0 | M100: =M4+M16+M28+M40+M52+M64 -> 0 | N100: =M100-L100 -> 0 | O100: =O4+O16+O28+O40+O52+O64 -> 0 | Q100: 213 Norte | R100: =R4+R16+R28+R40+R52+R64 -> 0 | S100: =S4+S16+S28+S40+S52+S64 -> 0 | T100: =T4+T16+T28+T40+T52+T64 -> 0 | U100: =T100-S100 -> 0 | V100: =V4+V16+V28+V40+V52+V64 -> 0 | X100: 213 Norte | Y100: =Y4+Y16+Y28+Y40+Y52+Y64 -> 0 | Z100: =Z4+Z16+Z28+Z40+Z52+Z64 -> 0 | AA100: =AA4+AA16+AA28+AA40+AA52+AA64 -> 0 | AB100: =AA100-Z100 -> 0 | AC100: =AC4+AC16+AC28+AC40+AC52+AC64 -> 0 | AE100: 213 Norte | AF100: =AF4+AF16+AF28+AF40+AF52+AF64 -> 0 | AG100: =AG4+AG16+AG28+AG40+AG52+AG64 -> 0 | AH100: =AH4+AH16+AH28+AH40+AH52+AH64 -> 0 | AI100: =AH100-AG100 -> 0 | AJ100: =AJ4+AJ16+AJ28+AJ40+AJ52+AJ64 -> 0
C101: 307 Norte | D101: =D5+D17+D29+D41+D53+D65 -> 0 | E101: =E5+E17+E29+E41+E53+E65 -> 0 | F101: =F5+F17+F29+F41+F53+F65 -> 0 | G101: =F101-E101 -> 0 | H101: =H5+H17+H29+H41+H53+H65 -> 0 | J101: 307 Norte | K101: =K5+K17+K29+K41+K53+K65 -> 0 | L101: =L5+L17+L29+L41+L53+L65 -> 0 | M101: =M5+M17+M29+M41+M53+M65 -> 0 | N101: =M101-L101 -> 0 | O101: =O5+O17+O29+O41+O53+O65 -> 0 | Q101: 307 Norte | R101: =R5+R17+R29+R41+R53+R65 -> 0 | S101: =S5+S17+S29+S41+S53+S65 -> 0 | T101: =T5+T17+T29+T41+T53+T65 -> 0 | U101: =T101-S101 -> 0 | V101: =V5+V17+V29+V41+V53+V65 -> 0 | X101: 307 Norte | Y101: =Y5+Y17+Y29+Y41+Y53+Y65 -> 0 | Z101: =Z5+Z17+Z29+Z41+Z53+Z65 -> 0 | AA101: =AA5+AA17+AA29+AA41+AA53+AA65 -> 0 | AB101: =AA101-Z101 -> 0 | AC101: =AC5+AC17+AC29+AC41+AC53+AC65 -> 0 | AE101: 307 Norte | AF101: =AF5+AF17+AF29+AF41+AF53+AF65 -> 0 | AG101: =AG5+AG17+AG29+AG41+AG53+AG65 -> 0 | AH101: =AH5+AH17+AH29+AH41+AH53+AH65 -> 0 | AI101: =AH101-AG101 -> 0 | AJ101: =AJ5+AJ17+AJ29+AJ41+AJ53+AJ65 -> 0
C102: 313 Norte | D102: =D6+D18+D30+D42+D54+D66 -> 0 | E102: =E6+E18+E30+E42+E54+E66 -> 0 | F102: =F6+F18+F30+F42+F54+F66 -> 0 | G102: =F102-E102 -> 0 | H102: =H6+H18+H30+H42+H54+H66 -> 0 | J102: 313 Norte | K102: =K6+K18+K30+K42+K54+K66 -> 0 | L102: =L6+L18+L30+L42+L54+L66 -> 0 | M102: =M6+M18+M30+M42+M54+M66 -> 0 | N102: =M102-L102 -> 0 | O102: =O6+O18+O30+O42+O54+O66 -> 0 | Q102: 313 Norte | R102: =R6+R18+R30+R42+R54+R66 -> 0 | S102: =S6+S18+S30+S42+S54+S66 -> 0 | T102: =T6+T18+T30+T42+T54+T66 -> 0 | U102: =T102-S102 -> 0 | V102: =V6+V18+V30+V42+V54+V66 -> 0 | X102: 313 Norte | Y102: =Y6+Y18+Y30+Y42+Y54+Y66 -> 0 | Z102: =Z6+Z18+Z30+Z42+Z54+Z66 -> 0 | AA102: =AA6+AA18+AA30+AA42+AA54+AA66 -> 0 | AB102: =AA102-Z102 -> 0 | AC102: =AC6+AC18+AC30+AC42+AC54+AC66 -> 0 | AE102: 313 Norte | AF102: =AF6+AF18+AF30+AF42+AF54+AF66 -> 0 | AG102: =AG6+AG18+AG30+AG42+AG54+AG66 -> 0 | AH102: =AH6+AH18+AH30+AH42+AH54+AH66 -> 0 | AI102: =AH102-AG102 -> 0 | AJ102: =AJ6+AJ18+AJ30+AJ42+AJ54+AJ66 -> 0
C103: 314 Sul | D103: =D7+D19+D31+D43+D55+D67 -> 0 | E103: =E7+E19+E31+E43+E55+E67 -> 0 | F103: =F7+F19+F31+F43+F55+F67 -> 0 | G103: =F103-E103 -> 0 | H103: =H7+H19+H31+H43+H55+H67 -> 0 | J103: 314 Sul | K103: =K7+K19+K31+K43+K55+K67 -> 0 | L103: =L7+L19+L31+L43+L55+L67 -> 0 | M103: =M7+M19+M31+M43+M55+M67 -> 0 | N103: =M103-L103 -> 0 | O103: =O7+O19+O31+O43+O55+O67 -> 0 | Q103: 314 Sul | R103: =R7+R19+R31+R43+R55+R67 -> 0 | S103: =S7+S19+S31+S43+S55+S67 -> 0 | T103: =T7+T19+T31+T43+T55+T67 -> 0 | U103: =T103-S103 -> 0 | V103: =V7+V19+V31+V43+V55+V67 -> 0 | X103: 314 Sul | Y103: =Y7+Y19+Y31+Y43+Y55+Y67 -> 0 | Z103: =Z7+Z19+Z31+Z43+Z55+Z67 -> 0 | AA103: =AA7+AA19+AA31+AA43+AA55+AA67 -> 0 | AB103: =AA103-Z103 -> 0 | AC103: =AC7+AC19+AC31+AC43+AC55+AC67 -> 0 | AE103: 314 Sul | AF103: =AF7+AF19+AF31+AF43+AF55+AF67 -> 0 | AG103: =AG7+AG19+AG31+AG43+AG55+AG67 -> 0 | AH103: =AH7+AH19+AH31+AH43+AH55+AH67 -> 0 | AI103: =AH103-AG103 -> 0 | AJ103: =AJ7+AJ19+AJ31+AJ43+AJ55+AJ67 -> 0
C104: Sudoeste | D104: =D8+D20+D32+D44+D56+D68 -> 0 | E104: =E8+E20+E32+E44+E56+E68 -> 0 | F104: =F8+F20+F32+F44+F56+F68 -> 0 | G104: =F104-E104 -> 0 | H104: =H8+H20+H32+H44+H56+H68 -> 0 | J104: Sudoeste | K104: =K8+K20+K32+K44+K56+K68 -> 0 | L104: =L8+L20+L32+L44+L56+L68 -> 0 | M104: =M8+M20+M32+M44+M56+M68 -> 0 | N104: =M104-L104 -> 0 | O104: =O8+O20+O32+O44+O56+O68 -> 0 | Q104: Sudoeste | R104: =R8+R20+R32+R44+R56+R68 -> 0 | S104: =S8+S20+S32+S44+S56+S68 -> 0 | T104: =T8+T20+T32+T44+T56+T68 -> 0 | U104: =T104-S104 -> 0 | V104: =V8+V20+V32+V44+V56+V68 -> 0 | X104: Sudoeste | Y104: =Y8+Y20+Y32+Y44+Y56+Y68 -> 0 | Z104: =Z8+Z20+Z32+Z44+Z56+Z68 -> 0 | AA104: =AA8+AA20+AA32+AA44+AA56+AA68 -> 0 | AB104: =AA104-Z104 -> 0 | AC104: =AC8+AC20+AC32+AC44+AC56+AC68 -> 0 | AE104: Sudoeste | AF104: =AF8+AF20+AF32+AF44+AF56+AF68 -> 0 | AG104: =AG8+AG20+AG32+AG44+AG56+AG68 -> 0 | AH104: =AH8+AH20+AH32+AH44+AH56+AH68 -> 0 | AI104: =AH104-AG104 -> 0 | AJ104: =AJ8+AJ20+AJ32+AJ44+AJ56+AJ68 -> 0
...

Sheet Abr
B1: Dia | C1: Lojas | D1: Faturamento dia | E1: Não pago dia | F1: Recebido dia | G1: Não pago Acumulado | H1: Peças | I1: Dia | J1: Lojas | K1: Faturamento | L1: Não pago dia | M1: Recebido dia | N1: Não pago Acumulado | O1: Peças | P1: Dia | Q1: Lojas | R1: Faturamento | S1: Não pago dia | T1: Recebido dia | U1: Não pago Acumulado | V1: Peças | W1: Dia | X1: Lojas | Y1: Faturamento | Z1: Não pago dia | AA1: Recebido dia | AB1: Não pago Acumulado | AC1: Peças | AD1: Dia | AE1: Lojas | AF1: Faturamento | AG1: Não pago dia | AH1: Recebido dia | AI1: Não pago Acumulado | AJ1: Peças | AM1: Lojas | AN1: Faturamento | AO1: Não pago dia | AP1: Recebido | AQ1: Peças
A2: Segunda-feira | B2: 45747 | C2: Lago Norte | I2: 45754 | J2: Lago Norte | P2: 45761 | Q2: Lago Norte | W2: 45768 | X2: Lago Norte | AD2: 45775 | AL2: Faturamento Total das Segundas-feiras | AM2: Lago Norte | AN2: =D2+K2+R2+Y2+AF2 -> 0 | AO2: =E2+L2+S2+Z2+AG2 -> 0 | AP2: =F2+M2+T2+AA2+AH2 -> 0 | AQ2: =H2+O2+V2+AC2+AJ2 -> 0
C3: 202 Norte | J3: 202 Norte | Q3: 202 Norte | X3: 202 Norte | AM3: 202 Norte | AN3: =D3+K3+R3+Y3+AF3 -> 0 | AO3: =E3+L3+S3+Z3+AG3 -> 0 | AP3: =F3+M3+T3+AA3+AH3 -> 0 | AQ3: =H3+O3+V3+AC3+AJ3 -> 0
C4: 213 Norte | J4: 213 Norte | Q4: 213 Norte | X4: 213 Norte | AM4: 213 Norte | AN4: =D4+K4+R4+Y4+AF4 -> 0 | AO4: =E4+L4+S4+Z4+AG4 -> 0 | AP4: =F4+M4+T4+AA4+AH4 -> 0 | AQ4: =H4+O4+V4+AC4+AJ4 -> 0
C5: 307 Norte | J5: 307 Norte | Q5: 307 Norte | X5: 307 Norte | AM5: 307 Norte | AN5: =D5+K5+R5+Y5+AF5 -> 0 | AO5: =E5+L5+S5+Z5+AG5 -> 0 | AP5: =F5+M5+T5+AA5+AH5 -> 0 | AQ5: =H5+O5+V5+AC5+AJ5 -> 0
C6: 313 Norte | J6: 313 Norte | Q6: 313 Norte | X6: 313 Norte | AM6: 313 Norte | AN6: =D6+K6+R6+Y6+AF6 -> 0 | AO6: =E6+L6+S6+Z6+AG6 -> 0 | AP6: =F6+M6+T6+AA6+AH6 -> 0 | AQ6: =H6+O6+V6+AC6+AJ6 -> 0
C7: 314 Sul | J7: 314 Sul | Q7: 314 Sul | X7: 314 Sul | AM7: 314 Sul | AN7: =D7+K7+R7+Y7+AF7 -> 0 | AO7: =E7+L7+S7+Z7+AG7 -> 0 | AP7: =F7+M7+T7+AA7+AH7 -> 0 | AQ7: =H7+O7+V7+AC7+AJ7 -> 0
C8: Sudoeste | J8: Sudoeste | Q8: Sudoeste | X8: Sudoeste | AM8: Sudoeste | AN8: =D8+K8+R8+Y8+AF8 -> 0 | AO8: =E8+L8+S8+Z8+AG8 -> 0 | AP8: =F8+M8+T8+AA8+AH8 -> 0 | AQ8: =H8+O8+V8+AC8+AJ8 -> 0
C9: Noroeste | J9: Noroeste | Q9: Noroeste | X9: Noroeste | AM9: Noroeste | AN9: =D9+K9+R9+Y9+AF9 -> 0 | AO9: =E9+L9+S9+Z9+AG9 -> 0 | AP9: =F9+M9+T9+AA9+AH9 -> 0 | AQ9: =H9+O9+V9+AC9+AJ9 -> 0
C10: Total: | D10: =D2+D3+D4+D5+D6+D7+D8+D9 -> 0 | E10: =E2+E3+E4+E5+E6+E7+E8+E9 -> 0 | F10: =F2+F3+F4+F5+F6+F7+F8+F9 -> 0 | G10: =G2+G3+G4+G5+G6+G7+G8+G9 -> 0 | H10: =H2+H3+H4+H5+H6+H7+H8+H9 -> 0 | J10: Total: | K10: =K2+K3+K4+K5+K6+K7+K8+K9 -> 0 | L10: =L2+L3+L4+L5+L6+L7+L8+L9 -> 0 | M10: =M2+M3+M4+M5+M6+M7+M8+M9 -> 0 | N10: =N2+N3+N4+N5+N6+N7+N8+N9 -> 0 | O10: =O2+O3+O4+O5+O6+O7+O8+O9 -> 0 | Q10: Total: | R10: =R2+R3+R4+R5+R6+R7+R8+R9 -> 0 | S10: =S2+S3+S4+S5+S6+S7+S8+S9 -> 0 | T10: =T2+T3+T4+T5+T6+T7+T8+T9 -> 0 | U10: =U2+U3+U4+U5+U6+U7+U8+U9 -> 0 | V10: =V2+V3+V4+V5+V6+V7+V8+V9 -> 0 | X10: Total: | Y10: =Y2+Y3+Y4+Y5+Y6+Y7+Y8+Y9 -> 0 | Z10: =Z2+Z3+Z4+Z5+Z6+Z7+Z8+Z9 -> 0 | AA10: =AA2+AA3+AA4+AA5+AA6+AA7+AA8+AA9 -> 0 | AB10: =AB2+AB3+AB4+AB5+AB6+AB7+AB8+AB9 -> 0 | AC10: =AC2+AC3+AC4+AC5+AC6+AC7+AC8+AC9 -> 0 | AE10: Total: | AF10: =AF2+AF3+AF4+AF5+AF6+AF7+AF8+AF9 -> 0 | AG10: =AG2+AG3+AG4+AG5+AG6+AG7+AG8+AG9 -> 0 | AH10: =AH2+AH3+AH4+AH5+AH6+AH7+AH8+AH9 -> 0 | AI10: =AI2+AI3+AI4+AI5+AI6+AI7+AI8+AI9 -> 0 | AJ10: =AJ2+AJ3+AJ4+AJ5+AJ6+AJ7+AJ8+AJ9 -> 0 | AM10: Total: | AN10: =AN2+AN3+AN4+AN5+AN6+AN7+AN8+AN9 -> 0 | AO10: =AO2+AO3+AO4+AO5+AO6+AO7+AO8+AO9 -> 0 | AP10: =AP2+AP3+AP4+AP5+AP6+AP7+AP8+AP9 -> 0 | AQ10: =AQ2+AQ3+AQ4+AQ5+AQ6+AQ7+AQ8+AQ9 -> 0
C11: Faturado dia real | D11: =D10-E10 -> 0 | J11: Faturado dia real | K11: =K10-L10 -> 0 | Q11: Faturado dia real | R11: =R10-S10 -> 0 | X11: Faturado dia real | Y11: =Y10-Z10 -> 0 | AE11: Faturado dia real | AF11: =AF10-AG10 -> 0 | AM11: Fat. Real | AN11: =AN10-AO10 -> 0
C12: Recebido dia real | D12: =F10-E10 -> 0 | J12: Recebido dia real | K12: =M10-L10 -> 0 | Q12: Recebido dia real | R12: =T10-S10 -> 0 | X12: Recebido dia real | Y12: =AA10-Z10 -> 0 | AE12: Recebido dia real | AF12: =AH10-AG10 -> 0
B13: Dia | C13: Lojas | D13: Faturamento dia | E13: Não pago dia | F13: Recebido dia | G13: Não pago Acumulado | H13: Peças | I13: Dia | J13: Lojas | K13: Faturamento | L13: Não pago dia | M13: Recebido dia | N13: Não pago Acumulado | O13: Peças | P13: Dia | Q13: Lojas | R13: Faturamento | S13: Não pago dia | T13: Recebido dia | U13: Não pago Acumulado | V13: Peças | W13: Dia | X13: Lojas | Y13: Faturamento | Z13: Não pago dia | AA13: Recebido dia | AB13: Não pago Acumulado | AC13: Peças | AD13: Dia | AE13: Lojas | AF13: Faturamento | AG13: Não pago dia | AH13: Recebido dia | AI13: Não pago Acumulado | AJ13: Peças | AM13: Lojas | AN13: Faturamento | AO13: Não pago dia | AP13: Recebido | AQ13: Peças
A14: Terça-feira | B14: 45748 | C14: Lago Norte | I14: 45755 | J14: Lago Norte | P14: 45762 | Q14: Lago Norte | W14: 45769 | X14: Lago Norte | AD14: 45776 | AE14: Lago Norte | AL14: Faturamento Total das Terças-feiras | AM14: Lago Norte | AN14: =D14+K14+R14+Y14+AF14 -> 0 | AO14: =E14+L14+S14+Z14+AG14 -> 0 | AP14: =F14+M14+T14+AA14+AH14 -> 0 | AQ14: =H14+O14+V14+AC14+AJ14 -> 0
C15: 202 Norte | J15: 202 Norte | Q15: 202 Norte | X15: 202 Norte | AE15: 202 Norte | AM15: 202 Norte | AN15: =D15+K15+R15+Y15+AF15 -> 0 | AO15: =E15+L15+S15+Z15+AG15 -> 0 | AP15: =F15+M15+T15+AA15+AH15 -> 0 | AQ15: =H15+O15+V15+AC15+AJ15 -> 0
C16: 213 Norte | J16: 213 Norte | Q16: 213 Norte | X16: 213 Norte | AE16: 213 Norte | AM16: 213 Norte | AN16: =D16+K16+R16+Y16+AF16 -> 0 | AO16: =E16+L16+S16+Z16+AG16 -> 0 | AP16: =F16+M16+T16+AA16+AH16 -> 0 | AQ16: =H16+O16+V16+AC16+AJ16 -> 0
C17: 307 Norte | J17: 307 Norte | Q17: 307 Norte | X17: 307 Norte | AE17: 307 Norte | AM17: 307 Norte | AN17: =D17+K17+R17+Y17+AF17 -> 0 | AO17: =E17+L17+S17+Z17+AG17 -> 0 | AP17: =F17+M17+T17+AA17+AH17 -> 0 | AQ17: =H17+O17+V17+AC17+AJ17 -> 0
C18: 313 Norte | J18: 313 Norte | Q18: 313 Norte | X18: 313 Norte | AE18: 313 Norte | AM18: 313 Norte | AN18: =D18+K18+R18+Y18+AF18 -> 0 | AO18: =E18+L18+S18+Z18+AG18 -> 0 | AP18: =F18+M18+T18+AA18+AH18 -> 0 | AQ18: =H18+O18+V18+AC18+AJ18 -> 0
C19: 314 Sul | J19: 314 Sul | Q19: 314 Sul | X19: 314 Sul | AE19: 314 Sul | AM19: 314 Sul | AN19: =D19+K19+R19+Y19+AF19 -> 0 | AO19: =E19+L19+S19+Z19+AG19 -> 0 | AP19: =F19+M19+T19+AA19+AH19 -> 0 | AQ19: =H19+O19+V19+AC19+AJ19 -> 0
C20: Sudoeste | J20: Sudoeste | Q20: Sudoeste | X20: Sudoeste | AE20: Sudoeste | AM20: Sudoeste | AN20: =D20+K20+R20+Y20+AF20 -> 0 | AO20: =E20+L20+S20+Z20+AG20 -> 0 | AP20: =F20+M20+T20+AA20+AH20 -> 0 | AQ20: =H20+O20+V20+AC20+AJ20 -> 0
C21: Noroeste | J21: Noroeste | Q21: Noroeste | X21: Noroeste | AE21: Noroeste | AM21: Noroeste | AN21: =D21+K21+R21+Y21+AF21 -> 0 | AO21: =E21+L21+S21+Z21+AG21 -> 0 | AP21: =F21+M21+T21+AA21+AH21 -> 0 | AQ21: =H21+O21+V21+AC21+AJ21 -> 0
C22: Total: | D22: =D14+D15+D16+D17+D18+D19+D20+D21 -> 0 | E22: =E14+E15+E16+E17+E18+E19+E20+E21 -> 0 | F22: =F14+F15+F16+F17+F18+F19+F20+F21 -> 0 | G22: =G14+G15+G16+G17+G18+G19+G20+G21 -> 0 | H22: =H14+H15+H16+H17+H18+H19+H20+H21 -> 0 | J22: Total: | K22: =K14+K15+K16+K17+K18+K19+K20+K21 -> 0 | L22: =L14+L15+L16+L17+L18+L19+L20+L21 -> 0 | M22: =M14+M15+M16+M17+M18+M19+M20+M21 -> 0 | N22: =N14+N15+N16+N17+N18+N19+N20+N21 -> 0 | O22: =O14+O15+O16+O17+O18+O19+O20+O21 -> 0 | Q22: Total: | R22: =R14+R15+R16+R17+R18+R19+R20+R21 -> 0 | S22: =S14+S15+S16+S17+S18+S19+S20+S21 -> 0 | T22: =T14+T15+T16+T17+T18+T19+T20+T21 -> 0 | U22: =U14+U15+U16+U17+U18+U19+U20+U21 -> 0 | V22: =V14+V15+V16+V17+V18+V19+V20+V21 -> 0 | X22: Total: | AE22: Total: | AF22: =AF14+AF15+AF16+AF17+AF18+AF19+AF20+AF21 -> 0 | AG22: =AG14+AG15+AG16+AG17+AG18+AG19+AG20+AG21 -> 0 | AH22: =AH14+AH15+AH16+AH17+AH18+AH19+AH20+AH21 -> 0 | AI22: =AI14+AI15+AI16+AI17+AI18+AI19+AI20+AI21 -> 0 | AJ22: =AJ14+AJ15+AJ16+AJ17+AJ18+AJ19+AJ20+AJ21 -> 0 | AM22: Total: | AN22: =AN14+AN15+AN16+AN17+AN18+AN19+AN20+AN21 -> 0 | AO22: =AO14+AO15+AO16+AO17+AO18+AO19+AO20+AO21 -> 0 | AP22: =AP14+AP15+AP16+AP17+AP18+AP19+AP20+AP21 -> 0 | AQ22: =AQ14+AQ15+AQ16+AQ17+AQ18+AQ19+AQ20+AQ21 -> 0
C23: Faturado dia real | D23: =D22-E22 -> 0 | J23: Faturado dia real | K23: =K22-L22 -> 0 | Q23: Faturado dia real | R23: =R22-S22 -> 0 | X23: Faturado dia real | Y23: =Y22-Z22 -> 0 | AE23: Faturado dia real | AF23: =AF22-AG22 -> 0 | AM23: Fat. Real | AN23: =AN22-AO22 -> 0
C24: Recebido dia real | D24: =F22-E22 -> 0 | J24: Recebido dia real | K24: =M22-L22 -> 0 | Q24: Recebido dia real | R24: =T22-S22 -> 0 | X24: Recebido dia real | Y24: =AA22-Z22 -> 0 | AE24: Recebido dia real | AF24: =AH22-AG22 -> 0
B25: Dia | C25: Lojas | D25: Faturamento dia | E25: Não pago dia | F25: Recebido dia | G25: Não pago Acumulado | H25: Peças | I25: Dia | J25: Lojas | K25: Faturamento | L25: Não pago dia | M25: Recebido dia | N25: Não pago Acumulado | O25: Peças | P25: Dia | Q25: Lojas | R25: Faturamento | S25: Não pago dia | T25: Recebido dia | U25: Não pago Acumulado | V25: Peças | W25: Dia | X25: Lojas | Y25: Faturamento | Z25: Não pago dia | AA25: Recebido dia | AB25: Não pago Acumulado | AC25: Peças | AD25: Dia | AE25: Lojas | AF25: Faturamento | AG25: Não pago dia | AH25: Recebido dia | AI25: Não pago Acumulado | AJ25: Peças | AM25: Lojas | AN25: Faturamento | AO25: Não pago dia | AP25: Recebido | AQ25: Peças
A26: Quarta-feira | B26: 45749 | C26: Lago Norte | I26: 45756 | J26: Lago Norte | P26: 45763 | Q26: Lago Norte | W26: 45770 | X26: Lago Norte | AD26: 45777 | AE26: Lago Norte | AL26: Faturamento Total das Quartas-feiras | AM26: Lago Norte | AN26: =D26+K26+R26+Y26+AF26 -> 0 | AO26: =E26+L26+S26+Z26+AG26 -> 0 | AP26: =F26+M26+T26+AA26+AH26 -> 0 | AQ26: =H26+O26+V26+AC26+AJ26 -> 0
C27: 202 Norte | J27: 202 Norte | Q27: 202 Norte | X27: 202 Norte | AE27: 202 Norte | AM27: 202 Norte | AN27: =D27+K27+R27+Y27+AF27 -> 0 | AO27: =E27+L27+S27+Z27+AG27 -> 0 | AP27: =F27+M27+T27+AA27+AH27 -> 0 | AQ27: =H27+O27+V27+AC27+AJ27 -> 0
C28: 213 Norte | J28: 213 Norte | Q28: 213 Norte | X28: 213 Norte | AE28: 213 Norte | AM28: 213 Norte | AN28: =D28+K28+R28+Y28+AF28 -> 0 | AO28: =E28+L28+S28+Z28+AG28 -> 0 | AP28: =F28+M28+T28+AA28+AH28 -> 0 | AQ28: =H28+O28+V28+AC28+AJ28 -> 0
C29: 307 Norte | J29: 307 Norte | Q29: 307 Norte | X29: 307 Norte | AE29: 307 Norte | AM29: 307 Norte | AN29: =D29+K29+R29+Y29+AF29 -> 0 | AO29: =E29+L29+S29+Z29+AG29 -> 0 | AP29: =F29+M29+T29+AA29+AH29 -> 0 | AQ29: =H29+O29+V29+AC29+AJ29 -> 0
C30: 313 Norte | J30: 313 Norte | Q30: 313 Norte | X30: 313 Norte | AE30: 313 Norte | AM30: 313 Norte | AN30: =D30+K30+R30+Y30+AF30 -> 0 | AO30: =E30+L30+S30+Z30+AG30 -> 0 | AP30: =F30+M30+T30+AA30+AH30 -> 0 | AQ30: =H30+O30+V30+AC30+AJ30 -> 0
C31: 314 Sul | J31: 314 Sul | Q31: 314 Sul | X31: 314 Sul | AE31: 314 Sul | AM31: 314 Sul | AN31: =D31+K31+R31+Y31+AF31 -> 0 | AO31: =E31+L31+S31+Z31+AG31 -> 0 | AP31: =F31+M31+T31+AA31+AH31 -> 0 | AQ31: =H31+O31+V31+AC31+AJ31 -> 0
C32: Sudoeste | J32: Sudoeste | Q32: Sudoeste | X32: Sudoeste | AE32: Sudoeste | AM32: Sudoeste | AN32: =D32+K32+R32+Y32+AF32 -> 0 | AO32: =E32+L32+S32+Z32+AG32 -> 0 | AP32: =F32+M32+T32+AA32+AH32 -> 0 | AQ32: =H32+O32+V32+AC32+AJ32 -> 0
C33: Noroeste | J33: Noroeste | Q33: Noroeste | X33: Noroeste | AE33: Noroeste | AM33: Noroeste | AN33: =D33+K33+R33+Y33+AF33 -> 0 | AO33: =E33+L33+S33+Z33+AG33 -> 0 | AP33: =F33+M33+T33+AA33+AH33 -> 0 | AQ33: =H33+O33+V33+AC33+AJ33 -> 0
C34: Total: | D34: =D26+D27+D28+D29+D30+D31+D32+D33 -> 0 | E34: =E26+E27+E28+E29+E30+E31+E32+E33 -> 0 | F34: =F26+F27+F28+F29+F30+F31+F32+F33 -> 0 | G34: =G26+G27+G28+G29+G30+G31+G32+G33 -> 0 | H34: =H26+H27+H28+H29+H30+H31+H32+H33 -> 0 | J34: Total: | K34: =K26+K27+K28+K29+K30+K31+K32+K33 -> 0 | L34: =L26+L27+L28+L29+L30+L31+L32+L33 -> 0 | M34: =M26+M27+M28+M29+M30+M31+M32+M33 -> 0 | N34: =N26+N27+N28+N29+N30+N31+N32+N33 -> 0 | O34: =O26+O27+O28+O29+O30+O31+O32+O33 -> 0 | Q34: Total: | R34: =R26+R27+R28+R29+R30+R31+R32+R33 -> 0 | S34: =S26+S27+S28+S29+S30+S31+S32+S33 -> 0 | T34: =T26+T27+T28+T29+T30+T31+T32+T33 -> 0 | U34: =U26+U27+U28+U29+U30+U31+U32+U33 -> 0 | V34: =V26+V27+V28+V29+V30+V31+V32+V33 -> 0 | X34: Total: | Y34: =Y26+Y27+Y28+Y29+Y30+Y31+Y32+Y33 -> 0 | Z34: =Z26+Z27+Z28+Z29+Z30+Z31+Z32+Z33 -> 0 | AA34: =AA26+AA27+AA28+AA29+AA30+AA31+AA32+AA33 -> 0 | AB34: =AB26+AB27+AB28+AB29+AB30+AB31+AB32+AB33 -> 0 | AC34: =AC26+AC27+AC28+AC29+AC30+AC31+AC32+AC33 -> 0 | AE34: Total: | AF34: =AF26+AF27+AF28+AF29+AF30+AF31+AF32+AF33 -> 0 | AG34: =AG26+AG27+AG28+AG29+AG30+AG31+AG32+AG33 -> 0 | AH34: =AH26+AH27+AH28+AH29+AH30+AH31+AH32+AH33 -> 0 | AI34: =AI26+AI27+AI28+AI29+AI30+AI31+AI32+AI33 -> 0 | AJ34: =AJ26+AJ27+AJ28+AJ29+AJ30+AJ31+AJ32+AJ33 -> 0 | AM34: Total: | AN34: =AN26+AN27+AN28+AN29+AN30+AN31+AN32+AN33 -> 0 | AO34: =AO26+AO27+AO28+AO29+AO30+AO31+AO32+AO33 -> 0 | AP34: =AP26+AP27+AP28+AP29+AP30+AP31+AP32+AP33 -> 0 | AQ34: =AQ26+AQ27+AQ28+AQ29+AQ30+AQ31+AQ32+AQ33 -> 0
C35: Faturado dia real | D35: =D34-E34 -> 0 | J35: Faturado dia real | K35: =K34-L34 -> 0 | Q35: Faturado dia real | R35: =R34-S34 -> 0 | X35: Faturado dia real | Y35: =Y34-Z34 -> 0 | AE35: Faturado dia real | AF35: =AF34-AG34 -> 0 | AM35: Fat. Real | AN35: =AN34-AO34 -> 0
C36: Recebido dia real | D36: =F34-E34 -> 0 | J36: Recebido dia real | K36: =M34-L34 -> 0 | Q36: Recebido dia real | R36: =T34-S34 -> 0 | X36: Recebido dia real | Y36: =AA34-Z34 -> 0 | AE36: Recebido dia real | AF36: =AH34-AG34 -> 0
B37: Dia | C37: Lojas | D37: Faturamento dia | E37: Não pago dia | F37: Recebido dia | G37: Não pago Acumulado | H37: Peças | I37: Dia | J37: Lojas | K37: Faturamento | L37: Não pago dia | M37: Recebido dia | N37: Não pago Acumulado | O37: Peças | P37: Dia | Q37: Lojas | R37: Faturamento | S37: Não pago dia | T37: Recebido dia | U37: Não pago Acumulado | V37: Peças | W37: Dia | X37: Lojas | Y37: Faturamento | Z37: Não pago dia | AA37: Recebido dia | AB37: Não pago Acumulado | AC37: Peças | AD37: Dia | AE37: Lojas | AF37: Faturamento | AG37: Não pago dia | AH37: Recebido dia | AI37: Não pago Acumulado | AJ37: Peças | AM37: Lojas | AN37: Faturamento | AO37: Não pago dia | AP37: Recebido | AQ37: Peças
A38: Quinta-feira | B38: 45750 | C38: Lago Norte | I38: 45757 | J38: Lago Norte | P38: 45764 | Q38: Lago Norte | W38: 45771 | X38: Lago Norte | AE38: Lago Norte | AL38: Faturamento Total das Quintas-feiras | AM38: Lago Norte | AN38: =D38+K38+R38+Y38+AF38 -> 0 | AO38: =E38+L38+S38+Z38+AG38 -> 0 | AP38: =F38+M38+T38+AA38+AH38 -> 0 | AQ38: =H38+O38+V38+AC38+AJ38 -> 0
C39: 202 Norte | J39: 202 Norte | Q39: 202 Norte | X39: 202 Norte | AE39: 202 Norte | AM39: 202 Norte | AN39: =D39+K39+R39+Y39+AF39 -> 0 | AO39: =E39+L39+S39+Z39+AG39 -> 0 | AP39: =F39+M39+T39+AA39+AH39 -> 0 | AQ39: =H39+O39+V39+AC39+AJ39 -> 0
C40: 213 Norte | J40: 213 Norte | Q40: 213 Norte | X40: 213 Norte | AE40: 213 Norte | AM40: 213 Norte | AN40: =D40+K40+R40+Y40+AF40 -> 0 | AO40: =E40+L40+S40+Z40+AG40 -> 0 | AP40: =F40+M40+T40+AA40+AH40 -> 0 | AQ40: =H40+O40+V40+AC40+AJ40 -> 0
C41: 307 Norte | J41: 307 Norte | Q41: 307 Norte | X41: 307 Norte | AE41: 307 Norte | AM41: 307 Norte | AN41: =D41+K41+R41+Y41+AF41 -> 0 | AO41: =E41+L41+S41+Z41+AG41 -> 0 | AP41: =F41+M41+T41+AA41+AH41 -> 0 | AQ41: =H41+O41+V41+AC41+AJ41 -> 0
C42: 313 Norte | J42: 313 Norte | Q42: 313 Norte | X42: 313 Norte | AE42: 313 Norte | AM42: 313 Norte | AN42: =D42+K42+R42+Y42+AF42 -> 0 | AO42: =E42+L42+S42+Z42+AG42 -> 0 | AP42: =F42+M42+T42+AA42+AH42 -> 0 | AQ42: =H42+O42+V42+AC42+AJ42 -> 0
C43: 314 Sul | J43: 314 Sul | Q43: 314 Sul | X43: 314 Sul | AE43: 314 Sul | AM43: 314 Sul | AN43: =D43+K43+R43+Y43+AF43 -> 0 | AO43: =E43+L43+S43+Z43+AG43 -> 0 | AP43: =F43+M43+T43+AA43+AH43 -> 0 | AQ43: =H43+O43+V43+AC43+AJ43 -> 0
C44: Sudoeste | J44: Sudoeste | Q44: Sudoeste | X44: Sudoeste | AE44: Sudoeste | AM44: Sudoeste | AN44: =D44+K44+R44+Y44+AF44 -> 0 | AO44: =E44+L44+S44+Z44+AG44 -> 0 | AP44: =F44+M44+T44+AA44+AH44 -> 0 | AQ44: =H44+O44+V44+AC44+AJ44 -> 0
C45: Noroeste | J45: Noroeste | Q45: Noroeste | X45: Noroeste | AE45: Noroeste | AM45: Noroeste | AN45: =D45+K45+R45+Y45+AF45 -> 0 | AO45: =E45+L45+S45+Z45+AG45 -> 0 | AP45: =F45+M45+T45+AA45+AH45 -> 0 | AQ45: =H45+O45+V45+AC45+AJ45 -> 0
C46: Total: | D46: =D38+D39+D40+D41+D42+D43+D44+D45 -> 0 | E46: =E38+E39+E40+E41+E42+E43+E44+E45 -> 0 | F46: =F38+F39+F40+F41+F42+F43+F44+F45 -> 0 | G46: =G38+G39+G40+G41+G42+G43+G44+G45 -> 0 | H46: =H38+H39+H40+H41+H42+H43+H44+H45 -> 0 | J46: Total: | K46: =K38+K39+K40+K41+K42+K43+K44+K45 -> 0 | L46: =L38+L39+L40+L41+L42+L43+L44+L45 -> 0 | M46: =M38+M39+M40+M41+M42+M43+M44+M45 -> 0 | N46: =N38+N39+N40+N41+N42+N43+N44+N45 -> 0 | O46: =O38+O39+O40+O41+O42+O43+O44+O45 -> 0 | Q46: Total: | R46: =R38+R39+R40+R41+R42+R43+R44+R45 -> 0 | S46: =S38+S39+S40+S41+S42+S43+S44+S45 -> 0 | T46: =T38+T39+T40+T41+T42+T43+T44+T45 -> 0 | U46: =U38+U39+U40+U41+U42+U43+U44+U45 -> 0 | V46: =V38+V39+V40+V41+V42+V43+V44+V45 -> 0 | X46: Total: | Y46: =Y38+Y39+Y40+Y41+Y42+Y43+Y44+Y45 -> 0 | Z46: =Z38+Z39+Z40+Z41+Z42+Z43+Z44+Z45 -> 0 | AA46: =AA38+AA39+AA40+AA41+AA42+AA43+AA44+AA45 -> 0 | AB46: =AB38+AB39+AB40+AB41+AB42+AB43+AB44+AB45 -> 0 | AC46: =AC38+AC39+AC40+AC41+AC42+AC43+AC44+AC45 -> 0 | AE46: Total: | AF46: =AF38+AF39+AF40+AF41+AF42+AF43+AF44+AF45 -> 0 | AG46: =AG38+AG39+AG40+AG41+AG42+AG43+AG44+AG45 -> 0 | AH46: =AH38+AH39+AH40+AH41+AH42+AH43+AH44+AH45 -> 0 | AI46: =AI38+AI39+AI40+AI41+AI42+AI43+AI44+AI45 -> 0 | AJ46: =AJ38+AJ39+AJ40+AJ41+AJ42+AJ43+AJ44+AJ45 -> 0 | AM46: Total: | AN46: =AN38+AN39+AN40+AN41+AN42+AN43+AN44+AN45 -> 0 | AO46: =AO38+AO39+AO40+AO41+AO42+AO43+AO44+AO45 -> 0 | AP46: =AP38+AP39+AP40+AP41+AP42+AP43+AP44+AP45 -> 0 | AQ46: =AQ38+AQ39+AQ40+AQ41+AQ42+AQ43+AQ44+AQ45 -> 0
C47: Faturado dia real | D47: =D46-E46 -> 0 | J47: Faturado dia real | K47: =K46-L46 -> 0 | Q47: Faturado dia real | R47: =R46-S46 -> 0 | X47: Faturado dia real | Y47: =Y46-Z46 -> 0 | AE47: Faturado dia real | AF47: =AF46-AG46 -> 0 | AM47: Fat. Real | AN47: =AN46-AO46 -> 0
C48: Recebido dia real | D48: =F46-E46 -> 0 | J48: Recebido dia real | K48: =M46-L46 -> 0 | Q48: Recebido dia real | R48: =T46-S46 -> 0 | X48: Recebido dia real | Y48: =AA46-Z46 -> 0 | AE48: Recebido dia real | AF48: =AH46-AG46 -> 0
B49: Dia | C49: Lojas | D49: Faturamento dia | E49: Não pago dia | F49: Recebido dia | G49: Não pago Acumulado | H49: Peças | I49: Dia | J49: Lojas | K49: Faturamento | L49: Não pago dia | M49: Recebido dia | N49: Não pago Acumulado | O49: Peças | P49: Dia | Q49: Lojas | R49: Faturamento | S49: Não pago dia | T49: Recebido dia | U49: Não pago Acumulado | V49: Peças | W49: Dia | X49: Lojas | Y49: Faturamento | Z49: Não pago dia | AA49: Recebido dia | AB49: Não pago Acumulado | AC49: Peças | AD49: Dia | AE49: Lojas | AF49: Faturamento | AG49: Não pago dia | AH49: Recebido dia | AI49: Não pago Acumulado | AJ49: Peças | AM49: Lojas | AN49: Faturamento | AO49: Não pago dia | AP49: Recebido | AQ49: Peças
A50: Sexta-feira | B50: 45751 | C50: Lago Norte | I50: 45758 | J50: Lago Norte | P50: 18/04/2025 - Feriado | Q50: Lago Norte | W50: 45802 | X50: Lago Norte | AE50: Lago Norte | AL50: Faturamento Total das Sextas-feiras | AM50: Lago Norte | AN50: =D50+K50+R50+Y50+AF50 -> 0 | AO50: =E50+L50+S50+Z50+AG50 -> 0 | AP50: =F50+M50+T50+AA50+AH50 -> 0 | AQ50: =H50+O50+V50+AC50+AJ50 -> 0
C51: 202 Norte | J51: 202 Norte | Q51: 202 Norte | X51: 202 Norte | AE51: 202 Norte | AM51: 202 Norte | AN51: =D51+K51+R51+Y51+AF51 -> 0 | AO51: =E51+L51+S51+Z51+AG51 -> 0 | AP51: =F51+M51+T51+AA51+AH51 -> 0 | AQ51: =H51+O51+V51+AC51+AJ51 -> 0
C52: 213 Norte | J52: 213 Norte | Q52: 213 Norte | X52: 213 Norte | AE52: 213 Norte | AM52: 213 Norte | AN52: =D52+K52+R52+Y52+AF52 -> 0 | AO52: =E52+L52+S52+Z52+AG52 -> 0 | AP52: =F52+M52+T52+AA52+AH52 -> 0 | AQ52: =H52+O52+V52+AC52+AJ52 -> 0
C53: 307 Norte | J53: 307 Norte | Q53: 307 Norte | X53: 307 Norte | AE53: 307 Norte | AM53: 307 Norte | AN53: =D53+K53+R53+Y53+AF53 -> 0 | AO53: =E53+L53+S53+Z53+AG53 -> 0 | AP53: =F53+M53+T53+AA53+AH53 -> 0 | AQ53: =H53+O53+V53+AC53+AJ53 -> 0
C54: 313 Norte | J54: 313 Norte | Q54: 313 Norte | X54: 313 Norte | AE54: 313 Norte | AM54: 313 Norte | AN54: =D54+K54+R54+Y54+AF54 -> 0 | AO54: =E54+L54+S54+Z54+AG54 -> 0 | AP54: =F54+M54+T54+AA54+AH54 -> 0 | AQ54: =H54+O54+V54+AC54+AJ54 -> 0
